Workbook

Sheet LIST
A1: NICTHS: 2019 and 2024
A2: List of Tables
A4: Items | B4: Respondent | C4: Table Number | D4: Table
A5: Profile | B5: Household | C5: 1 | D5: Estimated Number of Households
A6: Profile | B6: Individuals | C6: 2 | D6: Estimated Number of Individuals
A7: Profile | B7: Individuals | C7: 2a | D7: Estimated Number of Individuals by Sex and Region
A8: Cellphone | B8: Household | C8: 3 | D8: Households with Access to Communal or Shared Cellphone by any Household Member at Any Time
A9: Cellphone | B9: Household | C9: 4 | D9: Households with Cellphone That Can be Used by Any Household Member at Any Time by Type of Cellphone
A10: Cellphone | B10: Individuals | C10: 5 | D10: Individuals Who Used Cellphone
A11: Cellphone | B11: Individuals | C11: 6 | D11: Individuals Who Own Cellphone
A12: Cellphone | B12: Individuals | C12: 6 | D12: Cellphone Owners by Type of Cellphone
A13: Cellphone | B13: Individuals | C13: 7 | D13: Cellphone Owners by Type of SIM Used
A14: SIM Registration | B14: Individuals | C14: 8 | D14: Individuals with ICT Device and Active SIM by Details Used in SIM Registration
A15: SIM Registration | B15: Individuals | C15: 9 | D15: Individuals with ICT Device and Active SIM Who Did Not Use Own Information in SIM Registration by Main Reason
A16: SIM Registration | B16: Individuals | C16: 10 | D16: Individuals with ICT Device, Active SIM and Registered SIM by Main Difficulty Encountered
A17: SIM Registration | B17: Individuals | C17: 11 | D17: Individual Average Monthly Spending on Load or Subscription
A18: Computer | B18: Household | C18: 12 | D18: Households with Computer That Can be Used by Any Household Member at Any Time
A19: Computer | B19: Household | C19: 13 | D19: Households with Computer That Can be Used by Any Household Member at Any Time by Type
A20: Computer | B20: Household | C20: 14 | D20: Households Accessing a Computer By Alternative Access Method
A21: Computer | B21: Individuals | C21: 15 | D21: Individuals Using a Computer
A22: Computer | B22: Individuals | C22: 15 | D22: Computer Users by Type
A23: Computer | B23: Individuals | C23: 16 | D23: Individuals Using Computer by Activity
A24: Internet | B24: Household | C24: 17 | D24: Households With/Have Access to the Internet
A25: Internet | B25: Household | C25: 18 | D25: Households with Internet by Usage of Internet
A26: Internet | B26: Household | C26: 19 | D26: Households Average Monthly Spending on Internet
A27: Internet | B27: Individuals | C27: 20 | D27: Individuals Using the Internet
A28: Internet | B28: Individuals | C28: 20 | D28: Individuals Using the Internet by Type of Device Used
A29: Internet | B29: Individuals | C29: 21 | D29: Individuals Using the Internet by Access Location
A30: Internet | B30: Individuals | C30: 22 | D30: Individuals Using the Internet by Frequency
A31: Internet | B31: Individuals | C31: 23 | D31: Top 5 Purposes for Using the Internet by Individuals
A32: Internet | B32: Household | C32: 24 | D32: Top 5 Barriers for Not Having Internet Connection at Home in 2024
A33: Internet | B33: Individuals | C33: 25 | D33: Top 5 Barriers to Internet Access in 2024 by Individuals
A34: Television | B34: Household | C34: 26 | D34: Households Access to Television
A35: Television | B35: Household | C35: 27 | D35: Households Access to Television by Type
A36: Digital Economy/E-Commerce | B36: Individuals | C36: 28 | D36: individuals Who Have Online Bank Account
A37: Digital Economy/E-Commerce | B37: Individuals | C37: 28 | D37: Individuals with an ICT Device and an Active SIM Who Have Electronic/Mobile Money Account
A38: Digital Economy/E-Commerce | B38: Individuals | C38: 29 | D38: Individuals Who Have Electronic/Mobile Money Account
A39: Digital Economy/E-Commerce | B39: Individuals | C39: 30 | D39: Individuals Who are Engaged in Online Activities to Earn Money by Type of Activity
A40: Digital Economy/E-Commerce | B40: Individuals | C40: 28 | D40: Individuals Who have an Online Buying or Online Selling Accounts
A41: Digital Economy/E-Commerce | B41: Individuals | C41: 30 | D41: Individuals Who are Internet Users and Selling Goods Online to Earn Money
A42: Digital Economy/E-Commerce | B42: Individuals | C42: 31 | D42: Individuals Who Are Selling Goods Online by Type of Goods Sold
A43: Digital Economy/E-Commerce | B43: Individuals | C43: 32 | D43: Individuals Who Are Selling Goods Online by Type of Online Site or Mobile Application Used
A44: Digital Economy/E-Commerce | B44: Individuals | C44: 33 | D44: Individuals Who Are Selling Goods Online by Mode of Payment Being Accepted
A45: Digital Economy/E-Commerce | B45: Individuals | C45: 34 | D45: Internet Users Who are Purchasing Goods and/or Services Online
A46: Digital Economy/E-Commerce | B46: Individuals | C46: 34 | D46: Top 5 Types of Goods/Services Purchased Online in 2024
A47: Digital Economy/E-Commerce | B47: Individuals | C47: 35 | D47: Individuals Who Purchase Goods/Services Online by Online Site or Mobile Application Used
A48: Digital Economy/E-Commerce | B48: Individuals | C48: 36 | D48: Individuals Who Purchase Goods/Services Online by Type of Device Used
A49: Digital Economy/E-Commerce | B49: Individuals | C49: 37 | D49: Individuals Who Purchase Goods/Services Online by Type of Delivery/Fulfillment Method Chosen
A50: Digital Economy/E-Commerce | B50: Individuals | C50: 38 | D50: Individuals Who Purchase Goods/Services Online by Mode of Payment Used
A51: Digital Economy/E-Commerce | B51: Individuals | C51: 39 | D51: Individuals Who are Not Using Electronic Payments on Online Purchases
A52: Digital Economy/E-Commerce | B52: Individuals | C52: 40 | D52: Individuals Who are Not Purchasing Online by Type of Reason
A53: Government Websites/Online Services | B53: Individuals | C53: 41 | D53: Individuals Who are Aware of Any Government Websites or Online Services
A54: Government Websites/Online Services | B54: Individuals | C54: 41 | D54: Individuals with Internet Who are Using the Internet to Access Government Websites/Services
A55: Government Websites/Online Services | B55: Individuals | C55: 42 | D55: Individuals Who Used the Internet and Accessed Online Government Websites/Services by Website/Service
A56: Technology-Enabled Incidents | B56: Individuals | C56: 43 | D56: Individuals Who are Aware of Cybersecurity or Data Privacy
A57: Technology-Enabled Incidents | B57: Individuals | C57: 44 | D57: Individuals Who Experienced Any Cyber Incidents (Text Scams, Phishing, and Hacking)
A58: Technology-Enabled Incidents | B58: Individuals | C58: 44 | D58: Individuals Who Experienced Any Cyber Incidents and Have Reported the Incident
A59: Technology-Enabled Incidents | B59: Individuals | C59: 44 | D59: Individuals Who Experienced Any Cyber Incidents and Have Been a Victim of the Incident by Type
A60: Technology-Enabled Incidents | B60: Individuals | C60: 44 | D60: 'i_F6&7&9&10'!A1
A61: Artificial Intelligence | B61: Individuals | C61: 45 | D61: Individuals Who are Using Artificial Intelligence Applications
A62: Artificial Intelligence | B62: Individuals | C62: 45 | D62: Individuals Who are Familiar with the Concept of Artificial Intelligence
A63: Artificial Intelligence | B63: Individuals | C63: 45 | D63: 'i_G1-5'!A1
A64: Artificial Intelligence | B64: Individuals | C64: 45 | D64: Individuals Who Feel Safe/Comfortable in Using Artificial Intelligence
A65: Artificial Intelligence | B65: Individuals | C65: 45 | D65: 'i_G1-5'!A1
A66: e-Waste | B66: Individuals | C66: 46 | D66: Individuals Who are Aware and Knowledgeable About e-Waste
A67: e-Waste | B67: Individuals | C67: 46 | D67: Individuals Who are Aware of e-Waste by Source of Information
A68: e-Waste | B68: Individuals | C68: 47 | D68: Individuals Who Have Disposed an Electronic Device/Appliance
A69: Emergency and Disaster Preparedness | B69: Individuals | C69: 48 | D69: Individuals by Source of Information About a Disaster
A70: Emergency and Disaster Preparedness | B70: Individuals | C70: 49 | D70: Individuals by Most Effective Means of Receiving Information on Making Household Safe from Natural Disasters
A71: Emergency and Disaster Preparedness | B71: Individuals | C71: 50 | D71: Individuals Who Have Received Any Emergency Mobile Alerts
A72: Government Websites/Online Services | B72: Individuals | C72: 51 | D72: governemnt websites by platform used to accessed
A73: Technology-Enabled Incidents | B73: Individuals | C73: 52 | D73: individuals who received/experienced cyber incidents

Sheet Estimated Totals
A1: BACK TO LIST
A2: Table #. Estimated Number of Households and Individuals Aged 10 and Over by Region, Philippines: 2019 and 2024p
A4: Region | B4: Number of Households | D4: Number of Individuals
B5: 2019 | C5: 2024 | D5: 2019* | E5: 2024
A7: PHILIPPINES | B7: 23360960 | C7: 27793884 | D7: 83258836 | E7: 91383228
A8: National Capital Region | B8: 3009545 | C8: 3667731 | D8: 11005073 | E8: 11919468
A9: Cordillera Administrative Region | B9: 388188 | C9: 468413 | D9: 1394660 | E9: 1496049
A10: Region I - Ilocos Region | B10: 1250337 | C10: 1316881 | D10: 4063052 | E10: 4389510
A11: Region II - Cagayan Valley | B11: 855893 | C11: 934252 | D11: 2820240 | E11: 3055894
A12: Region III - Central Luzon | B12: 2823200 | C12: 3161851 | D12: 9585315 | E12: 10708290
A13: Region IV-A - CALABARZON | B13: 3486186 | C13: 4369198 | D13: 12457452 | E13: 13985526
A14: MIMAROPA Region | B14: 686916 | C14: 828498 | D14: 2347582 | E14: 2538126
A15: Region V - Bicol Region | B15: 1030986 | C15: 1384033 | D15: 4528646 | E15: 4884805
A16: Region VI - Western Visayas | B16: 1705556 | C16: 2040922 | D16: 6087553 | E16: 6586874
A17: Region VII - Central Visayas | B17: 1820052 | C17: 2077216 | D17: 6058752 | E17: 6668940
A18: Region VIII - Eastern Visayas | B18: 1042723 | C18: 1200913 | D18: 3529248 | E18: 3864215
... A24: Bangsamoro Autonomous Region in Muslim Mindanao | B24: 521349 | C24: 846042 | D24: 2943119 | E24: 3746618
A27: Notes:
A28: Details may not add up to totals due to rounding.
A29: * Based on the July 2019 Population Projection.
A30: p Estimates are preliminary and may change
A31: Source of data: Philippine Statistics Authority, 2024 National Information and Communications Technology Household Survey.

Sheet Estimated Individuals by Sex
A1: BACK TO LIST
A2: Table #. Estimated Number of Individuals Aged 10 and Over by Region and Sex, Philippines: 2024p
A4: Region | B4: Number of Individuals
B5: Total | C5: Male | D5: Female
A7: PHILIPPINES | B7: 91383228 | C7: 45892072 | D7: 45491156
A8: National Capital Region | B8: 11919468 | C8: 5828575 | D8: 6090893
A9: Cordillera Administrative Region | B9: 1496049 | C9: 758033 | D9: 738016
A10: Region I - Ilocos Region | B10: 4389510 | C10: 2203738 | D10: 2185772
A11: Region II - Cagayan Valley | B11: 3055894 | C11: 1547225 | D11: 1508669
A12: Region III - Central Luzon | B12: 10708290 | C12: 5386609 | D12: 5321681
A13: Region IV-A - CALABARZON | B13: 13985526 | C13: 6942876 | D13: 7042650
A14: MIMAROPA Region | B14: 2538126 | C14: 1296138 | D14: 1241988
A15: Region V - Bicol Region | B15: 4884805 | C15: 2481154 | D15: 2403651
A16: Region VI - Western Visayas | B16: 6586874 | C16: 3329796 | D16: 3257078
A17: Region VII - Central Visayas | B17: 6668940 | C17: 3364353 | D17: 3304587
A18: Region VIII - Eastern Visayas | B18: 3864215 | C18: 1981621 | D18: 1882594
... A24: Bangsamoro Autonomous Region in Muslim Mindanao | B24: 3746618 | C24: 1849043 | D24: 1897575
A27: Notes:
A28: Details may not add up to totals due to rounding.
A29: p Estimates are preliminary and may change
A30: Source of data: Philippine Statistics Authority, 2024 National Information and Communications Technology Household Survey.

Sheet c27
A1: BACK TO LIST
A2: Table #. Number and Percentage of Households with Access to Communal or Shared Cellphone by any Household Member at Any Time by Region, Philippines: 2019 and 2024p
A4: Region | B4: 2019 | E4: 2024
B5: Total Households | C5: With Access to Communal or Shared Cellphone | E5: Total Households | F5: With Access to Communal or Shared Cellphone
C6: Number | D6: Proportion | F6: Number | G6: Proportion
A8: PHILIPPINES | B8: ='Estimated Totals'!B7 -> 23360960 | C8: 5616891 | D8: =(C8/B8)*100 -> 24.043922 | E8: 27793884 | F8: 3633210 | G8: =(F8/E8)*100 -> 13.071977
A9: National Capital Region | B9: ='Estimated Totals'!B8 -> 3009545 | C9: 361042 | D9: =(C9/B9)*100 -> 11.996564 | E9: 3667731 | F9: 514743 | G9: =(F9/E9)*100 -> 14.034372
A10: Cordillera Administrative Region | B10: ='Estimated Totals'!B9 -> 388188 | C10: 96263 | D10: =(C10/B10)*100 -> 24.798036 | E10: 468413 | F10: 13931 | G10: =(F10/E10)*100 -> 2.9740848
A11: Region I - Ilocos Region | B11: ='Estimated Totals'!B10 -> 1250337 | C11: 154243 | D11: =(C11/B11)*100 -> 12.336114 | E11: 1316881 | F11: 110041 | G11: =(F11/E11)*100 -> 8.356184
A12: Region II - Cagayan Valley | B12: ='Estimated Totals'!B11 -> 855893 | C12: 328525 | D12: =(C12/B12)*100 -> 38.383887 | E12: 934252 | F12: 177943 | G12: =(F12/E12)*100 -> 19.046574
A13: Region III - Central Luzon | B13: ='Estimated Totals'!B12 -> 2823200 | C13: 737821 | D13: =(C13/B13)*100 -> 26.134209 | E13: 3161851 | F13: 537446 | G13: =(F13/E13)*100 -> 16.997828
A14: Region IV-A - CALABARZON | B14: ='Estimated Totals'!B13 -> 3486186 | C14: 368496 | D14: =(C14/B14)*100 -> 10.570176 | E14: 4369198 | F14: 554046 | G14: =(F14/E14)*100 -> 12.680725
A15: MIMAROPA Region | B15: ='Estimated Totals'!B14 -> 686916 | C15: 127459 | D15: =(C15/B15)*100 -> 18.555253 | E15: 828498 | F15: 41005 | G15: =(F15/E15)*100 -> 4.9493179
A16: Region V - Bicol Region | B16: ='Estimated Totals'!B15 -> 1030986 | C16: 269349 | D16: =(C16/B16)*100 -> 26.125379 | E16: 1384033 | F16: 314774 | G16: =(F16/E16)*100 -> 22.743244
A17: Region VI - Western Visayas | B17: ='Estimated Totals'!B16 -> 1705556 | C17: 580410 | D17: =(C17/B17)*100 -> 34.030545 | E17: 2040922 | F17: 174752 | G17: =(F17/E17)*100 -> 8.5624046
A18: Region VII - Central Visayas | B18: ='Estimated Totals'!B17 -> 1820052 | C18: 341703 | D18: =(C18/B18)*100 -> 18.774354 | E18: 2077216 | F18: 109608 | G18: =(F18/E18)*100 -> 5.276678
A19: Region VIII - Eastern Visayas | B19: ='Estimated Totals'!B18 -> 1042723 | C19: 80941 | D19: =(C19/B19)*100 -> 7.7624642 | E19: 1200913 | F19: 83721 | G19: =(F19/E19)*100 -> 6.9714459
... A25: Bangsamoro Autonomous Region in Muslim Mindanao | B25: ='Estimated Totals'!B24 -> 521349 | C25: 249945 | D25: =(C25/B25)*100 -> 47.941974 | E25: 846042 | F25: 190555 | G25: =(F25/E25)*100 -> 22.523114
A28: Notes:
A29: Details may not add up to totals due to rounding.
A30: p Estimates are preliminary and may change
A31: Source of data: Philippine Statistics Authority, 2024 National Information and Communications Technology Household Survey.

Sheet c28_a and b
A1: BACK TO LIST
A2: Table #. Number and Proportion of Households with Access to Communal or Shared Cellphone by Type of Cellphone by Region, Philippines: 2024p
A4: Region | B4: 2024
B5: With Access to Communal or Shared Cellphone | C5: Basic Cellphone | E5: Smart Phone
C6: Number | D6: Proportion | E6: Number | F6: Proportion
A8: PHILIPPINES | B8: 3633210 | C8: 542871 | D8: =(C8/B8)*100 -> 14.941911 | E8: 3305348 | F8: =(E8/B8)*100 -> 90.975969
A9: National Capital Region | B9: 514743 | C9: 44992 | D9: =(C9/B9)*100 -> 8.7406725 | E9: 491247 | F9: =(E9/B9)*100 -> 95.435392
A10: Cordillera Administrative Region | B10: 13931 | C10: 3545 | D10: =(C10/B10)*100 -> 25.446845 | E10: 11223 | F10: =(E10/B10)*100 -> 80.561338
A11: Region I - Ilocos Region | B11: 110041 | C11: 10380 | D11: =(C11/B11)*100 -> 9.4328478 | E11: 106070 | F11: =(E11/B11)*100 -> 96.391345
A12: Region II - Cagayan Valley | B12: 177943 | C12: 35501 | D12: =(C12/B12)*100 -> 19.950771 | E12: 163111 | F12: =(E12/B12)*100 -> 91.664747
A13: Region III - Central Luzon | B13: 537446 | C13: 57482 | D13: =(C13/B13)*100 -> 10.6954 | E13: 516563 | F13: =(E13/B13)*100 -> 96.1144
A14: Region IV-A - CALABARZON | B14: 554046 | C14: 44999 | D14: =(C14/B14)*100 -> 8.1218888 | E14: 521611 | F14: =(E14/B14)*100 -> 94.145793
A15: MIMAROPA Region | B15: 41005 | C15: 4920 | D15: =(C15/B15)*100 -> 11.998537 | E15: 36666 | F15: =(E15/B15)*100 -> 89.418364
A16: Region V - Bicol Region | B16: 314774 | C16: 25667 | D16: =(C16/B16)*100 -> 8.1541042 | E16: 301454 | F16: =(E16/B16)*100 -> 95.768393
A17: Region VI - Western Visayas | B17: 174752 | C17: 19136 | D17: =(C17/B17)*100 -> 10.950375 | E17: 163520 | F17: =(E17/B17)*100 -> 93.572606
A18: Region VII - Central Visayas | B18: 109608 | C18: 23989 | D18: =(C18/B18)*100 -> 21.886176 | E18: 88082 | F18: =(E18/B18)*100 -> 80.360923
A19: Region VIII - Eastern Visayas | B19: 83721 | C19: 9284 | D19: =(C19/B19)*100 -> 11.089213 | E19: 75303 | F19: =(E19/B19)*100 -> 89.945175
... A25: Bangsamoro Autonomous Region in Muslim Mindanao | B25: 190555 | C25: 108843 | D25: =(C25/B25)*100 -> 57.118942 | E25: 128143 | F25: =(E25/B25)*100 -> 67.247251
A28: Notes:
A29: Details may not add up to totals due to rounding.
A30: p Estimates are preliminary and may change
A31: Source of data: Philippine Statistics Authority, 2024 National Information and Communications Technology Household Survey.

Sheet i_C6
A1: BACK TO LIST
A2: Table #. Number and Proportion of Individuals Who Used a Cellphone by Region, Philippines: 2019r and 2024p
A4: Region | B4: 2019 | E4: 2024
B5: Total Individuals | C5: Used a Cellphone | E5: Total Individuals | F5: Used a Cellphone
C6: Number | D6: Proportion | F6: Number | G6: Proportion
A8: PHILIPPINES | B8: ='Estimated Totals'!D7 -> 83258836 | C8: 35596631 | D8: =(C8/$B8)*100 -> 42.754178 | E8: 91383228 | F8: 74604857 | G8: =(F8/$E8)*100 -> 81.639551
A9: National Capital Region | B9: ='Estimated Totals'!D8 -> 11005073 | C9: 5768766 | D9: =(C9/$B9)*100 -> 52.419153 | E9: 11919468 | F9: 11067327 | G9: =(F9/$E9)*100 -> 92.850847
A10: Cordillera Administrative Region | B10: ='Estimated Totals'!D9 -> 1394660 | C10: 558479 | D10: =(C10/$B10)*100 -> 40.044097 | E10: 1496049 | F10: 1275461 | G10: =(F10/$E10)*100 -> 85.255296
A11: Region I - Ilocos Region | B11: ='Estimated Totals'!D10 -> 4063052 | C11: 2042932 | D11: =(C11/$B11)*100 -> 50.280725 | E11: 4389510 | F11: 3697111 | G11: =(F11/$E11)*100 -> 84.226053
A12: Region II - Cagayan Valley | B12: ='Estimated Totals'!D11 -> 2820240 | C12: 1435281 | D12: =(C12/$B12)*100 -> 50.892158 | E12: 3055894 | F12: 2601214 | G12: =(F12/$E12)*100 -> 85.121212
A13: Region III - Central Luzon | B13: ='Estimated Totals'!D12 -> 9585315 | C13: 4868143 | D13: =(C13/$B13)*100 -> 50.787512 | E13: 10708290 | F13: 9150022 | G13: =(F13/$E13)*100 -> 85.448022
A14: Region IV-A - CALABARZON | B14: ='Estimated Totals'!D13 -> 12457452 | C14: 6007369 | D14: =(C14/$B14)*100 -> 48.223096 | E14: 13985526 | F14: 12243411 | G14: =(F14/$E14)*100 -> 87.543443
A15: MIMAROPA Region | B15: ='Estimated Totals'!D14 -> 2347582 | C15: 906922 | D15: =(C15/$B15)*100 -> 38.632176 | E15: 2538126 | F15: 1994623 | G15: =(F15/$E15)*100 -> 78.586445
A16: Region V - Bicol Region | B16: ='Estimated Totals'!D15 -> 4528646 | C16: 1707802 | D16: =(C16/$B16)*100 -> 37.711095 | E16: 4884805 | F16: 3669067 | G16: =(F16/$E16)*100 -> 75.111842
A17: Region VI - Western Visayas | B17: ='Estimated Totals'!D16 -> 6087553 | C17: 2127227 | D17: =(C17/$B17)*100 -> 34.943876 | E17: 6586874 | F17: 5061672 | G17: =(F17/$E17)*100 -> 76.844828
A18: Region VII - Central Visayas | B18: ='Estimated Totals'!D17 -> 6058752 | C18: 1540479 | D18: =(C18/$B18)*100 -> 25.425682 | E18: 6668940 | F18: 5435569 | G18: =(F18/$E18)*100 -> 81.505742
A19: Region VIII - Eastern Visayas | B19: ='Estimated Totals'!D18 -> 3529248 | C19: 1650577 | D19: =(C19/$B19)*100 -> 46.768518 | E19: 3864215 | F19: 2961963 | G19: =(F19/$E19)*100 -> 76.651092
... A25: Bangsamoro Autonomous Region in Muslim Mindanao | B25: ='Estimated Totals'!D24 -> 2943119 | C25: 764912 | D25: =(C25/$B25)*100 -> 25.989843 | E25: 3746618 | F25: 2456282 | G25: =(F25/$E25)*100 -> 65.55998
A28: Notes:
A29: Details may not add up to totals due to rounding.
A30: p Estimates are preliminary and may change
A31: r Revised
A32: Source of data: Philippine Statistics Authority, 2024 National Information and Communications Technology Household Survey.

Sheet i_C8
A1: BACK TO LIST
A2: Table #. Number and Proportion of Individuals Who Own a Cellphone by Type of Cellphone and Region, Philippines: 2019r and 2024p
A4: Region | B4: 2019 | I4: 2024
B5: Total Individuals | C5: Cellphone Owners | E5: Type of Cellphone | I5: Total Individuals | J5: Cellphone Owners | L5: Type of Cellphone
E6: Basic/Analog Phone | G6: Smartphone | L6: Basic/Analog Phone | N6: Smartphone
C7: Number | D7: Proportion | E7: Number | F7: Proportion | G7: Number | H7: Proportion | J7: Number | K7: Proportion | L7: Number | M7: Proportion | N7: Number | O7: Proportion
A9: PHILIPPINES | B9: ='Estimated Totals'!D7 -> 83258836 | C9: 33940106 | D9: =(C9/$B9)*100 -> 40.76457 | E9: 10656100 | F9: =(E9/$C9)*100 -> 31.396778 | G9: 24261441 | H9: =(G9/$C9)*100 -> 71.483104 | I9: 91383228 | J9: 72873415 | K9: =(J9/$I9)*100 -> 79.744847 | L9: 5516992 | M9: =(L9/$J9)*100 -> 7.5706511 | N9: 67746423 | O9: =(N9/$J9)*100 -> 92.964523
A10: National Capital Region | B10: ='Estimated Totals'!D8 -> 11005073 | C10: 5613470.5 | D10: =(C10/$B10)*100 -> 51.008026 | E10: 708861.96 | F10: =(E10/$C10)*100 -> 12.627873 | G10: 5042024.5 | H10: =(G10/$C10)*100 -> 89.820093 | I10: 11919468 | J10: 10924677 | K10: =(J10/$I10)*100 -> 91.654065 | L10: 156776 | M10: =(L10/$J10)*100 -> 1.435063 | N10: 10793232 | O10: =(N10/$J10)*100 -> 98.796807
A11: Cordillera Administrative Region | B11: ='Estimated Totals'!D9 -> 1394660 | C11: 556690.66 | D11: =(C11/$B11)*100 -> 39.915869 | E11: 222736.6 | F11: =(E11/$C11)*100 -> 40.010837 | G11: 344665.61 | H11: =(G11/$C11)*100 -> 61.913309 | I11: 1496049 | J11: 1277366 | K11: =(J11/$I11)*100 -> 85.382631 | L11: 158661 | M11: =(L11/$J11)*100 -> 12.420951 | N11: 1138648 | O11: =(N11/$J11)*100 -> 89.140309
A12: Region I - Ilocos Region | B12: ='Estimated Totals'!D10 -> 4063052 | C12: 2001306 | D12: =(C12/$B12)*100 -> 49.256224 | E12: 677748.2 | F12: =(E12/$C12)*100 -> 33.865296 | G12: 1418816.9 | H12: =(G12/$C12)*100 -> 70.894552 | I12: 4389510 | J12: 3683268 | K12: =(J12/$I12)*100 -> 83.910687 | L12: 200746 | M12: =(L12/$J12)*100 -> 5.4502143 | N12: 3482522 | O12: =(N12/$J12)*100 -> 94.549786
A13: Region II - Cagayan Valley | B13: ='Estimated Totals'!D11 -> 2820240 | C13: 1344522.4 | D13: =(C13/$B13)*100 -> 47.674043 | E13: 574121.17 | F13: =(E13/$C13)*100 -> 42.70075 | G13: 832935.16 | H13: =(G13/$C13)*100 -> 61.950261 | I13: 3055894 | J13: 2451050 | K13: =(J13/$I13)*100 -> 80.207298 | L13: 201403 | M13: =(L13/$J13)*100 -> 8.217009 | N13: 2260260 | O13: =(N13/$J13)*100 -> 92.215989
A14: Region III - Central Luzon | B14: ='Estimated Totals'!D12 -> 9585315 | C14: 4847012.4 | D14: =(C14/$B14)*100 -> 50.567065 | E14: 1388040.8 | F14: =(E14/$C14)*100 -> 28.637038 | G14: 3593231.3 | H14: =(G14/$C14)*100 -> 74.13291 | I14: 10708290 | J14: 9021916 | K14: =(J14/$I14)*100 -> 84.251697 | L14: 432819 | M14: =(L14/$J14)*100 -> 4.7974178 | N14: 8610854 | O14: =(N14/$J14)*100 -> 95.443739
A15: Region IV-A - CALABARZON | B15: ='Estimated Totals'!D13 -> 12457452 | C15: 5566196.9 | D15: =(C15/$B15)*100 -> 44.681664 | E15: 1161361.4 | F15: =(E15/$C15)*100 -> 20.864541 | G15: 4538133.3 | H15: =(G15/$C15)*100 -> 81.530234 | I15: 13985526 | J15: 12081369 | K15: =(J15/$I15)*100 -> 86.384802 | L15: 565208 | M15: =(L15/$J15)*100 -> 4.678344 | N15: 11574712 | O15: =(N15/$J15)*100 -> 95.806295
A16: MIMAROPA Region | B16: ='Estimated Totals'!D14 -> 2347582 | C16: 761294.45 | D16: =(C16/$B16)*100 -> 32.428876 | E16: 291383.62 | F16: =(E16/$C16)*100 -> 38.27476 | G16: 506241.65 | H16: =(G16/$C16)*100 -> 66.497483 | I16: 2538126 | J16: 1900349 | K16: =(J16/$I16)*100 -> 74.87213 | L16: 152671 | M16: =(L16/$J16)*100 -> 8.0338401 | N16: 1757178 | O16: =(N16/$J16)*100 -> 92.466068
A17: Region V - Bicol Region | B17: ='Estimated Totals'!D15 -> 4528646 | C17: 1690938.7 | D17: =(C17/$B17)*100 -> 37.338726 | E17: 522906.83 | F17: =(E17/$C17)*100 -> 30.924055 | G17: 1194218.5 | H17: =(G17/$C17)*100 -> 70.624586 | I17: 4884805 | J17: 3577241 | K17: =(J17/$I17)*100 -> 73.232012 | L17: 204844 | M17: =(L17/$J17)*100 -> 5.7263125 | N17: 3404672 | O17: =(N17/$J17)*100 -> 95.175919
A18: Region VI - Western Visayas | B18: ='Estimated Totals'!D16 -> 6087553 | C18: 2159752 | D18: =(C18/$B18)*100 -> 35.478164 | E18: 722128.07 | F18: =(E18/$C18)*100 -> 33.435694 | G18: 1517000.4 | H18: =(G18/$C18)*100 -> 70.239565 | I18: 6586874 | J18: 4990093 | K18: =(J18/$I18)*100 -> 75.758137 | L18: 389379 | M18: =(L18/$J18)*100 -> 7.8030409 | N18: 4622547 | O18: =(N18/$J18)*100 -> 92.634486
A19: Region VII - Central Visayas | B19: ='Estimated Totals'!D17 -> 6058752 | C19: 1476407.2 | D19: =(C19/$B19)*100 -> 24.368173 | E19: 703079.31 | F19: =(E19/$C19)*100 -> 47.620963 | G19: 834318.78 | H19: =(G19/$C19)*100 -> 56.510073 | I19: 6668940 | J19: 5296648 | K19: =(J19/$I19)*100 -> 79.422637 | L19: 440263 | M19: =(L19/$J19)*100 -> 8.3121061 | N19: 4895590 | O19: =(N19/$J19)*100 -> 92.428079
A20: Region VIII - Eastern Visayas | B20: ='Estimated Totals'!D18 -> 3529248 | C20: 1318328.5 | D20: =(C20/$B20)*100 -> 37.354374 | E20: 432071.58 | F20: =(E20/$C20)*100 -> 32.774197 | G20: 917823.48 | H20: =(G20/$C20)*100 -> 69.62024 | I20: 3864215 | J20: 2705948 | K20: =(J20/$I20)*100 -> 70.025814 | L20: 193374 | M20: =(L20/$J20)*100 -> 7.1462571 | N20: 2524972 | O20: =(N20/$J20)*100 -> 93.311919
... A26: Bangsamoro Autonomous Region in Muslim Mindanao | B26: ='Estimated Totals'!D24 -> 2943119 | C26: 779688.76 | D26: =(C26/$B26)*100 -> 26.491921 | E26: 569733.04 | F26: =(E26/$C26)*100 -> 73.071855 | G26: 211031.81 | H26: =(G26/$C26)*100 -> 27.066161 | I26: 3746618 | J26: 2608489 | K26: =(J26/$I26)*100 -> 69.622497 | L26: 787402 | M26: =(L26/$J26)*100 -> 30.186135 | N26: 1848389 | O26: =(N26/$J26)*100 -> 70.860525
A29: Notes:
A30: Details may not add up to totals due to rounding.
A31: p Estimates are preliminary and may change
A32: r Revised
A33: Source of data: Philippine Statistics Authority, 2024 National Information and Communications Technology Household Survey.

Sheet i_C8&11
A1: BACK TO LIST
A2: Table #. Number and Proportion of Cellphone Owners by Type of SIM Card Used and Region, Philippines: 2019r and 2024p
A4: Region | B4: 2019 | G4: 2024
B5: Cellphone Owners | C5: Prepaid | E5: Postpaid | G5: Cellphone Owners | H5: Prepaid | J5: Postpaid
C6: Number | D6: Proportion | E6: Number | F6: Proportion | H6: Number | I6: Proportion | J6: Number | K6: Proportion
A8: PHILIPPINES | B8: =i_C8!C9 -> 33940106 | C8: 33189995 | D8: =(C8/$B8)*100 -> 97.789896 | E8: 818864.67 | F8: =(E8/$B8)*100 -> 2.4126756 | G8: 72873415 | H8: 70966582 | I8: =(H8/$G8)*100 -> 97.383363 | J8: 2257234 | K8: =(J8/$G8)*100 -> 3.0974725
A9: National Capital Region | B9: =i_C8!C10 -> 5613470.5 | C9: 5355014.8 | D9: =(C9/$B9)*100 -> 95.395794 | E9: 263894.89 | F9: =(E9/$B9)*100 -> 4.7011005 | G9: 10924677 | H9: 10594051 | I9: =(H9/$G9)*100 -> 96.973586 | J9: 436615 | K9: =(J9/$G9)*100 -> 3.9965941
A10: Cordillera Administrative Region | B10: =i_C8!C11 -> 556690.66 | C10: 554273.85 | D10: =(C10/$B10)*100 -> 99.565861 | E10: 2580.5649 | F10: =(E10/$B10)*100 -> 0.46355455 | G10: 1277366 | H10: 1226462 | I10: =(H10/$G10)*100 -> 96.014924 | J10: 57996 | K10: =(J10/$G10)*100 -> 4.5402805
A11: Region I - Ilocos Region | B11: =i_C8!C12 -> 2001306 | C11: 1966006.2 | D11: =(C11/$B11)*100 -> 98.236162 | E11: 39298.321 | F11: =(E11/$B11)*100 -> 1.9636338 | G11: 3683268 | H11: 3518329 | I11: =(H11/$G11)*100 -> 95.521939 | J11: 168734 | K11: =(J11/$G11)*100 -> 4.5810948
A12: Region II - Cagayan Valley | B12: =i_C8!C13 -> 1344522.4 | C12: 1334417.1 | D12: =(C12/$B12)*100 -> 99.248404 | E12: 18682.305 | F12: =(E12/$B12)*100 -> 1.3895123 | G12: 2451050 | H12: 2440210 | I12: =(H12/$G12)*100 -> 99.557741 | J12: 15419 | K12: =(J12/$G12)*100 -> 0.62907733
A13: Region III - Central Luzon | B13: =i_C8!C14 -> 4847012.4 | C13: 4765111.8 | D13: =(C13/$B13)*100 -> 98.310287 | E13: 88332.684 | F13: =(E13/$B13)*100 -> 1.8224151 | G13: 9021916 | H13: 8721921 | I13: =(H13/$G13)*100 -> 96.674819 | J13: 330842 | K13: =(J13/$G13)*100 -> 3.6670924
A14: Region IV-A - CALABARZON | B14: =i_C8!C15 -> 5566196.9 | C14: 5405404.8 | D14: =(C14/$B14)*100 -> 97.111276 | E14: 173992.38 | F14: =(E14/$B14)*100 -> 3.1258754 | G14: 12081369 | H14: 11816558 | I14: =(H14/$G14)*100 -> 97.808104 | J14: 326586 | K14: =(J14/$G14)*100 -> 2.7032201
A15: MIMAROPA Region | B15: =i_C8!C16 -> 761294.45 | C15: 756606.72 | D15: =(C15/$B15)*100 -> 99.384243 | E15: 7634.8877 | F15: =(E15/$B15)*100 -> 1.0028824 | G15: 1900349 | H15: 1884654 | I15: =(H15/$G15)*100 -> 99.174099 | J15: 29388 | K15: =(J15/$G15)*100 -> 1.5464528
A16: Region V - Bicol Region | B16: =i_C8!C17 -> 1690938.7 | C16: 1665837.5 | D16: =(C16/$B16)*100 -> 98.515541 | E16: 17517.414 | F16: =(E16/$B16)*100 -> 1.0359579 | G16: 3577241 | H16: 3486357 | I16: =(H16/$G16)*100 -> 97.459383 | J16: 95944 | K16: =(J16/$G16)*100 -> 2.682067
A17: Region VI - Western Visayas | B17: =i_C8!C18 -> 2159752 | C17: 2130834.4 | D17: =(C17/$B17)*100 -> 98.661067 | E17: 42559.781 | F17: =(E17/$B17)*100 -> 1.9705865 | G17: 4990093 | H17: 4828205 | I17: =(H17/$G17)*100 -> 96.755812 | J17: 178398 | K17: =(J17/$G17)*100 -> 3.5750436
A18: Region VII - Central Visayas | B18: =i_C8!C19 -> 1476407.2 | C18: 1454815.6 | D18: =(C18/$B18)*100 -> 98.537557 | E18: 21946.062 | F18: =(E18/$B18)*100 -> 1.4864505 | G18: 5296648 | H18: 5121217 | I18: =(H18/$G18)*100 -> 96.687886 | J18: 213237 | K18: =(J18/$G18)*100 -> 4.0258858
A19: Region VIII - Eastern Visayas | B19: =i_C8!C20 -> 1318328.5 | C19: 1287336 | D19: =(C19/$B19)*100 -> 97.649108 | E19: 36231.534 | F19: =(E19/$B19)*100 -> 2.7482933 | G19: 2705948 | H19: 2679128 | I19: =(H19/$G19)*100 -> 99.00885 | J19: 43261 | K19: =(J19/$G19)*100 -> 1.5987373
... A25: Bangsamoro Autonomous Region in Muslim Mindanao | B25: =i_C8!C26 -> 779688.76 | C25: 774492.55 | D25: =(C25/$B25)*100 -> 99.333553 | E25: 2695.8593 | F25: =(E25/$B25)*100 -> 0.34576095 | G25: 2608489 | H25: 2540113 | I25: =(H25/$G25)*100 -> 97.378712 | J25: 74592 | K25: =(J25/$G25)*100 -> 2.8595865
A28: Notes:
A29: Details may not add up to totals due to rounding.
A30: p Estimates are preliminary and may change
A31: r Revised
A32: Source of data: Philippine Statistics Authority, 2024 National Information and Communications Technology Household Survey.

Sheet i_C12
A1: BACK TO LIST
A2: Table #. Number and Proportion of Individuals With ICT Device and Active SIM by Details Used in SIM Card Registration and Region, Philippines: 2024p
A4: Region | B4: With ICT Device and Active SIM | C4: Details Used in SIM Registration
C5: Owner | E5: Relative | G5: Others*
C6: Number | D6: Proportion | E6: Number | F6: Proportion | G6: Number | H6: Proportion
A8: PHILIPPINES | B8: 72989986 | C8: 61831391 | D8: =(C8/$B8)*100 -> 84.712156 | E8: 9212540 | F8: =(E8/$B8)*100 -> 12.621649 | G8: 2195966 | H8: =(G8/$B8)*100 -> 3.0085853
A9: National Capital Region | B9: 10953079 | C9: 9823627 | D9: =(C9/$B9)*100 -> 89.688269 | E9: 990700 | F9: =(E9/$B9)*100 -> 9.0449453 | G9: 166319 | H9: =(G9/$B9)*100 -> 1.518468
A10: Cordillera Administrative Region | B10: 1278264 | C10: 965232 | D10: =(C10/$B10)*100 -> 75.511162 | E10: 266527 | F10: =(E10/$B10)*100 -> 20.850701 | G10: 48335 | H10: =(G10/$B10)*100 -> 3.7813003
A11: Region I - Ilocos Region | B11: 3690995 | C11: 3080402 | D11: =(C11/$B11)*100 -> 83.457225 | E11: 570484 | F11: =(E11/$B11)*100 -> 15.456103 | G11: 40109 | H11: =(G11/$B11)*100 -> 1.0866718
A12: Region II - Cagayan Valley | B12: 2454608 | C12: 2126558 | D12: =(C12/$B12)*100 -> 86.635341 | E12: 269894 | F12: =(E12/$B12)*100 -> 10.995401 | G12: 65047 | H12: =(G12/$B12)*100 -> 2.6499954
A13: Region III - Central Luzon | B13: 9031169 | C13: 7850092 | D13: =(C13/$B13)*100 -> 86.922213 | E13: 1137264 | F13: =(E13/$B13)*100 -> 12.592655 | G13: 53207 | H13: =(G13/$B13)*100 -> 0.58914854
A14: Region IV-A - CALABARZON | B14: 12098018 | C14: 10136640 | D14: =(C14/$B14)*100 -> 83.787609 | E14: 1737288 | F14: =(E14/$B14)*100 -> 14.360104 | G14: 271609 | H14: =(G14/$B14)*100 -> 2.2450702
A15: MIMAROPA Region | B15: 1905284 | C15: 1418050 | D15: =(C15/$B15)*100 -> 74.427224 | E15: 395749 | F15: =(E15/$B15)*100 -> 20.771129 | G15: 103019 | H15: =(G15/$B15)*100 -> 5.4070154
A16: Region V - Bicol Region | B16: 3580110 | C16: 2765560 | D16: =(C16/$B16)*100 -> 77.247906 | E16: 604525 | F16: =(E16/$B16)*100 -> 16.885654 | G16: 222533 | H16: =(G16/$B16)*100 -> 6.2158146
A17: Region VI - Western Visayas | B17: 4997303 | C17: 4421971 | D17: =(C17/$B17)*100 -> 88.48715 | E17: 481861 | F17: =(E17/$B17)*100 -> 9.6424211 | G17: 134427 | H17: =(G17/$B17)*100 -> 2.689991
A18: Region VII - Central Visayas | B18: 5303296 | C18: 4464670 | D18: =(C18/$B18)*100 -> 84.186702 | E18: 614620 | F18: =(E18/$B18)*100 -> 11.589396 | G18: 236453 | H18: =(G18/$B18)*100 -> 4.4586046
A19: Region VIII - Eastern Visayas | B19: 2707991 | C19: 2318040 | D19: =(C19/$B19)*100 -> 85.599989 | E19: 271039 | F19: =(E19/$B19)*100 -> 10.008859 | G19: 130022 | H19: =(G19/$B19)*100 -> 4.8014192
... A25: Bangsamoro Autonomous Region in Muslim Mindanao | B25: 2609448 | C25: 2050292 | D25: =(C25/$B25)*100 -> 78.571867 | E25: 366282 | F25: =(E25/$B25)*100 -> 14.036762 | G25: 220473 | H25: =(G25/$B25)*100 -> 8.4490283
A28: Notes:
A29: Details may not add up to totals due to rounding.
A30: * Includes Friend, Pre-Registered, Employer, Others
A31: p Estimates are preliminary and may change
A32: Source of data: Philippine Statistics Authority, 2024 National Information and Communications Technology Household Survey.

Sheet i_C13
A1: BACK TO LIST
A2: Table #. Number and Proportion of Individuals with ICT Device and Active SIM Who Did Not Use Own Information in SIM Registration by Main Reason and Region, Philippines: 2024p
A4: Region | B4: Did Not Use Own Information | C4: Main Reason for Not Using Own Information
C5: No Government Issued ID | E5: Don't Know the Process | G5: Child (Parental Control) | I5: Others
C6: Number | D6: Proportion | E6: Number | F6: Proportion | G6: Number | H6: Proportion | I6: Number | J6: Proportion
A8: PHILIPPINES | B8: 11364259 | C8: 2216397 | D8: =(C8/$B8)*100 -> 19.503225 | E8: 4214914 | F8: =(E8/$B8)*100 -> 37.089211 | G8: 4221711 | H8: =(G8/$B8)*100 -> 37.149021 | I8: 641634 | J8: =(I8/$B8)*100 -> 5.6460698
A9: National Capital Region | B9: 1157019 | C9: 170718 | D9: =(C9/$B9)*100 -> 14.754987 | E9: 171704 | F9: =(E9/$B9)*100 -> 14.840206 | G9: 735644 | H9: =(G9/$B9)*100 -> 63.580978 | I9: 76015 | J9: =(I9/$B9)*100 -> 6.5699008
A10: Cordillera Administrative Region | B10: 313801 | C10: 51946 | D10: =(C10/$B10)*100 -> 16.553803 | E10: 172795 | F10: =(E10/$B10)*100 -> 55.065153 | G10: 80371 | H10: =(G10/$B10)*100 -> 25.612092 | I10: 8238 | J10: =(I10/$B10)*100 -> 2.6252306
A11: Region I - Ilocos Region | B11: 610593 | C11: 164712 | D11: =(C11/$B11)*100 -> 26.975743 | E11: 339389 | F11: =(E11/$B11)*100 -> 55.583507 | G11: 99020 | H11: =(G11/$B11)*100 -> 16.217022 | I11: 7472 | J11: =(I11/$B11)*100 -> 1.2237284
A12: Region II - Cagayan Valley | B12: 334942 | C12: 44891 | D12: =(C12/$B12)*100 -> 13.402619 | E12: 96425 | F12: =(E12/$B12)*100 -> 28.788566 | G12: 155869 | H12: =(G12/$B12)*100 -> 46.536117 | I12: 36205 | J12: =(I12/$B12)*100 -> 10.809334
A13: Region III - Central Luzon | B13: 1190471 | C13: 207672 | D13: =(C13/$B13)*100 -> 17.444524 | E13: 206739 | F13: =(E13/$B13)*100 -> 17.366152 | G13: 666321 | H13: =(G13/$B13)*100 -> 55.971208 | I13: 103731 | J13: =(I13/$B13)*100 -> 8.713442
A14: Region IV-A - CALABARZON | B14: 1999010 | C14: 407989 | D14: =(C14/$B14)*100 -> 20.409553 | E14: 561307 | F14: =(E14/$B14)*100 -> 28.079249 | G14: 890818 | H14: =(G14/$B14)*100 -> 44.562959 | I14: 123577 | J14: =(I14/$B14)*100 -> 6.18191
A15: MIMAROPA Region | B15: 498094 | C15: 157666 | D15: =(C15/$B15)*100 -> 31.653865 | E15: 234774 | F15: =(E15/$B15)*100 -> 47.134477 | G15: 91597 | H15: =(G15/$B15)*100 -> 18.389501 | I15: 11194 | J15: =(I15/$B15)*100 -> 2.247367
A16: Region V - Bicol Region | B16: 827059 | C16: 179570 | D16: =(C16/$B16)*100 -> 21.711873 | E16: 312753 | F16: =(E16/$B16)*100 -> 37.815077 | G16: 291568 | H16: =(G16/$B16)*100 -> 35.253591 | I16: 37089 | J16: =(I16/$B16)*100 -> 4.4844443
A17: Region VI - Western Visayas | B17: 610574 | C17: 85860 | D17: =(C17/$B17)*100 -> 14.062178 | E17: 239694 | F17: =(E17/$B17)*100 -> 39.257158 | G17: 250844 | H17: =(G17/$B17)*100 -> 41.083308 | I17: 24194 | J17: =(I17/$B17)*100 -> 3.9625009
A18: Region VII - Central Visayas | B18: 845861 | C18: 91989 | D18: =(C18/$B18)*100 -> 10.875191 | E18: 324772 | F18: =(E18/$B18)*100 -> 38.395434 | G18: 352369 | H18: =(G18/$B18)*100 -> 41.658027 | I18: 72168 | J18: =(I18/$B18)*100 -> 8.5318983
A19: Region VIII - Eastern Visayas | B19: 399041 | C19: 82391 | D19: =(C19/$B19)*100 -> 20.647252 | E19: 178025 | F19: =(E19/$B19)*100 -> 44.61321 | G19: 96974 | H19: =(G19/$B19)*100 -> 24.301763 | I19: 37257 | J19: =(I19/$B19)*100 -> 9.3366346
... A25: Bangsamoro Autonomous Region in Muslim Mindanao | B25: 576944 | C25: 78025 | D25: =(C25/$B25)*100 -> 13.523843 | E25: 423573 | F25: =(E25/$B25)*100 -> 73.416657 | G25: 74825 | H25: =(G25/$B25)*100 -> 12.969196 | I25: 959 | J25: =(I25/$B25)*100 -> 0.16622064
A28: Notes:
A29: Details may not add up to totals due to rounding.
A30: p Estimates are preliminary and may change
A31: Source of data: Philippine Statistics Authority, 2024 National Information and Communications Technology Household Survey.

Sheet i_C14
A1: BACK TO LIST
A2: Table #. Number and Proportion of Individuals with ICT Device, Active SIM and Registered SIM by Main Difficulty Encountered and Region, Philippines: 2024p
A4: Region | B4: With ICT Device and Active SIM | C4: Main Difficulty Encountered in SIM Registration
C5: Difficulty in Accessing the Registration Site | E5: Difficulty in Uploading ID | G5: Difficulty in Accomplishing the Registration Form | I5: Registration Site Took a Long Time to Load | K5: Did not Encounter any Difficulty | M5: Others
C6: Number | D6: Proportion | E6: Number | F6: Proportion | G6: Number | H6: Proportion | I6: Number | J6: Proportion | K6: Number | L6: Proportion | M6: Number | N6: Proportion
A8: PHILIPPINES | B8: 72989986 | C8: 4883635 | D8: =(C8/$B8)*100 -> 6.6908288 | E8: 8332250 | F8: =(E8/$B8)*100 -> 11.415607 | G8: 2134333 | H8: =(G8/$B8)*100 -> 2.924145 | I8: 3083032 | J8: =(I8/$B8)*100 -> 4.2239109 | K8: 54540047 | L8: =(K8/$B8)*100 -> 74.722643 | M8: 665541 | N8: =(M8/$B8)*100 -> 0.91182508
A9: National Capital Region | B9: 10953079 | C9: 652608 | D9: =(C9/$B9)*100 -> 5.958215 | E9: 868748 | F9: =(E9/$B9)*100 -> 7.9315414 | G9: 210371 | H9: =(G9/$B9)*100 -> 1.9206563 | I9: 352841 | J9: =(I9/$B9)*100 -> 3.2213864 | K9: 8881891 | L9: =(K9/$B9)*100 -> 81.090358 | M9: 80039 | N9: =(M9/$B9)*100 -> 0.7307443
A10: Cordillera Administrative Region | B10: 1278264 | C10: 103654 | D10: =(C10/$B10)*100 -> 8.1089665 | E10: 332694 | F10: =(E10/$B10)*100 -> 26.027018 | G10: 51103 | H10: =(G10/$B10)*100 -> 3.997844 | I10: 88462 | J10: =(I10/$B10)*100 -> 6.9204797 | K10: 738591 | L10: =(K10/$B10)*100 -> 57.780787 | M10: 8493 | N10: =(M10/$B10)*100 -> 0.66441674
A11: Region I - Ilocos Region | B11: 3690995 | C11: 166998 | D11: =(C11/$B11)*100 -> 4.524471 | E11: 761215 | F11: =(E11/$B11)*100 -> 20.623572 | G11: 163060 | H11: =(G11/$B11)*100 -> 4.4177789 | I11: 268703 | J11: =(I11/$B11)*100 -> 7.2799611 | K11: 2333201 | L11: =(K11/$B11)*100 -> 63.213334 | M11: 3622 | N11: =(M11/$B11)*100 -> 0.098130721
A12: Region II - Cagayan Valley | B12: 2454608 | C12: 79050 | D12: =(C12/$B12)*100 -> 3.2204735 | E12: 375411 | F12: =(E12/$B12)*100 -> 15.294133 | G12: 71533 | H12: =(G12/$B12)*100 -> 2.9142331 | I12: 226673 | J12: =(I12/$B12)*100 -> 9.2345906 | K12: 1682607 | L12: =(K12/$B12)*100 -> 68.548909 | M12: 28850 | N12: =(M12/$B12)*100 -> 1.1753404
A13: Region III - Central Luzon | B13: 9031169 | C13: 244177 | D13: =(C13/$B13)*100 -> 2.7037142 | E13: 1130607 | F13: =(E13/$B13)*100 -> 12.518944 | G13: 339327 | H13: =(G13/$B13)*100 -> 3.7572877 | I13: 251348 | J13: =(I13/$B13)*100 -> 2.783117 | K13: 7076712 | L13: =(K13/$B13)*100 -> 78.35876 | M13: 26853 | N13: =(M13/$B13)*100 -> 0.29733692
A14: Region IV-A - CALABARZON | B14: 12098018 | C14: 1014060 | D14: =(C14/$B14)*100 -> 8.3820341 | E14: 943927 | F14: =(E14/$B14)*100 -> 7.8023276 | G14: 241450 | H14: =(G14/$B14)*100 -> 1.9957815 | I14: 278432 | J14: =(I14/$B14)*100 -> 2.3014679 | K14: 9519762 | L14: =(K14/$B14)*100 -> 78.688608 | M14: 199953 | N14: =(M14/$B14)*100 -> 1.6527749
A15: MIMAROPA Region | B15: 1905284 | C15: 132075 | D15: =(C15/$B15)*100 -> 6.9320374 | E15: 352871 | F15: =(E15/$B15)*100 -> 18.520651 | G15: 77609 | H15: =(G15/$B15)*100 -> 4.073356 | I15: 93165 | J15: =(I15/$B15)*100 -> 4.8898222 | K15: 1230557 | L15: =(K15/$B15)*100 -> 64.586539 | M15: 44592 | N15: =(M15/$B15)*100 -> 2.3404385
A16: Region V - Bicol Region | B16: 3580110 | C16: 148774 | D16: =(C16/$B16)*100 -> 4.1555706 | E16: 531567 | F16: =(E16/$B16)*100 -> 14.847784 | G16: 66701 | H16: =(G16/$B16)*100 -> 1.8630992 | I16: 130357 | J16: =(I16/$B16)*100 -> 3.6411451 | K16: 2709645 | L16: =(K16/$B16)*100 -> 75.686082 | M16: 42149 | N16: =(M16/$B16)*100 -> 1.1773102
A17: Region VI - Western Visayas | B17: 4997303 | C17: 331894 | D17: =(C17/$B17)*100 -> 6.6414624 | E17: 606803 | F17: =(E17/$B17)*100 -> 12.14261 | G17: 115088 | H17: =(G17/$B17)*100 -> 2.3030022 | I17: 178732 | J17: =(I17/$B17)*100 -> 3.5765692 | K17: 3780626 | L17: =(K17/$B17)*100 -> 75.653327 | M17: 13654 | N17: =(M17/$B17)*100 -> 0.27322738
A18: Region VII - Central Visayas | B18: 5303296 | C18: 232552 | D18: =(C18/$B18)*100 -> 4.3850466 | E18: 349238 | F18: =(E18/$B18)*100 -> 6.5853009 | G18: 139987 | H18: =(G18/$B18)*100 -> 2.6396226 | I18: 331055 | J18: =(I18/$B18)*100 -> 6.2424387 | K18: 4270866 | L18: =(K18/$B18)*100 -> 80.532295 | M18: 31165 | N18: =(M18/$B18)*100 -> 0.58765341
A19: Region VIII - Eastern Visayas | B19: 2707991 | C19: 225430 | D19: =(C19/$B19)*100 -> 8.3246215 | E19: 301428 | F19: =(E19/$B19)*100 -> 11.131056 | G19: 40970 | H19: =(G19/$B19)*100 -> 1.5129297 | I19: 85526 | J19: =(I19/$B19)*100 -> 3.1582823 | K19: 2043178 | L19: =(K19/$B19)*100 -> 75.449955 | M19: 27647 | N19: =(M19/$B19)*100 -> 1.0209414
... A25: Bangsamoro Autonomous Region in Muslim Mindanao | B25: 2609448 | C25: 645288 | D25: =(C25/$B25)*100 -> 24.728908 | E25: 523269 | F25: =(E25/$B25)*100 -> 20.052862 | G25: 217706 | H25: =(G25/$B25)*100 -> 8.3429905 | I25: 212311 | J25: =(I25/$B25)*100 -> 8.1362418 | K25: 1117753 | L25: =(K25/$B25)*100 -> 42.834845 | M25: 8486 | N25: =(M25/$B25)*100 -> 0.32520288
A28: Notes:
A29: Details may not add up to totals due to rounding.
A30: p Estimates are preliminary and may change
A31: Source of data: Philippine Statistics Authority, 2024 National Information and Communications Technology Household Survey.

Sheet i_C15
A1: BACK TO LIST
A2: Table #. Individual Average Monthly Spending on Load or Subscription by Region, Philippines: 2019 and 2024p
A4: Region | B4: Average Monthly Spending
B5: 2019 | C5: 2024
A7: PHILIPPINES | B7: 255.5118 | C7: 265.3
A8: National Capital Region | B8: 338.68679 | C8: 320.3
A9: Cordillera Administrative Region | B9: 252.93832 | C9: 281.5
A10: Region I - Ilocos Region | B10: 186.50589 | C10: 284.5
A11: Region II - Cagayan Valley | B11: 218.05583 | C11: 271.5
A12: Region III - Central Luzon | B12: 289.09803 | C12: 289.4
A13: Region IV-A - CALABARZON | B13: 287.43904 | C13: 240.4
A14: MIMAROPA Region | B14: 223.18947 | C14: 301.9
A15: Region V - Bicol Region | B15: 185.38549 | C15: 236.6
A16: Region VI - Western Visayas | B16: 311.07504 | C16: 260.1
A17: Region VII - Central Visayas | B17: 195.33539 | C17: 288.8
A18: Region VIII - Eastern Visayas | B18: 219.41155 | C18: 261.7
... A24: Bangsamoro Autonomous Region in Muslim Mindanao | B24: 126.95219 | C24: 252.7
A27: Notes:
A28: p Estimates are preliminary and may change
A29: Source of data: Philippine Statistics Authority, 2024 National Information and Communications Technology Household Survey.

Sheet c29
A1: BACK TO LIST
A2: Table #. Number and Proportion of Households with Communal or Shared Computer That Can be Used by Any Household Member at Any Time by Region, Philippines: 2019 and 2024p
A4: Region | B4: 2019 | E4: 2024
B5: Total Households | C5: With Communal or Shared Computer | E5: Total Households | F5: With Communal or Shared Computer
C6: Number | D6: Proportion | F6: Number | G6: Proportion
A8: PHILIPPINES | B8: ='Estimated Totals'!B7 -> 23360960 | C8: 5557498 | D8: =(C8/B8)*100 -> 23.789682 | E8: 27793884 | F8: 3006985 | G8: =(F8/E8)*100 -> 10.818873
A9: National Capital Region | B9: ='Estimated Totals'!B8 -> 3009545 | C9: 1117522 | D9: =(C9/B9)*100 -> 37.13259 | E9: 3667731 | F9: 667137 | G9: =(F9/E9)*100 -> 18.189366
A10: Cordillera Administrative Region | B10: ='Estimated Totals'!B9 -> 388188 | C10: 116362 | D10: =(C10/B10)*100 -> 29.975682 | E10: 468413 | F10: 62352 | G10: =(F10/E10)*100 -> 13.31133
A11: Region I - Ilocos Region | B11: ='Estimated Totals'!B10 -> 1250337 | C11: 291371 | D11: =(C11/B11)*100 -> 23.303397 | E11: 1316881 | F11: 119488 | G11: =(F11/E11)*100 -> 9.0735609
A12: Region II - Cagayan Valley | B12: ='Estimated Totals'!B11 -> 855893 | C12: 146921 | D12: =(C12/B12)*100 -> 17.165814 | E12: 934252 | F12: 97834 | G12: =(F12/E12)*100 -> 10.471907
A13: Region III - Central Luzon | B13: ='Estimated Totals'!B12 -> 2823200 | C13: 654747 | D13: =(C13/B13)*100 -> 23.191662 | E13: 3161851 | F13: 390356 | G13: =(F13/E13)*100 -> 12.345806
A14: Region IV-A - CALABARZON | B14: ='Estimated Totals'!B13 -> 3486186 | C14: 1488913 | D14: =(C14/B14)*100 -> 42.708937 | E14: 4369198 | F14: 580410 | G14: =(F14/E14)*100 -> 13.284131
A15: MIMAROPA Region | B15: ='Estimated Totals'!B14 -> 686916 | C15: 99090 | D15: =(C15/B15)*100 -> 14.425345 | E15: 828498 | F15: 63200 | G15: =(F15/E15)*100 -> 7.6282622
A16: Region V - Bicol Region | B16: ='Estimated Totals'!B15 -> 1030986 | C16: 162411 | D16: =(C16/B16)*100 -> 15.752978 | E16: 1384033 | F16: 137805 | G16: =(F16/E16)*100 -> 9.9567713
A17: Region VI - Western Visayas | B17: ='Estimated Totals'!B16 -> 1705556 | C17: 281295 | D17: =(C17/B17)*100 -> 16.492862 | E17: 2040922 | F17: 129132 | G17: =(F17/E17)*100 -> 6.3271404
A18: Region VII - Central Visayas | B18: ='Estimated Totals'!B17 -> 1820052 | C18: 297076 | D18: =(C18/B18)*100 -> 16.322391 | E18: 2077216 | F18: 189142 | G18: =(F18/E18)*100 -> 9.1055528
A19: Region VIII - Eastern Visayas | B19: ='Estimated Totals'!B18 -> 1042723 | C19: 148345 | D19: =(C19/B19)*100 -> 14.226693 | E19: 1200913 | F19: 71688 | G19: =(F19/E19)*100 -> 5.9694582
... A25: Bangsamoro Autonomous Region in Muslim Mindanao | B25: ='Estimated Totals'!B24 -> 521349 | C25: 44261 | D25: =(C25/B25)*100 -> 8.4897065 | E25: 846042 | F25: 38074 | G25: =(F25/E25)*100 -> 4.5002494
A28: Notes:
A29: Details may not add up to totals due to rounding.
A30: p Estimates are preliminary and may change
A31: Source of data: Philippine Statistics Authority, 2024 National Information and Communications Technology Household Survey.

Sheet c30_a to d
A1: BACK TO LIST
A2: Table #. Number and Proportion of Households with Communal or Shared Computer That Can be Used by Any Household Member at Any Time by Type and Region, Philippines: 2019r and 2024p
A4: Region | B4: 2019 | K4: 2024
B5: With Communal or Shared Computer | C5: Type of Computer | K5: With Communal or Shared Computer | L5: Type of Computer
C6: Desktop | E6: Laptop | G6: Tablet or Similar Device | I6: Others | L6: Desktop | N6: Laptop | P6: Tablet or Similar Device | R6: Others
C7: Number | D7: Proportion | E7: Number | F7: Proportion | G7: Number | H7: Proportion | I7: Number | J7: Proportion | L7: Number | M7: Proportion | N7: Number | O7: Proportion | P7: Number | Q7: Proportion | R7: Number | S7: Proportion
A9: PHILIPPINES | B9: 5557498 | C9: 1373230 | D9: =(C9/$B9)*100 -> 24.709501 | E9: 3661577 | F9: =(E9/$B9)*100 -> 65.88535 | G9: 2191905 | H9: =(G9/$B9)*100 -> 39.4405 | I9: 17195 | J9: =IFERROR((I9/$B9)*100,"-") -> 0.30940182 | K9: 3006985 | L9: 916719 | M9: =(L9/$K9)*100 -> 30.486318 | N9: 2363672 | O9: =(N9/$K9)*100 -> 78.606046 | P9: 681463 | Q9: =(P9/$K9)*100 -> 22.662667 | R9: 4599 | S9: =(R9/$K9)*100 -> 0.1529439
A10: National Capital Region | B10: 1117522 | C10: 411311 | D10: =(C10/$B10)*100 -> 36.805629 | E10: 801970 | F10: =(E10/$B10)*100 -> 71.76324 | G10: 323043 | H10: =(G10/$B10)*100 -> 28.907082 | I10: 1436 | J10: =IFERROR((I10/$B10)*100,"-") -> 0.12849859 | K10: 667137 | L10: 216586 | M10: =(L10/$K10)*100 -> 32.464996 | N10: 516556 | O10: =(N10/$K10)*100 -> 77.428774 | P10: 166450 | Q10: =(P10/$K10)*100 -> 24.949898 | R10: 67 | S10: =(R10/$K10)*100 -> 0.010042915
A11: Cordillera Administrative Region | B11: 116362 | C11: 29433 | D11: =(C11/$B11)*100 -> 25.29434 | E11: 86727 | F11: =(E11/$B11)*100 -> 74.532064 | G11: 26372 | H11: =(G11/$B11)*100 -> 22.663756 | I11: - | J11: =IFERROR((I11/$B11)*100,"-") -> - | K11: 62352 | L11: 17940 | M11: =(L11/$K11)*100 -> 28.772132 | N11: 49654 | O11: =(N11/$K11)*100 -> 79.634976 | P11: 10728 | Q11: =(P11/$K11)*100 -> 17.205543 | R11: 383 | S11: =(R11/$K11)*100 -> 0.61425455
A12: Region I - Ilocos Region | B12: 291371 | C12: 42040 | D12: =(C12/$B12)*100 -> 14.42834 | E12: 214846 | F12: =(E12/$B12)*100 -> 73.736233 | G12: 146709 | H12: =(G12/$B12)*100 -> 50.35127 | I12: 1115 | J12: =IFERROR((I12/$B12)*100,"-") -> 0.38267364 | K12: 119488 | L12: 32644 | M12: =(L12/$K12)*100 -> 27.319898 | N12: 95336 | O12: =(N12/$K12)*100 -> 79.787092 | P12: 32691 | Q12: =(P12/$K12)*100 -> 27.359233 | R12: 0 | S12: =(R12/$K12)*100 -> 0
A13: Region II - Cagayan Valley | B13: 146921 | C13: 25267 | D13: =(C13/$B13)*100 -> 17.197678 | E13: 113696 | F13: =(E13/$B13)*100 -> 77.385806 | G13: 27309 | H13: =(G13/$B13)*100 -> 18.58754 | I13: 1345 | J13: =IFERROR((I13/$B13)*100,"-") -> 0.91545797 | K13: 97834 | L13: 12578 | M13: =(L13/$K13)*100 -> 12.856471 | N13: 83606 | O13: =(N13/$K13)*100 -> 85.456999 | P13: 18056 | Q13: =(P13/$K13)*100 -> 18.455752 | R13: 0 | S13: =(R13/$K13)*100 -> 0
A14: Region III - Central Luzon | B14: 654747 | C14: 165868 | D14: =(C14/$B14)*100 -> 25.333144 | E14: 444351 | F14: =(E14/$B14)*100 -> 67.866061 | G14: 214727 | H14: =(G14/$B14)*100 -> 32.795416 | I14: - | J14: =IFERROR((I14/$B14)*100,"-") -> - | K14: 390356 | L14: 113732 | M14: =(L14/$K14)*100 -> 29.135456 | N14: 302263 | O14: =(N14/$K14)*100 -> 77.432651 | P14: 104432 | Q14: =(P14/$K14)*100 -> 26.753015 | R14: 1180 | S14: =(R14/$K14)*100 -> 0.30228817
A15: Region IV-A - CALABARZON | B15: 1488913 | C15: 315901 | D15: =(C15/$B15)*100 -> 21.216888 | E15: 745307 | F15: =(E15/$B15)*100 -> 50.057122 | G15: 847654 | H15: =(G15/$B15)*100 -> 56.931063 | I15: 324 | J15: =IFERROR((I15/$B15)*100,"-") -> 0.021760842 | K15: 580410 | L15: 207594 | M15: =(L15/$K15)*100 -> 35.766786 | N15: 433890 | O15: =(N15/$K15)*100 -> 74.755776 | P15: 144672 | Q15: =(P15/$K15)*100 -> 24.925828 | R15: 0 | S15: =(R15/$K15)*100 -> 0
A16: MIMAROPA Region | B16: 99090 | C16: 10111 | D16: =(C16/$B16)*100 -> 10.203855 | E16: 75268 | F16: =(E16/$B16)*100 -> 75.959229 | G16: 32627 | H16: =(G16/$B16)*100 -> 32.926632 | I16: 658 | J16: =IFERROR((I16/$B16)*100,"-") -> 0.66404279 | K16: 63200 | L16: 12484 | M16: =(L16/$K16)*100 -> 19.753165 | N16: 51680 | O16: =(N16/$K16)*100 -> 81.772152 | P16: 13552 | Q16: =(P16/$K16)*100 -> 21.443038 | R16: 297 | S16: =(R16/$K16)*100 -> 0.46993671
A17: Region V - Bicol Region | B17: 162411 | C17: 30424 | D17: =(C17/$B17)*100 -> 18.732721 | E17: 123591 | F17: =(E17/$B17)*100 -> 76.097678 | G17: 59931 | H17: =(G17/$B17)*100 -> 36.900826 | I17: 651 | J17: =IFERROR((I17/$B17)*100,"-") -> 0.40083492 | K17: 137805 | L17: 35824 | M17: =(L17/$K17)*100 -> 25.996154 | N17: 116821 | O17: =(N17/$K17)*100 -> 84.772686 | P17: 19355 | Q17: =(P17/$K17)*100 -> 14.045209 | R17: 548 | S17: =(R17/$K17)*100 -> 0.39766336
A18: Region VI - Western Visayas | B18: 281295 | C18: 66499 | D18: =(C18/$B18)*100 -> 23.640306 | E18: 187237 | F18: =(E18/$B18)*100 -> 66.562506 | G18: 116412 | H18: =(G18/$B18)*100 -> 41.384312 | I18: 399 | J18: =IFERROR((I18/$B18)*100,"-") -> 0.14184397 | K18: 129132 | L18: 33714 | M18: =(L18/$K18)*100 -> 26.108168 | N18: 112965 | O18: =(N18/$K18)*100 -> 87.480253 | P18: 20230 | Q18: =(P18/$K18)*100 -> 15.66614 | R18: 0 | S18: =(R18/$K18)*100 -> 0
A19: Region VII - Central Visayas | B19: 297076 | C19: 80646 | D19: =(C19/$B19)*100 -> 27.146589 | E19: 206775 | F19: =(E19/$B19)*100 -> 69.603401 | G19: 89778 | H19: =(G19/$B19)*100 -> 30.22055 | I19: 2588 | J19: =IFERROR((I19/$B19)*100,"-") -> 0.87115755 | K19: 189142 | L19: 71753 | M19: =(L19/$K19)*100 -> 37.936048 | N19: 149167 | O19: =(N19/$K19)*100 -> 78.865085 | P19: 44572 | Q19: =(P19/$K19)*100 -> 23.565364 | R19: 800 | S19: =(R19/$K19)*100 -> 0.42296264
A20: Region VIII - Eastern Visayas | B20: 148345 | C20: 24630 | D20: =(C20/$B20)*100 -> 16.603189 | E20: 112648 | F20: =(E20/$B20)*100 -> 75.936499 | G20: 47455 | H20: =(G20/$B20)*100 -> 31.989619 | I20: 958 | J20: =IFERROR((I20/$B20)*100,"-") -> 0.6457919 | K20: 71688 | L20: 13746 | M20: =(L20/$K20)*100 -> 19.174757 | N20: 60478 | O20: =(N20/$K20)*100 -> 84.362794 | P20: 15057 | Q20: =(P20/$K20)*100 -> 21.003515 | R20: 829 | S20: =(R20/$K20)*100 -> 1.1564
A21: Region IX - Zamboanga Peninsula | B21: 84974 | C21: 18459 | D21: =(C21/$B21)*100 -> 21.723115 | E21: 67399 | F21: =(E21/$B21)*100 -> 79.317203 | G21: 33108 | H21: =(G21/$B21)*100 -> 38.962506 | I21: 376 | J21: =IFERROR((I21/$B21)*100,"-") -> 0.44248829 | K21: 46837 | L21: 10407 | M21: =(L21/$K21)*100 -> 22.219613 | N21: 37665 | O21: =(N21/$K21)*100 -> 80.417192 | P21: 11452 | Q21: =(P21/$K21)*100 -> 24.450755 | R21: 0 | S21: =(R21/$K21)*100 -> 0
A22: Region X - Northern Mindanao | B22: 152576 | C22: 39845 | D22: =(C22/$B22)*100 -> 26.114854 | E22: 108913 | F22: =(E22/$B22)*100 -> 71.382786 | G22: 59259 | H22: =(G22/$B22)*100 -> 38.839005 | I22: - | J22: =IFERROR((I22/$B22)*100,"-") -> - | K22: 146395 | L22: 54281 | M22: =(L22/$K22)*100 -> 37.078452 | N22: 110136 | O22: =(N22/$K22)*100 -> 75.232078 | P22: 24656 | Q22: =(P22/$K22)*100 -> 16.842105 | R22: 495 | S22: =(R22/$K22)*100 -> 0.3381263
A23: Region XI - Davao Region | B23: 212526 | C23: 48679 | D23: =(C23/$B23)*100 -> 22.904962 | E23: 160423 | F23: =(E23/$B23)*100 -> 75.483941 | G23: 68103 | H23: =(G23/$B23)*100 -> 32.04455 | I23: 1719 | J23: =IFERROR((I23/$B23)*100,"-") -> 0.80884221 | K23: 100970 | L23: 26277 | M23: =(L23/$K23)*100 -> 26.024562 | N23: 76627 | O23: =(N23/$K23)*100 -> 75.890859 | P23: 18988 | Q23: =(P23/$K23)*100 -> 18.805586 | R23: 0 | S23: =(R23/$K23)*100 -> 0
A24: Region XII - SOCCSKSARGEN | B24: 162894 | C24: 39987 | D24: =(C24/$B24)*100 -> 24.547865 | E24: 118068 | F24: =(E24/$B24)*100 -> 72.481491 | G24: 42669 | H24: =(G24/$B24)*100 -> 26.194335 | I24: 5157 | J24: =IFERROR((I24/$B24)*100,"-") -> 3.1658625 | K24: 125471 | L24: 40141 | M24: =(L24/$K24)*100 -> 31.992253 | N24: 101281 | O24: =(N24/$K24)*100 -> 80.720645 | P24: 19329 | Q24: =(P24/$K24)*100 -> 15.405153 | R24: 0 | S24: =(R24/$K24)*100 -> 0
A25: Region XIII - Caraga | B25: 96216 | C25: 18854 | D25: =(C25/$B25)*100 -> 19.595493 | E25: 64238 | F25: =(E25/$B25)*100 -> 66.764364 | G25: 42814 | H25: =(G25/$B25)*100 -> 44.497797 | I25: 469 | J25: =IFERROR((I25/$B25)*100,"-") -> 0.48744492 | K25: 40695 | L25: 10902 | M25: =(L25/$K25)*100 -> 26.789532 | N25: 30807 | O25: =(N25/$K25)*100 -> 75.702175 | P25: 11523 | Q25: =(P25/$K25)*100 -> 28.315518 | R25: 0 | S25: =(R25/$K25)*100 -> 0
A26: Bangsamoro Autonomous Region in Muslim Mindanao | B26: 44261 | C26: 5276 | D26: =(C26/$B26)*100 -> 11.920201 | E26: 30120 | F26: =(E26/$B26)*100 -> 68.05088 | G26: 13934 | H26: =(G26/$B26)*100 -> 31.48144 | I26: - | J26: =IFERROR((I26/$B26)*100,"-") -> - | K26: 38074 | L26: 6115 | M26: =(L26/$K26)*100 -> 16.060829 | N26: 34741 | O26: =(N26/$K26)*100 -> 91.245995 | P26: 5720 | Q26: =(P26/$K26)*100 -> 15.023376 | R26: 0 | S26: =(R26/$K26)*100 -> 0
A29: Notes:
A30: Details may not add up to totals due to rounding.
A31: p Estimates are preliminary and may change
A32: r Revised
A33: Source of data: Philippine Statistics Authority, 2024 National Information and Communications Technology Household Survey.

Sheet c29_C31_a to C31_g
A1: BACK TO LIST
A2: Table #. Number and Proportion of Households Accessing a Computer by Alternative Access Method and Region, Philippines: 2019 and 2024p
A4: Region | B4: 2019 | M4: 2024
B5: Total Households | C5: Alternative Access Method | M5: Total Households | N5: Alternative Access Method
C6: School/Work | E6: Relatives/ Friends/Neighbors | G6: Barangay/ Community Computers | I6: Computer Shops | K6: Others | N6: School | P6: Work | R6: Relatives/ Friends/Neighbors | T6: Barangay/ Community Computers | V6: Computer Shops | X6: Pisonet | Z6: Others
C7: Number | D7: Proportion | E7: Number | F7: Proportion | G7: Number | H7: Proportion | I7: Number | J7: Proportion | K7: Number | L7: Proportion | N7: Number | O7: Proportion | P7: Number | Q7: Proportion | R7: Number | S7: Proportion | T7: Number | U7: Proportion | V7: Number | W7: Proportion | X7: Number | Y7: Proportion | Z7: Number | AA7: Proportion
A9: PHILIPPINES | B9: ='Estimated Totals'!B7 -> 23360960 | C9: 3672255 | D9: =(C9/$B9)*100 -> 15.719624 | E9: 1406742 | F9: =(E9/$B9)*100 -> 6.0217645 | G9: 273362 | H9: =(G9/$B9)*100 -> 1.170166 | I9: 8137749 | J9: =(I9/$B9)*100 -> 34.834823 | K9: 609873 | L9: =(K9/$B9)*100 -> 2.6106504 | M9: 27793884 | N9: 5259073 | O9: =(N9/$M9)*100 -> 18.921692 | P9: 5477573 | Q9: =(P9/$M9)*100 -> 19.707836 | R9: 4419694 | S9: =(R9/$M9)*100 -> 15.901678 | T9: 858483 | U9: =(T9/$M9)*100 -> 3.0887479 | V9: 4853300 | W9: =(V9/$M9)*100 -> 17.461755 | X9: 4012681 | Y9: =(X9/$M9)*100 -> 14.437281 | Z9: 181993 | AA9: =(Z9/$M9)*100 -> 0.65479513
A10: National Capital Region | B10: ='Estimated Totals'!B8 -> 3009545 | C10: 529212 | D10: =(C10/$B10)*100 -> 17.584452 | E10: 183393 | F10: =(E10/$B10)*100 -> 6.0937118 | G10: 11333 | H10: =(G10/$B10)*100 -> 0.37656855 | I10: 1202151 | J10: =(I10/$B10)*100 -> 39.94461 | K10: 72812 | L10: =(K10/$B10)*100 -> 2.419369 | M10: 3667731 | N10: 539224 | O10: =(N10/$M10)*100 -> 14.701842 | P10: 1251863 | Q10: =(P10/$M10)*100 -> 34.131811 | R10: 617584 | S10: =(R10/$M10)*100 -> 16.838312 | T10: 51408 | U10: =(T10/$M10)*100 -> 1.4016295 | V10: 662537 | W10: =(V10/$M10)*100 -> 18.063947 | X10: 387450 | Y10: =(X10/$M10)*100 -> 10.563752 | Z10: 1044 | AA10: =(Z10/$M10)*100 -> 0.028464465
A11: Cordillera Administrative Region | B11: ='Estimated Totals'!B9 -> 388188 | C11: 77139 | D11: =(C11/$B11)*100 -> 19.871557 | E11: 6215 | F11: =(E11/$B11)*100 -> 1.6010284 | G11: 18806 | H11: =(G11/$B11)*100 -> 4.8445599 | I11: 106880 | J11: =(I11/$B11)*100 -> 27.533051 | K11: 6592 | L11: =(K11/$B11)*100 -> 1.6981463 | M11: 468413 | N11: 114311 | O11: =(N11/$M11)*100 -> 24.403891 | P11: 85212 | Q11: =(P11/$M11)*100 -> 18.191639 | R11: 130465 | S11: =(R11/$M11)*100 -> 27.852557 | T11: 44615 | U11: =(T11/$M11)*100 -> 9.5247143 | V11: 94151 | W11: =(V11/$M11)*100 -> 20.099997 | X11: 26319 | Y11: =(X11/$M11)*100 -> 5.6187595 | Z11: 359 | AA11: =(Z11/$M11)*100 -> 0.076641767
A12: Region I - Ilocos Region | B12: ='Estimated Totals'!B10 -> 1250337 | C12: 131179 | D12: =(C12/$B12)*100 -> 10.491491 | E12: 100036 | F12: =(E12/$B12)*100 -> 8.000723 | G12: 2212 | H12: =(G12/$B12)*100 -> 0.1769123 | I12: 454726 | J12: =(I12/$B12)*100 -> 36.368275 | K12: 55347 | L12: =(K12/$B12)*100 -> 4.4265666 | M12: 1316881 | N12: 365440 | O12: =(N12/$M12)*100 -> 27.750419 | P12: 274078 | Q12: =(P12/$M12)*100 -> 20.812663 | R12: 351369 | S12: =(R12/$M12)*100 -> 26.68191 | T12: 126549 | U12: =(T12/$M12)*100 -> 9.6097521 | V12: 426762 | W12: =(V12/$M12)*100 -> 32.407028 | X12: 53196 | Y12: =(X12/$M12)*100 -> 4.039545 | Z12: 0 | AA12: =(Z12/$M12)*100 -> 0
A13: Region II - Cagayan Valley | B13: ='Estimated Totals'!B11 -> 855893 | C13: 83914 | D13: =(C13/$B13)*100 -> 9.8042629 | E13: 39942 | F13: =(E13/$B13)*100 -> 4.6667048 | G13: 35092 | H13: =(G13/$B13)*100 -> 4.1000452 | I13: 392258 | J13: =(I13/$B13)*100 -> 45.830261 | K13: 15761 | L13: =(K13/$B13)*100 -> 1.8414685 | M13: 934252 | N13: 241421 | O13: =(N13/$M13)*100 -> 25.841101 | P13: 155188 | Q13: =(P13/$M13)*100 -> 16.610936 | R13: 155267 | S13: =(R13/$M13)*100 -> 16.619392 | T13: 29258 | U13: =(T13/$M13)*100 -> 3.1317032 | V13: 164899 | W13: =(V13/$M13)*100 -> 17.650377 | X13: 28020 | Y13: =(X13/$M13)*100 -> 2.9991908 | Z13: 11367 | AA13: =(Z13/$M13)*100 -> 1.2166953
A14: Region III - Central Luzon | B14: ='Estimated Totals'!B12 -> 2823200 | C14: 270128 | D14: =(C14/$B14)*100 -> 9.5681496 | E14: 195663 | F14: =(E14/$B14)*100 -> 6.9305398 | G14: 31114 | H14: =(G14/$B14)*100 -> 1.1020827 | I14: 877237 | J14: =(I14/$B14)*100 -> 31.072436 | K14: 6160 | L14: =(K14/$B14)*100 -> 0.21819212 | M14: 3161851 | N14: 543172 | O14: =(N14/$M14)*100 -> 17.178925 | P14: 546460 | Q14: =(P14/$M14)*100 -> 17.282914 | R14: 545151 | S14: =(R14/$M14)*100 -> 17.241515 | T14: 74043 | U14: =(T14/$M14)*100 -> 2.3417612 | V14: 459584 | W14: =(V14/$M14)*100 -> 14.535283 | X14: 163743 | Y14: =(X14/$M14)*100 -> 5.178707 | Z14: 26133 | AA14: =(Z14/$M14)*100 -> 0.82650954
A15: Region IV-A - CALABARZON | B15: ='Estimated Totals'!B13 -> 3486186 | C15: 714557 | D15: =(C15/$B15)*100 -> 20.496812 | E15: 266782 | F15: =(E15/$B15)*100 -> 7.6525464 | G15: 2205 | H15: =(G15/$B15)*100 -> 0.063249637 | I15: 1646400 | J15: =(I15/$B15)*100 -> 47.226396 | K15: 94218 | L15: =(K15/$B15)*100 -> 2.7026097 | M15: 4369198 | N15: 828096 | O15: =(N15/$M15)*100 -> 18.953044 | P15: 1011162 | Q15: =(P15/$M15)*100 -> 23.142966 | R15: 827369 | S15: =(R15/$M15)*100 -> 18.936404 | T15: 111048 | U15: =(T15/$M15)*100 -> 2.5416106 | V15: 747237 | W15: =(V15/$M15)*100 -> 17.102384 | X15: 506128 | Y15: =(X15/$M15)*100 -> 11.584002 | Z15: 1850 | AA15: =(Z15/$M15)*100 -> 0.042341867
A16: MIMAROPA Region | B16: ='Estimated Totals'!B14 -> 686916 | C16: 229378 | D16: =(C16/$B16)*100 -> 33.392438 | E16: 26982 | F16: =(E16/$B16)*100 -> 3.9279912 | G16: 5658 | H16: =(G16/$B16)*100 -> 0.8236815 | I16: 164601 | J16: =(I16/$B16)*100 -> 23.962319 | K16: 33633 | L16: =(K16/$B16)*100 -> 4.8962319 | M16: 828498 | N16: 191872 | O16: =(N16/$M16)*100 -> 23.159018 | P16: 148661 | Q16: =(P16/$M16)*100 -> 17.943435 | R16: 122809 | S16: =(R16/$M16)*100 -> 14.823089 | T16: 31253 | U16: =(T16/$M16)*100 -> 3.7722481 | V16: 163396 | W16: =(V16/$M16)*100 -> 19.721955 | X16: 90439 | Y16: =(X16/$M16)*100 -> 10.916019 | Z16: 3513 | AA16: =(Z16/$M16)*100 -> 0.42402034
A17: Region V - Bicol Region | B17: ='Estimated Totals'!B15 -> 1030986 | C17: 111995 | D17: =(C17/$B17)*100 -> 10.862902 | E17: 18074 | F17: =(E17/$B17)*100 -> 1.7530791 | G17: 5013 | H17: =(G17/$B17)*100 -> 0.48623357 | I17: 180200 | J17: =(I17/$B17)*100 -> 17.478414 | K17: 164826 | L17: =(K17/$B17)*100 -> 15.98722 | M17: 1384033 | N17: 256214 | O17: =(N17/$M17)*100 -> 18.512131 | P17: 193053 | Q17: =(P17/$M17)*100 -> 13.948584 | R17: 130125 | S17: =(R17/$M17)*100 -> 9.4018712 | T17: 28223 | U17: =(T17/$M17)*100 -> 2.0391855 | V17: 214876 | W17: =(V17/$M17)*100 -> 15.525352 | X17: 167724 | Y17: =(X17/$M17)*100 -> 12.118497 | Z17: 13755 | AA17: =(Z17/$M17)*100 -> 0.99383468
A18: Region VI - Western Visayas | B18: ='Estimated Totals'!B16 -> 1705556 | C18: 315566 | D18: =(C18/$B18)*100 -> 18.502236 | E18: 211556 | F18: =(E18/$B18)*100 -> 12.403932 | G18: 15906 | H18: =(G18/$B18)*100 -> 0.93259911 | I18: 483299 | J18: =(I18/$B18)*100 -> 28.336742 | K18: 11322 | L18: =(K18/$B18)*100 -> 0.66383045 | M18: 2040922 | N18: 417834 | O18: =(N18/$M18)*100 -> 20.472806 | P18: 334031 | Q18: =(P18/$M18)*100 -> 16.366672 | R18: 292385 | S18: =(R18/$M18)*100 -> 14.326123 | T18: 104849 | U18: =(T18/$M18)*100 -> 5.137335 | V18: 392816 | W18: =(V18/$M18)*100 -> 19.246987 | X18: 341235 | Y18: =(X18/$M18)*100 -> 16.719649 | Z18: 28008 | AA18: =(Z18/$M18)*100 -> 1.3723209
A19: Region VII - Central Visayas | B19: ='Estimated Totals'!B17 -> 1820052 | C19: 112293 | D19: =(C19/$B19)*100 -> 6.1697688 | E19: 49979 | F19: =(E19/$B19)*100 -> 2.7460204 | G19: 16358 | H19: =(G19/$B19)*100 -> 0.89876553 | I19: 651950 | J19: =(I19/$B19)*100 -> 35.820405 | K19: 4182 | L19: =(K19/$B19)*100 -> 0.22977365 | M19: 2077216 | N19: 447157 | O19: =(N19/$M19)*100 -> 21.526745 | P19: 459695 | Q19: =(P19/$M19)*100 -> 22.130342 | R19: 283197 | S19: =(R19/$M19)*100 -> 13.633488 | T19: 56333 | U19: =(T19/$M19)*100 -> 2.7119471 | V19: 417045 | W19: =(V19/$M19)*100 -> 20.077113 | X19: 463348 | Y19: =(X19/$M19)*100 -> 22.306202 | Z19: 16363 | AA19: =(Z19/$M19)*100 -> 0.78773705
A20: Region VIII - Eastern Visayas | B20: ='Estimated Totals'!B18 -> 1042723 | C20: 187452 | D20: =(C20/$B20)*100 -> 17.977162 | E20: 23635 | F20: =(E20/$B20)*100 -> 2.2666614 | G20: 4245 | H20: =(G20/$B20)*100 -> 0.40710716 | I20: 279829 | J20: =(I20/$B20)*100 -> 26.83637 | K20: 62382 | L20: =(K20/$B20)*100 -> 5.9826052 | M20: 1200913 | N20: 203525 | O20: =(N20/$M20)*100 -> 16.947522 | P20: 194687 | Q20: =(P20/$M20)*100 -> 16.211582 | R20: 55357 | S20: =(R20/$M20)*100 -> 4.6095762 | T20: 20929 | U20: =(T20/$M20)*100 -> 1.7427574 | V20: 173735 | W20: =(V20/$M20)*100 -> 14.46691 | X20: 209601 | Y20: =(X20/$M20)*100 -> 17.453471 | Z20: 38353 | AA20: =(Z20/$M20)*100 -> 3.1936535
... A26: Bangsamoro Autonomous Region in Muslim Mindanao | B26: ='Estimated Totals'!B24 -> 521349 | C26: 60274 | D26: =(C26/$B26)*100 -> 11.561162 | E26: 50696 | F26: =(E26/$B26)*100 -> 9.7240045 | G26: 35344 | H26: =(G26/$B26)*100 -> 6.7793359 | I26: 145577 | J26: =(I26/$B26)*100 -> 27.923138 | K26: 1480 | L26: =(K26/$B26)*100 -> 0.28387894 | M26: 846042 | N26: 84069 | O26: =(N26/$M26)*100 -> 9.9367407 | P26: 60758 | Q26: =(P26/$M26)*100 -> 7.1814402 | R26: 115285 | S26: =(R26/$M26)*100 -> 13.626392 | T26: 27907 | U26: =(T26/$M26)*100 -> 3.298536 | V26: 71137 | W26: =(V26/$M26)*100 -> 8.4082114 | X26: 223869 | Y26: =(X26/$M26)*100 -> 26.460743 | Z26: 8743 | AA26: =(Z26/$M26)*100 -> 1.0334002
A29: Notes:
A30: Details may not add up to totals due to rounding.
A31: p Estimates are preliminary and may change
A32: Source of data: Philippine Statistics Authority, 2024 National Information and Communications Technology Household Survey.

Sheet i_C17-18
A1: BACK TO LIST
A2: Table #. Number and Proportion of Individuals and Computer Users by Type of Computer and Region, Philippines: 2019r and 2024p
A4: Region | B4: 2019 | K4: 2024
B5: Total Individuals | C5: Computer Users | E5: Type of Computer | K5: Total Individuals | L5: Computer Users | N5: Type of Computer
E6: Desktop | G6: Laptop | I6: Tablet | N6: Desktop | P6: Laptop | R6: Tablet
C7: Number | D7: Proportion | E7: Number | F7: Proportion | G7: Number | H7: Proportion | I7: Number | J7: Proportion | L7: Number | M7: Proportion | N7: Number | O7: Proportion | P7: Number | Q7: Proportion | R7: Number | S7: Proportion
A9: PHILIPPINES | B9: ='Estimated Totals'!D7 -> 83258836 | C9: 15284052 | D9: =(C9/$B9)*100 -> 18.357273 | E9: 8622071 | F9: =(E9/$C9)*100 -> 56.412207 | G9: 6023599 | H9: =(G9/$C9)*100 -> 39.411008 | I9: 3413144 | J9: =(I9/$C9)*100 -> 22.331408 | K9: 91383228 | L9: 16326632 | M9: =(L9/K9)*100 -> 17.866115 | N9: 8080340.9 | O9: =(N9/$L9)*100 -> 49.49178 | P9: 11005037 | Q9: =(P9/$L9)*100 -> 67.405434 | R9: 2266916.9 | S9: =(R9/$L9)*100 -> 13.88478
A10: National Capital Region | B10: ='Estimated Totals'!D8 -> 11005073 | C10: 3374600 | D10: =(C10/$B10)*100 -> 30.66404 | E10: 2242936 | F10: =(E10/$C10)*100 -> 66.46524 | G10: 1460132 | H10: =(G10/$C10)*100 -> 43.268298 | I10: 452767 | J10: =(I10/$C10)*100 -> 13.416909 | K10: 11919468 | L10: 3504411.1 | M10: =(L10/K10)*100 -> 29.400734 | N10: 1603100.7 | O10: =(N10/$L10)*100 -> 45.745225 | P10: 2401785.9 | Q10: =(P10/$L10)*100 -> 68.536078 | R10: 592359.16 | S10: =(R10/$L10)*100 -> 16.903244
A11: Cordillera Administrative Region | B11: ='Estimated Totals'!D9 -> 1394660 | C11: 217204 | D11: =(C11/$B11)*100 -> 15.573975 | E11: 110168 | F11: =(E11/$C11)*100 -> 50.720981 | G11: 119816 | H11: =(G11/$C11)*100 -> 55.162888 | I11: 21908 | J11: =(I11/$C11)*100 -> 10.08637 | K11: 1496049 | L11: 311851.82 | M11: =(L11/K11)*100 -> 20.845028 | N11: 150470.27 | O11: =(N11/$L11)*100 -> 48.250565 | P11: 215407.15 | Q11: =(P11/$L11)*100 -> 69.073557 | R11: 36987.28 | S11: =(R11/$L11)*100 -> 11.86053
A12: Region I - Ilocos Region | B12: ='Estimated Totals'!D10 -> 4063052 | C12: 609906 | D12: =(C12/$B12)*100 -> 15.011031 | E12: 267617 | F12: =(E12/$C12)*100 -> 43.878401 | G12: 295684 | H12: =(G12/$C12)*100 -> 48.480258 | I12: 143984 | J12: =(I12/$C12)*100 -> 23.607572 | K12: 4389510 | L12: 653858.69 | M12: =(L12/K12)*100 -> 14.895938 | N12: 330361.26 | O12: =(N12/$L12)*100 -> 50.524871 | P12: 397762.13 | Q12: =(P12/$L12)*100 -> 60.833041 | R12: 122017.19 | S12: =(R12/$L12)*100 -> 18.661095
A13: Region II - Cagayan Valley | B13: ='Estimated Totals'!D11 -> 2820240 | C13: 440791 | D13: =(C13/$B13)*100 -> 15.629556 | E13: 177313 | F13: =(E13/$C13)*100 -> 40.226094 | G13: 246578 | H13: =(G13/$C13)*100 -> 55.93989 | I13: 61690 | J13: =(I13/$C13)*100 -> 13.995295 | K13: 3055894 | L13: 524739.25 | M13: =(L13/K13)*100 -> 17.171383 | N13: 205036.52 | O13: =(N13/$L13)*100 -> 39.073981 | P13: 404639.81 | Q13: =(P13/$L13)*100 -> 77.112549 | R13: 75819.498 | S13: =(R13/$L13)*100 -> 14.448985
A14: Region III - Central Luzon | B14: ='Estimated Totals'!D12 -> 9585315 | C14: 1649861 | D14: =(C14/$B14)*100 -> 17.212382 | E14: 712611 | F14: =(E14/$C14)*100 -> 43.192184 | G14: 719687 | H14: =(G14/$C14)*100 -> 43.621069 | I14: 346909 | J14: =(I14/$C14)*100 -> 21.026559 | K14: 10708290 | L14: 1897999.7 | M14: =(L14/K14)*100 -> 17.724582 | N14: 794966.38 | O14: =(N14/$L14)*100 -> 41.884432 | P14: 1415988.4 | Q14: =(P14/$L14)*100 -> 74.604249 | R14: 285725.68 | S14: =(R14/$L14)*100 -> 15.054042
A15: Region IV-A - CALABARZON | B15: ='Estimated Totals'!D13 -> 12457452 | C15: 3620392 | D15: =(C15/$B15)*100 -> 29.062059 | E15: 1832090 | F15: =(E15/$C15)*100 -> 50.604741 | G15: 1117351 | H15: =(G15/$C15)*100 -> 30.862708 | I15: 1336101 | J15: =(I15/$C15)*100 -> 36.904871 | K15: 13985526 | L15: 3038614.7 | M15: =(L15/K15)*100 -> 21.726853 | N15: 1788097.5 | O15: =(N15/$L15)*100 -> 58.845813 | P15: 1987090.4 | Q15: =(P15/$L15)*100 -> 65.394616 | R15: 406081.51 | S15: =(R15/$L15)*100 -> 13.364034
A16: MIMAROPA Region | B16: ='Estimated Totals'!D14 -> 2347582 | C16: 343371 | D16: =(C16/$B16)*100 -> 14.626582 | E16: 207659 | F16: =(E16/$C16)*100 -> 60.476569 | G16: 147945 | H16: =(G16/$C16)*100 -> 43.08605 | I16: 54275 | J16: =(I16/$C16)*100 -> 15.806518 | K16: 2538126 | L16: 371869.66 | M16: =(L16/K16)*100 -> 14.651347 | N16: 159364.31 | O16: =(N16/$L16)*100 -> 42.854884 | P16: 285951.89 | Q16: =(P16/$L16)*100 -> 76.895729 | R16: 59661.999 | S16: =(R16/$L16)*100 -> 16.043793
A17: Region V - Bicol Region | B17: ='Estimated Totals'!D15 -> 4528646 | C17: 745745 | D17: =(C17/$B17)*100 -> 16.467284 | E17: 408901 | F17: =(E17/$C17)*100 -> 54.831209 | G17: 348640 | H17: =(G17/$C17)*100 -> 46.750565 | I17: 205262 | J17: =(I17/$C17)*100 -> 27.524422 | K17: 4884805 | L17: 665051.18 | M17: =(L17/K17)*100 -> 13.614693 | N17: 299027.72 | O17: =(N17/$L17)*100 -> 44.963113 | P17: 485918.26 | Q17: =(P17/$L17)*100 -> 73.064792 | R17: 69860.057 | S17: =(R17/$L17)*100 -> 10.504463
A18: Region VI - Western Visayas | B18: ='Estimated Totals'!D16 -> 6087553 | C18: 728694 | D18: =(C18/$B18)*100 -> 11.970228 | E18: 376364 | F18: =(E18/$C18)*100 -> 51.649115 | G18: 312758 | H18: =(G18/$C18)*100 -> 42.920348 | I18: 189190 | J18: =(I18/$C18)*100 -> 25.962887 | K18: 6586874 | L18: 881483.55 | M18: =(L18/K18)*100 -> 13.382426 | N18: 483426.8 | O18: =(N18/$L18)*100 -> 54.842408 | P18: 549641.09 | Q18: =(P18/$L18)*100 -> 62.354095 | R18: 119386 | S18: =(R18/$L18)*100 -> 13.543758
A19: Region VII - Central Visayas | B19: ='Estimated Totals'!D17 -> 6058752 | C19: 592764 | D19: =(C19/$B19)*100 -> 9.783599 | E19: 414209 | F19: =(E19/$C19)*100 -> 69.877557 | G19: 192250 | H19: =(G19/$C19)*100 -> 32.432806 | I19: 118727 | J19: =(I19/$C19)*100 -> 20.029388 | K19: 6668940 | L19: 1377557.4 | M19: =(L19/K19)*100 -> 20.656318 | N19: 793909.03 | O19: =(N19/$L19)*100 -> 57.631646 | P19: 821616.72 | Q19: =(P19/$L19)*100 -> 59.64301 | R19: 135424.26 | S19: =(R19/$L19)*100 -> 9.8307521
A20: Region VIII - Eastern Visayas | B20: ='Estimated Totals'!D18 -> 3529248 | C20: 633212 | D20: =(C20/$B20)*100 -> 17.941839 | E20: 338824 | F20: =(E20/$C20)*100 -> 53.508777 | G20: 278624 | H20: =(G20/$C20)*100 -> 44.001693 | I20: 92424 | J20: =(I20/$C20)*100 -> 14.596059 | K20: 3864215 | L20: 578535.47 | M20: =(L20/K20)*100 -> 14.971617 | N20: 229353.02 | O20: =(N20/$L20)*100 -> 39.643726 | P20: 434975.62 | Q20: =(P20/$L20)*100 -> 75.185643 | R20: 58312.78 | S20: =(R20/$L20)*100 -> 10.079379
... A26: Bangsamoro Autonomous Region in Muslim Mindanao | B26: ='Estimated Totals'!D24 -> 2943119 | C26: 101218 | D26: =(C26/$B26)*100 -> 3.4391406 | E26: 18044 | F26: =(E26/$C26)*100 -> 17.826869 | G26: 51811 | H26: =(G26/$C26)*100 -> 51.187536 | I26: 38141 | J26: =(I26/$C26)*100 -> 37.682033 | K26: 3746618 | L26: 209771.24 | M26: =(L26/K26)*100 -> 5.5989492 | N26: 79110.201 | O26: =(N26/$L26)*100 -> 37.712606 | P26: 162121.07 | Q26: =(P26/$L26)*100 -> 77.284698 | R26: 16852.55 | S26: =(R26/$L26)*100 -> 8.0337754
A29: Notes:
A30: Details may not add up to totals due to rounding.
A31: p Estimates are preliminary and may change
A32: r Revised
A33: Source of data: Philippine Statistics Authority, 2024 National Information and Communications Technology Household Survey.

Sheet i_C17&20
A1: BACK TO LIST
A2: Table #. Number and Proportion of Individuals Using Computer by Activity and Region, Philippines: 2019r and 2024p
A4: Region | B4: 2019
B5: Computer Users | C5: Computer-Related Activities Performed
C6: Communication | E6: Entertainment and Gaming | G6: Distance/Online/ Computer-Aided Learning | I6: Using Copy and Paste Tools to Duplicate/Move Information (Files/Folder) | K6: Transferring Files Between a Computer and Other Devices | M6: Sending Emails (Text) | O6: Sending Emails with Attached Files (Document, Picture, Video) | Q6: Data Encoding | S6: Finding, Downloading, Installing and/or Configuring Software | U6: Running Software Program | W6: Using Basic Arithmetic Formula in a Spreadsheet | Y6: Creating Documents Using a Word Processing Software | AA6: Creating Electronic Presentations with Software | AC6: Data Management and Analysis | AE6: Using Modelling, Simulation and Rendering Software | AG6: Others
C7: Number | D7: Proportion | E7: Number | F7: Proportion | G7: Number | H7: Proportion | I7: Number | J7: Proportion | K7: Number | L7: Proportion | M7: Number | N7: Proportion | O7: Number | P7: Proportion | Q7: Number | R7: Proportion | S7: Number | T7: Proportion | U7: Number | V7: Proportion | W7: Number | X7: Proportion | Y7: Number | Z7: Proportion | AA7: Number | AB7: Proportion | AC7: Number | AD7: Proportion | AE7: Number | AF7: Proportion | AG7: Number | AH7: Proportion
A9: PHILIPPINES | B9: ='i_C17-18'!C9 -> 15284052 | C9: 10545681 | D9: =C9/$B9*100 -> 68.99794 | E9: 9695003 | F9: =E9/$B9*100 -> 63.432151 | G9: 3376591 | H9: =G9/$B9*100 -> 22.09225 | I9: 3495847 | J9: =I9/$B9*100 -> 22.872514 | K9: 3052761 | L9: =K9/$B9*100 -> 19.973506 | M9: 3524228 | N9: =M9/$B9*100 -> 23.058205 | O9: 3488633 | P9: =O9/$B9*100 -> 22.825315 | Q9: 3290438 | R9: =Q9/$B9*100 -> 21.528571 | S9: 1485792 | T9: =S9/$B9*100 -> 9.7211917 | U9: 691901 | V9: =U9/$B9*100 -> 4.5269474 | W9: 973492 | X9: =W9/$B9*100 -> 6.3693319 | Y9: 2722971 | Z9: =Y9/$B9*100 -> 17.815766 | AA9: 1237849 | AB9: =AA9/$B9*100 -> 8.0989583 | AC9: 659812 | AD9: =AC9/$B9*100 -> 4.3169966 | AE9: 26058 | AF9: =AE9/$B9*100 -> 0.17049144 | AG9: 33974 | AH9: =AG9/$B9*100 -> 0.22228399
A10: National Capital Region | B10: ='i_C17-18'!C10 -> 3374600 | C10: 2598891 | D10: =C10/$B10*100 -> 77.013305 | E10: 2428605 | F10: =E10/$B10*100 -> 71.967196 | G10: 805310 | H10: =G10/$B10*100 -> 23.863865 | I10: 734384 | J10: =I10/$B10*100 -> 21.762105 | K10: 600474 | L10: =K10/$B10*100 -> 17.793931 | M10: 839946 | N10: =M10/$B10*100 -> 24.890239 | O10: 960059 | P10: =O10/$B10*100 -> 28.449564 | Q10: 242281 | R10: =Q10/$B10*100 -> 7.1795472 | S10: 196596 | T10: =S10/$B10*100 -> 5.8257571 | U10: 117653 | V10: =U10/$B10*100 -> 3.486428 | W10: 99394 | X10: =W10/$B10*100 -> 2.9453565 | Y10: 355004 | Z10: =Y10/$B10*100 -> 10.519884 | AA10: 183429 | AB10: =AA10/$B10*100 -> 5.4355775 | AC10: 90483 | AD10: =AC10/$B10*100 -> 2.6812956 | AE10: 26058 | AF10: =AE10/$B10*100 -> 0.77218041 | AG10: 33974 | AH10: =AG10/$B10*100 -> 1.0067564
A11: Cordillera Administrative Region | B11: ='i_C17-18'!C11 -> 217204 | C11: 103570 | D11: =C11/$B11*100 -> 47.683284 | E11: 105870 | F11: =E11/$B11*100 -> 48.742196 | G11: 18835 | H11: =G11/$B11*100 -> 8.6715714 | I11: 40124 | J11: =I11/$B11*100 -> 18.472956 | K11: 28765 | L11: =K11/$B11*100 -> 13.24331 | M11: 19783 | N11: =M11/$B11*100 -> 9.1080275 | O11: 13271 | P11: =O11/$B11*100 -> 6.1099243 | Q11: 108898 | R11: =Q11/$B11*100 -> 50.136277 | S11: 17171 | T11: =S11/$B11*100 -> 7.9054714 | U11: 5897 | V11: =U11/$B11*100 -> 2.7149592 | W11: 1475 | X11: =W11/$B11*100 -> 0.6790851 | Y11: 41075 | Z11: =Y11/$B11*100 -> 18.910794 | AA11: 10829 | AB11: =AA11/$B11*100 -> 4.9856356 | AC11: 2490 | AD11: =AC11/$B11*100 -> 1.1463877 | AE11: 650 | AF11: =AE11/$B11*100 -> 0.29925784 | AG11: 3898 | AH11: =AG11/$B11*100 -> 1.7946263
A12: Region I - Ilocos Region | B12: ='i_C17-18'!C12 -> 609906 | C12: 403348 | D12: =C12/$B12*100 -> 66.132814 | E12: 383928 | F12: =E12/$B12*100 -> 62.948717 | G12: 136720 | H12: =G12/$B12*100 -> 22.416569 | I12: 117823 | J12: =I12/$B12*100 -> 19.318223 | K12: 134230 | L12: =K12/$B12*100 -> 22.008309 | M12: 219098 | N12: =M12/$B12*100 -> 35.923241 | O12: 199100 | P12: =O12/$B12*100 -> 32.644375 | Q12: 239854 | R12: =Q12/$B12*100 -> 39.326388 | S12: 84277 | T12: =S12/$B12*100 -> 13.818031 | U12: 12159 | V12: =U12/$B12*100 -> 1.9935859 | W12: 29449 | X12: =W12/$B12*100 -> 4.828449 | Y12: 52594 | Z12: =Y12/$B12*100 -> 8.623296 | AA12: 31229 | AB12: =AA12/$B12*100 -> 5.1202972 | AC12: 21084 | AD12: =AC12/$B12*100 -> 3.4569261 | AE12: 6200 | AF12: =AE12/$B12*100 -> 1.0165501 | AG12: 1432 | AH12: =AG12/$B12*100 -> 0.23479028
A13: Region II - Cagayan Valley | B13: ='i_C17-18'!C13 -> 440791 | C13: 183592 | D13: =C13/$B13*100 -> 41.650578 | E13: 174930 | F13: =E13/$B13*100 -> 39.685475 | G13: 59974 | H13: =G13/$B13*100 -> 13.605995 | I13: 130463 | J13: =I13/$B13*100 -> 29.597474 | K13: 94766 | L13: =K13/$B13*100 -> 21.499078 | M13: 66346 | N13: =M13/$B13*100 -> 15.051578 | O13: 40911 | P13: =O13/$B13*100 -> 9.2812694 | Q13: 162716 | R13: =Q13/$B13*100 -> 36.914547 | S13: 34502 | T13: =S13/$B13*100 -> 7.8272923 | U13: 21128 | V13: =U13/$B13*100 -> 4.7932013 | W13: 9951 | X13: =W13/$B13*100 -> 2.2575325 | Y13: 36624 | Z13: =Y13/$B13*100 -> 8.3086996 | AA13: 18487 | AB13: =AA13/$B13*100 -> 4.1940511 | AC13: 14776 | AD13: =AC13/$B13*100 -> 3.3521556 | AE13: 782 | AF13: =AE13/$B13*100 -> 0.17740834 | AG13: 1749 | AH13: =AG13/$B13*100 -> 0.39678669
A14: Region III - Central Luzon | B14: ='i_C17-18'!C14 -> 1649861 | C14: 1260260 | D14: =C14/$B14*100 -> 76.385829 | E14: 1149982 | F14: =E14/$B14*100 -> 69.701751 | G14: 643826 | H14: =G14/$B14*100 -> 39.023045 | I14: 320858 | J14: =I14/$B14*100 -> 19.447578 | K14: 310563 | L14: =K14/$B14*100 -> 18.823586 | M14: 318499 | N14: =M14/$B14*100 -> 19.304596 | O14: 323721 | P14: =O14/$B14*100 -> 19.621107 | Q14: 376537 | R14: =Q14/$B14*100 -> 22.822347 | S14: 154600 | T14: =S14/$B14*100 -> 9.3704864 | U14: 59742 | V14: =U14/$B14*100 -> 3.6210323 | W14: 97166 | X14: =W14/$B14*100 -> 5.8893446 | Y14: 245987 | Z14: =Y14/$B14*100 -> 14.909559 | AA14: 122038 | AB14: =AA14/$B14*100 -> 7.3968656 | AC14: 126469 | AD14: =AC14/$B14*100 -> 7.6654336 | AE14: 15813 | AF14: =AE14/$B14*100 -> 0.95844438 | AG14: 15419 | AH14: =AG14/$B14*100 -> 0.93456358
A15: Region IV-A - CALABARZON | B15: ='i_C17-18'!C15 -> 3620392 | C15: 2620223 | D15: =C15/$B15*100 -> 72.374014 | E15: 2252776 | F15: =E15/$B15*100 -> 62.224643 | G15: 790133 | H15: =G15/$B15*100 -> 21.824515 | I15: 947194 | J15: =I15/$B15*100 -> 26.162747 | K15: 861027 | L15: =K15/$B15*100 -> 23.782701 | M15: 1043659 | N15: =M15/$B15*100 -> 28.827237 | O15: 887292 | P15: =O15/$B15*100 -> 24.508175 | Q15: 618053 | R15: =Q15/$B15*100 -> 17.071439 | S15: 576553 | T15: =S15/$B15*100 -> 15.925154 | U15: 276595 | V15: =U15/$B15*100 -> 7.6399185 | W15: 378231 | X15: =W15/$B15*100 -> 10.447239 | Y15: 1032278 | Z15: =Y15/$B15*100 -> 28.512879 | AA15: 563361 | AB15: =AA15/$B15*100 -> 15.560774 | AC15: 268881 | AD15: =AC15/$B15*100 -> 7.4268477 | AE15: 265131 | AF15: =AE15/$B15*100 -> 7.3232678 | AG15: 125789 | AH15: =AG15/$B15*100 -> 3.474458
A16: MIMAROPA Region | B16: ='i_C17-18'!C16 -> 343371 | C16: 169616 | D16: =C16/$B16*100 -> 49.397299 | E16: 162061 | F16: =E16/$B16*100 -> 47.197055 | G16: 111732 | H16: =G16/$B16*100 -> 32.539731 | I16: 118203 | J16: =I16/$B16*100 -> 34.424282 | K16: 111150 | L16: =K16/$B16*100 -> 32.370235 | M16: 61656 | N16: =M16/$B16*100 -> 17.956088 | O16: 65145 | P16: =O16/$B16*100 -> 18.97219 | Q16: 111470 | R16: =Q16/$B16*100 -> 32.463429 | S16: 62959 | T16: =S16/$B16*100 -> 18.335561 | U16: 39711 | V16: =U16/$B16*100 -> 11.565042 | W16: 39911 | X16: =W16/$B16*100 -> 11.623288 | Y16: 96789 | Z16: =Y16/$B16*100 -> 28.187878 | AA16: 42274 | AB16: =AA16/$B16*100 -> 12.311465 | AC16: 13546 | AD16: =AC16/$B16*100 -> 3.9450041 | AE16: 917 | AF16: =AE16/$B16*100 -> 0.26705808 | AG16: 13166 | AH16: =AG16/$B16*100 -> 3.8343366
A17: Region V - Bicol Region | B17: ='i_C17-18'!C17 -> 745745 | C17: 471907 | D17: =C17/$B17*100 -> 63.279942 | E17: 424227 | F17: =E17/$B17*100 -> 56.886335 | G17: 132354 | H17: =G17/$B17*100 -> 17.74789 | I17: 64160 | J17: =I17/$B17*100 -> 8.6034771 | K17: 118822 | L17: =K17/$B17*100 -> 15.933328 | M17: 115894 | N17: =M17/$B17*100 -> 15.540701 | O17: 95402 | P17: =O17/$B17*100 -> 12.792845 | Q17: 290004 | R17: =Q17/$B17*100 -> 38.887824 | S17: 60397 | T17: =S17/$B17*100 -> 8.098881 | U17: 18317 | V17: =U17/$B17*100 -> 2.4562015 | W17: 26886 | X17: =W17/$B17*100 -> 3.6052538 | Y17: 57881 | Z17: =Y17/$B17*100 -> 7.7615002 | AA17: 20171 | AB17: =AA17/$B17*100 -> 2.704812 | AC17: 34356 | AD17: =AC17/$B17*100 -> 4.6069367 | AE17: 14783 | AF17: =AE17/$B17*100 -> 1.982313 | AG17: 8904 | AH17: =AG17/$B17*100 -> 1.1939738
A18: Region VI - Western Visayas | B18: ='i_C17-18'!C18 -> 728694 | C18: 488814 | D18: =C18/$B18*100 -> 67.080832 | E18: 483798 | F18: =E18/$B18*100 -> 66.392477 | G18: 70208 | H18: =G18/$B18*100 -> 9.6347712 | I18: 226891 | J18: =I18/$B18*100 -> 31.136664 | K18: 119568 | L18: =K18/$B18*100 -> 16.408534 | M18: 165696 | N18: =M18/$B18*100 -> 22.738763 | O18: 145513 | P18: =O18/$B18*100 -> 19.969013 | Q18: 86725 | R18: =Q18/$B18*100 -> 11.901429 | S18: 42338 | T18: =S18/$B18*100 -> 5.8101206 | U18: 11155 | V18: =U18/$B18*100 -> 1.5308209 | W18: 79963 | X18: =W18/$B18*100 -> 10.973468 | Y18: 109248 | Z18: =Y18/$B18*100 -> 14.992301 | AA18: 57334 | AB18: =AA18/$B18*100 -> 7.8680489 | AC18: 11219 | AD18: =AC18/$B18*100 -> 1.5396037 | AE18: 1013 | AF18: =AE18/$B18*100 -> 0.13901583 | AG18: 11350 | AH18: =AG18/$B18*100 -> 1.5575811
A19: Region VII - Central Visayas | B19: ='i_C17-18'!C19 -> 592764 | C19: 473739 | D19: =C19/$B19*100 -> 79.920339 | E19: 442476 | F19: =E19/$B19*100 -> 74.646234 | G19: 111298 | H19: =G19/$B19*100 -> 18.776107 | I19: 125871 | J19: =I19/$B19*100 -> 21.234589 | K19: 124807 | L19: =K19/$B19*100 -> 21.055091 | M19: 141053 | N19: =M19/$B19*100 -> 23.795811 | O19: 200517 | P19: =O19/$B19*100 -> 33.827459 | Q19: 64082 | R19: =Q19/$B19*100 -> 10.810711 | S19: 96358 | T19: =S19/$B19*100 -> 16.255711 | U19: 57961 | V19: =U19/$B19*100 -> 9.7780904 | W19: 53074 | X19: =W19/$B19*100 -> 8.9536477 | Y19: 116412 | Z19: =Y19/$B19*100 -> 19.638844 | AA19: 38204 | AB19: =AA19/$B19*100 -> 6.4450608 | AC19: 30687 | AD19: =AC19/$B19*100 -> 5.1769338 | AE19: 6469 | AF19: =AE19/$B19*100 -> 1.0913281 | AG19: 10088 | AH19: =AG19/$B19*100 -> 1.7018577
A20: Region VIII - Eastern Visayas | B20: ='i_C17-18'!C20 -> 633212 | C20: 325793 | D20: =C20/$B20*100 -> 51.450857 | E20: 284277 | F20: =E20/$B20*100 -> 44.894443 | G20: 76048 | H20: =G20/$B20*100 -> 12.00988 | I20: 208280 | J20: =I20/$B20*100 -> 32.892617 | K20: 145702 | L20: =K20/$B20*100 -> 23.009987 | M20: 142716 | N20: =M20/$B20*100 -> 22.538423 | O20: 148100 | P20: =O20/$B20*100 -> 23.388691 | Q20: 395155 | R20: =Q20/$B20*100 -> 62.40485 | S20: 69375 | T20: =S20/$B20*100 -> 10.956046 | U20: 41943 | V20: =U20/$B20*100 -> 6.6238479 | W20: 87102 | X20: =W20/$B20*100 -> 13.755583 | Y20: 121128 | Z20: =Y20/$B20*100 -> 19.129138 | AA20: 68535 | AB20: =AA20/$B20*100 -> 10.823389 | AC20: 13148 | AD20: =AC20/$B20*100 -> 2.0763978 | AE20: 8734 | AF20: =AE20/$B20*100 -> 1.3793169 | AG20: 25344 | AH20: =AG20/$B20*100 -> 4.002451
... A26: Bangsamoro Autonomous Region in Muslim Mindanao | B26: ='i_C17-18'!C26 -> 101218 | C26: 17924 | D26: =C26/$B26*100 -> 17.708313 | E26: 58903 | F26: =E26/$B26*100 -> 58.194195 | G26: 2452 | H26: =G26/$B26*100 -> 2.422494 | I26: 9806 | J26: =I26/$B26*100 -> 9.6880002 | K26: 1196 | L26: =K26/$B26*100 -> 1.181608 | M26: 7117 | N26: =M26/$B26*100 -> 7.0313581 | O26: 5341 | P26: =O26/$B26*100 -> 5.2767294 | Q26: 30942 | R26: =Q26/$B26*100 -> 30.569662 | S26: 0 | T26: =S26/$B26*100 -> 0 | U26: 0 | V26: =U26/$B26*100 -> 0 | W26: 0 | X26: =W26/$B26*100 -> 0 | Y26: 481 | Z26: =Y26/$B26*100 -> 0.47521192 | AA26: 0 | AB26: =AA26/$B26*100 -> 0 | AC26: 0 | AD26: =AC26/$B26*100 -> 0 | AE26: 0 | AF26: =AE26/$B26*100 -> 0 | AG26: 0 | AH26: =AG26/$B26*100 -> 0
A29: Region | B29: 2024
B30: Computer Users | C30: Computer-Related Activities Performed
C31: Using Copy and Paste Tools to Duplicate or Move Data, Information and Content in Digital Environment | E31: Sending Messages | G31: Using Basic Arithmetic Formula/Computation in a Spreadsheet | I31: Connecting and Installing New Devices Through Wired or Wireless Technology | K31: Finding, Downloading, Installing New Devices | M31: Creating Documents Using a Word Processing Software | O31: Creating Electronic Presentations with Presentation Software | Q31: Transferring Files or Applications Between Devices | S31: Setting Up Effective Security Measures to Protect Devices and Online Accounts | U31: Changing Privacy Settings on your Device, Account or App to Limit the Sharing of Personal Data and Information | W31: Verifying the Reliability of Information Found Online | Y31: Data Management and Analysis | AA31: Using Modelling, Simulation and Rendering Software | AC31: Programming or Coding in Digital Environments
C32: Number | D32: Proportion | E32: Number | F32: Proportion | G32: Number | H32: Proportion | I32: Number | J32: Proportion | K32: Number | L32: Proportion | M32: Number | N32: Proportion | O32: Number | P32: Proportion | Q32: Number | R32: Proportion | S32: Number | T32: Proportion | U32: Number | V32: Proportion | W32: Number | X32: Proportion | Y32: Number | Z32: Proportion | AA32: Number | AB32: Proportion | AC32: Number | AD32: Proportion
A34: PHILIPPINES | B34: 16326632 | C34: 10825243 | D34: =(C34/$B34)*100 -> 66.304202 | E34: 13670707 | F34: =(E34/$B34)*100 -> 83.73256 | G34: 7373384 | H34: =(G34/$B34)*100 -> 45.161697 | I34: 6458582 | J34: =(I34/$B34)*100 -> 39.558569 | K34: 7500638 | L34: =(K34/$B34)*100 -> 45.941122 | M34: 8442424 | N34: =(M34/$B34)*100 -> 51.709526 | O34: 8009369 | P34: =(O34/$B34)*100 -> 49.05708 | Q34: 6992632 | R34: =(Q34/$B34)*100 -> 42.829605 | S34: 7608090 | T34: =(S34/$B34)*100 -> 46.599262 | U34: 7655882 | V34: =(U34/$B34)*100 -> 46.891986 | W34: 7138142 | X34: =(W34/$B34)*100 -> 43.720848 | Y34: 4481600 | Z34: =(Y34/$B34)*100 -> 27.44963 | AA34: 2242614 | AB34: =(AA34/$B34)*100 -> 13.735925 | AC34: 2023952 | AD34: =(AC34/$B34)*100 -> 12.396629
A35: National Capital Region | B35: 3504411 | C35: 2346062 | D35: =(C35/$B35)*100 -> 66.945972 | E35: 3187140 | F35: =(E35/$B35)*100 -> 90.946524 | G35: 1730336 | H35: =(G35/$B35)*100 -> 49.375944 | I35: 1450649 | J35: =(I35/$B35)*100 -> 41.394945 | K35: 1719165 | L35: =(K35/$B35)*100 -> 49.057174 | M35: 1685043 | N35: =(M35/$B35)*100 -> 48.083487 | O35: 1946963 | P35: =(O35/$B35)*100 -> 55.557496 | Q35: 1712411 | R35: =(Q35/$B35)*100 -> 48.864445 | S35: 2179103 | T35: =(S35/$B35)*100 -> 62.181719 | U35: 2139009 | V35: =(U35/$B35)*100 -> 61.037618 | W35: 1959074 | X35: =(W35/$B35)*100 -> 55.903089 | Y35: 1225681 | Z35: =(Y35/$B35)*100 -> 34.975378 | AA35: 652287 | AB35: =(AA35/$B35)*100 -> 18.613313 | AC35: 542324 | AD35: =(AC35/$B35)*100 -> 15.475468
A36: Cordillera Administrative Region | B36: 311852 | C36: 230258 | D36: =(C36/$B36)*100 -> 73.835666 | E36: 236711 | F36: =(E36/$B36)*100 -> 75.904916 | G36: 139220 | H36: =(G36/$B36)*100 -> 44.642972 | I36: 116279 | J36: =(I36/$B36)*100 -> 37.286597 | K36: 126317 | L36: =(K36/$B36)*100 -> 40.505432 | M36: 192134 | N36: =(M36/$B36)*100 -> 61.610636 | O36: 142119 | P36: =(O36/$B36)*100 -> 45.572579 | Q36: 118439 | R36: =(Q36/$B36)*100 -> 37.979234 | S36: 131469 | T36: =(S36/$B36)*100 -> 42.157498 | U36: 129050 | V36: =(U36/$B36)*100 -> 41.381809 | W36: 113596 | X36: =(W36/$B36)*100 -> 36.426253 | Y36: 81231 | Z36: =(Y36/$B36)*100 -> 26.047933 | AA36: 32490 | AB36: =(AA36/$B36)*100 -> 10.418404 | AC36: 30066 | AD36: =(AC36/$B36)*100 -> 9.6411118
A37: Region I - Ilocos Region | B37: 653859 | C37: 422251 | D37: =(C37/$B37)*100 -> 64.578296 | E37: 564117 | F37: =(E37/$B37)*100 -> 86.275023 | G37: 208647 | H37: =(G37/$B37)*100 -> 31.910091 | I37: 231186 | J37: =(I37/$B37)*100 -> 35.357164 | K37: 325669 | L37: =(K37/$B37)*100 -> 49.807221 | M37: 326086 | N37: =(M37/$B37)*100 -> 49.870997 | O37: 297609 | P37: =(O37/$B37)*100 -> 45.515776 | Q37: 238183 | R37: =(Q37/$B37)*100 -> 36.427273 | S37: 222651 | T37: =(S37/$B37)*100 -> 34.051837 | U37: 240298 | V37: =(U37/$B37)*100 -> 36.750737 | W37: 220575 | X37: =(W37/$B37)*100 -> 33.734337 | Y37: 111668 | Z37: =(Y37/$B37)*100 -> 17.0783 | AA37: 60949 | AB37: =(AA37/$B37)*100 -> 9.3214286 | AC37: 68676 | AD37: =(AC37/$B37)*100 -> 10.503182
A38: Region II - Cagayan Valley | B38: 524739 | C38: 422119 | D38: =(C38/$B38)*100 -> 80.443611 | E38: 421864 | F38: =(E38/$B38)*100 -> 80.395015 | G38: 279822 | H38: =(G38/$B38)*100 -> 53.325939 | I38: 221345 | J38: =(I38/$B38)*100 -> 42.181923 | K38: 237731 | L38: =(K38/$B38)*100 -> 45.304618 | M38: 329018 | N38: =(M38/$B38)*100 -> 62.701267 | O38: 261567 | P38: =(O38/$B38)*100 -> 49.847067 | Q38: 266679 | R38: =(Q38/$B38)*100 -> 50.821265 | S38: 259880 | T38: =(S38/$B38)*100 -> 49.525574 | U38: 228446 | V38: =(U38/$B38)*100 -> 43.535167 | W38: 207843 | X38: =(W38/$B38)*100 -> 39.608834 | Y38: 158230 | Z38: =(Y38/$B38)*100 -> 30.154038 | AA38: 33940 | AB38: =(AA38/$B38)*100 -> 6.4679774 | AC38: 37730 | AD38: =(AC38/$B38)*100 -> 7.1902412
A39: Region III - Central Luzon | B39: 1898000 | C39: 1020683 | D39: =(C39/$B39)*100 -> 53.776765 | E39: 1584175 | F39: =(E39/$B39)*100 -> 83.46549 | G39: 721789 | H39: =(G39/$B39)*100 -> 38.028925 | I39: 680672 | J39: =(I39/$B39)*100 -> 35.862592 | K39: 778815 | L39: =(K39/$B39)*100 -> 41.033456 | M39: 895207 | N39: =(M39/$B39)*100 -> 47.165806 | O39: 729743 | P39: =(O39/$B39)*100 -> 38.447998 | Q39: 598001 | R39: =(Q39/$B39)*100 -> 31.506902 | S39: 725819 | T39: =(S39/$B39)*100 -> 38.241254 | U39: 775791 | V39: =(U39/$B39)*100 -> 40.874131 | W39: 687364 | X39: =(W39/$B39)*100 -> 36.215174 | Y39: 376341 | Z39: =(Y39/$B39)*100 -> 19.828293 | AA39: 168539 | AB39: =(AA39/$B39)*100 -> 8.8798209 | AC39: 167853 | AD39: =(AC39/$B39)*100 -> 8.8436776
A40: Region IV-A - CALABARZON | B40: 3038615 | C40: 2067537 | D40: =(C40/$B40)*100 -> 68.042085 | E40: 2618582 | F40: =(E40/$B40)*100 -> 86.176827 | G40: 1488289 | H40: =(G40/$B40)*100 -> 48.97919 | I40: 1413468 | J40: =(I40/$B40)*100 -> 46.516851 | K40: 1627998 | L40: =(K40/$B40)*100 -> 53.576975 | M40: 1544843 | N40: =(M40/$B40)*100 -> 50.840366 | O40: 1712148 | P40: =(O40/$B40)*100 -> 56.346329 | Q40: 1479658 | R40: =(Q40/$B40)*100 -> 48.695146 | S40: 1596401 | T40: =(S40/$B40)*100 -> 52.537126 | U40: 1519544 | V40: =(U40/$B40)*100 -> 50.007783 | W40: 1379946 | X40: =(W40/$B40)*100 -> 45.413651 | Y40: 949662 | Z40: =(Y40/$B40)*100 -> 31.25312 | AA40: 531973 | AB40: =(AA40/$B40)*100 -> 17.507088 | AC40: 457784 | AD40: =(AC40/$B40)*100 -> 15.065548
A41: MIMAROPA Region | B41: 371870 | C41: 270950 | D41: =(C41/$B41)*100 -> 72.861484 | E41: 298615 | F41: =(E41/$B41)*100 -> 80.300912 | G41: 165041 | H41: =(G41/$B41)*100 -> 44.38137 | I41: 138659 | J41: =(I41/$B41)*100 -> 37.286955 | K41: 199374 | L41: =(K41/$B41)*100 -> 53.613897 | M41: 219846 | N41: =(M41/$B41)*100 -> 59.119047 | O41: 204176 | P41: =(O41/$B41)*100 -> 54.905209 | Q41: 180285 | R41: =(Q41/$B41)*100 -> 48.480652 | S41: 180078 | T41: =(S41/$B41)*100 -> 48.424987 | U41: 151305 | V41: =(U41/$B41)*100 -> 40.687606 | W41: 112601 | X41: =(W41/$B41)*100 -> 30.279668 | Y41: 83623 | Z41: =(Y41/$B41)*100 -> 22.487159 | AA41: 34299 | AB41: =(AA41/$B41)*100 -> 9.2233845 | AC41: 35182 | AD41: =(AC41/$B41)*100 -> 9.4608331
A42: Region V - Bicol Region | B42: 665051 | C42: 536446 | D42: =(C42/$B42)*100 -> 80.662385 | E42: 510535 | F42: =(E42/$B42)*100 -> 76.766293 | G42: 344844 | H42: =(G42/$B42)*100 -> 51.852264 | I42: 272671 | J42: =(I42/$B42)*100 -> 41.000014 | K42: 317762 | L42: =(K42/$B42)*100 -> 47.780095 | M42: 427703 | N42: =(M42/$B42)*100 -> 64.311308 | O42: 329303 | P42: =(O42/$B42)*100 -> 49.515451 | Q42: 353337 | R42: =(Q42/$B42)*100 -> 53.129309 | S42: 322887 | T42: =(S42/$B42)*100 -> 48.550713 | U42: 354374 | V42: =(U42/$B42)*100 -> 53.285237 | W42: 389926 | X42: =(W42/$B42)*100 -> 58.630992 | Y42: 230051 | Z42: =(Y42/$B42)*100 -> 34.591482 | AA42: 88636 | AB42: =(AA42/$B42)*100 -> 13.3277 | AC42: 89371 | AD42: =(AC42/$B42)*100 -> 13.438218
A43: Region VI - Western Visayas | B43: 881484 | C43: 674347 | D43: =(C43/$B43)*100 -> 76.501332 | E43: 737783 | F43: =(E43/$B43)*100 -> 83.697832 | G43: 469830 | H43: =(G43/$B43)*100 -> 53.29989 | I43: 315612 | J43: =(I43/$B43)*100 -> 35.80462 | K43: 324262 | L43: =(K43/$B43)*100 -> 36.78592 | M43: 515726 | N43: =(M43/$B43)*100 -> 58.506564 | O43: 408584 | P43: =(O43/$B43)*100 -> 46.351834 | Q43: 364408 | R43: =(Q43/$B43)*100 -> 41.340285 | S43: 312164 | T43: =(S43/$B43)*100 -> 35.413462 | U43: 337613 | V43: =(U43/$B43)*100 -> 38.300525 | W43: 375732 | X43: =(W43/$B43)*100 -> 42.624937 | Y43: 159271 | Z43: =(Y43/$B43)*100 -> 18.068507 | AA43: 113297 | AB43: =(AA43/$B43)*100 -> 12.852984 | AC43: 78689 | AD43: =(AC43/$B43)*100 -> 8.9268779
A44: Region VII - Central Visayas | B44: 1377557 | C44: 914629 | D44: =(C44/$B44)*100 -> 66.395002 | E44: 1067245 | F44: =(E44/$B44)*100 -> 77.473745 | G44: 528897 | H44: =(G44/$B44)*100 -> 38.393838 | I44: 640305 | J44: =(I44/$B44)*100 -> 46.481198 | K44: 592132 | L44: =(K44/$B44)*100 -> 42.98421 | M44: 745640 | N44: =(M44/$B44)*100 -> 54.127706 | O44: 615226 | P44: =(O44/$B44)*100 -> 44.660657 | Q44: 565801 | R44: =(Q44/$B44)*100 -> 41.072783 | S44: 544612 | T44: =(S44/$B44)*100 -> 39.534625 | U44: 615077 | V44: =(U44/$B44)*100 -> 44.64984 | W44: 645307 | X44: =(W44/$B44)*100 -> 46.844305 | Y44: 453643 | Z44: =(Y44/$B44)*100 -> 32.930979 | AA44: 228168 | AB44: =(AA44/$B44)*100 -> 16.563235 | AC44: 217300 | AD44: =(AC44/$B44)*100 -> 15.774302
A45: Region VIII - Eastern Visayas | B45: 578535 | C45: 367277 | D45: =(C45/$B45)*100 -> 63.483972 | E45: 472077 | F45: =(E45/$B45)*100 -> 81.598693 | G45: 278996 | H45: =(G45/$B45)*100 -> 48.224567 | I45: 234724 | J45: =(I45/$B45)*100 -> 40.572135 | K45: 259888 | L45: =(K45/$B45)*100 -> 44.921742 | M45: 333119 | N45: =(M45/$B45)*100 -> 57.579749 | O45: 283177 | P45: =(O45/$B45)*100 -> 48.947255 | Q45: 232388 | R45: =(Q45/$B45)*100 -> 40.168356 | S45: 238720 | T45: =(S45/$B45)*100 -> 41.262845 | U45: 247912 | V45: =(U45/$B45)*100 -> 42.851686 | W45: 220832 | X45: =(W45/$B45)*100 -> 38.170897 | Y45: 172187 | Z45: =(Y45/$B45)*100 -> 29.76259 | AA45: 66948 | AB45: =(AA45/$B45)*100 -> 11.571988 | AC45: 89287 | AD45: =(AC45/$B45)*100 -> 15.433293
... A51: Bangsamoro Autonomous Region in Muslim Mindanao | B51: 209771 | C51: 107639 | D51: =(C51/$B51)*100 -> 51.312622 | E51: 150623 | F51: =(E51/$B51)*100 -> 71.803538 | G51: 35426 | H51: =(G51/$B51)*100 -> 16.88794 | I51: 38888 | J51: =(I51/$B51)*100 -> 18.538311 | K51: 68118 | L51: =(K51/$B51)*100 -> 32.472553 | M51: 96713 | N51: =(M51/$B51)*100 -> 46.104085 | O51: 83938 | P51: =(O51/$B51)*100 -> 40.014111 | Q51: 59540 | R51: =(Q51/$B51)*100 -> 28.383332 | S51: 22848 | T51: =(S51/$B51)*100 -> 10.891877 | U51: 30278 | V51: =(U51/$B51)*100 -> 14.433835 | W51: 27678 | X51: =(W51/$B51)*100 -> 13.194388 | Y51: 30350 | Z51: =(Y51/$B51)*100 -> 14.468158 | AA51: 18078 | AB51: =(AA51/$B51)*100 -> 8.6179691 | AC51: 13887 | AD51: =(AC51/$B51)*100 -> 6.6200762
A54: Notes:
A55: Details may not add up to totals due to rounding.
A56: p Estimates are preliminary and may change
A57: r Revised
A58: Source of data: Philippine Statistics Authority, 2024 National Information and Communications Technology Household Survey.

Sheet c32
A1: BACK TO LIST
A2: Table #. Number and Proportion of Households With Access to the Internet at Home by Region, Philippines: 2019 and 2024p
A5: Region | B5: 2019 | E5: 2024
B6: Total Households | C6: With Access to the Internet at Home | E6: Total Households | F6: With Access to the Internet at Home
C7: Number | D7: Proportion | F7: Number | G7: Proportion
A9: PHILIPPINES | B9: ='Estimated Totals'!B7 -> 23360960 | C9: 4123881 | D9: =(C9/$B9)*100 -> 17.652875 | E9: 27793884 | F9: 13555873 | G9: =(F9/$E9)*100 -> 48.772863
A10: National Capital Region | B10: ='Estimated Totals'!B8 -> 3009545 | C10: 1000671 | D10: =(C10/$B10)*100 -> 33.24991 | E10: 3667731 | F10: 2518277 | G10: =(F10/$E10)*100 -> 68.660352
A11: Cordillera Administrative Region | B11: ='Estimated Totals'!B9 -> 388188 | C11: 115495 | D11: =(C11/$B11)*100 -> 29.752336 | E11: 468413 | F11: 249276 | G11: =(F11/$E11)*100 -> 53.21714
A12: Region I - Ilocos Region | B12: ='Estimated Totals'!B10 -> 1250337 | C12: 224947 | D12: =(C12/$B12)*100 -> 17.99091 | E12: 1316881 | F12: 766431 | G12: =(F12/$E12)*100 -> 58.200475
A13: Region II - Cagayan Valley | B13: ='Estimated Totals'!B11 -> 855893 | C13: 154330 | D13: =(C13/$B13)*100 -> 18.03146 | E13: 934252 | F13: 520744 | G13: =(F13/$E13)*100 -> 55.739137
A14: Region III - Central Luzon | B14: ='Estimated Totals'!B12 -> 2823200 | C14: 663095 | D14: =(C14/$B14)*100 -> 23.487355 | E14: 3161851 | F14: 1939705 | G14: =(F14/$E14)*100 -> 61.347135
A15: Region IV-A - CALABARZON | B15: ='Estimated Totals'!B13 -> 3486186 | C15: 844147 | D15: =(C15/$B15)*100 -> 24.214055 | E15: 4369198 | F15: 2323365 | G15: =(F15/$E15)*100 -> 53.176006
A16: MIMAROPA Region | B16: ='Estimated Totals'!B14 -> 686916 | C16: 52140 | D16: =(C16/$B16)*100 -> 7.5904477 | E16: 828498 | F16: 256021 | G16: =(F16/$E16)*100 -> 30.901825
A17: Region V - Bicol Region | B17: ='Estimated Totals'!B15 -> 1030986 | C17: 75063 | D17: =(C17/$B17)*100 -> 7.2807002 | E17: 1384033 | F17: 564663 | G17: =(F17/$E17)*100 -> 40.798377
A18: Region VI - Western Visayas | B18: ='Estimated Totals'!B16 -> 1705556 | C18: 177260 | D18: =(C18/$B18)*100 -> 10.393092 | E18: 2040922 | F18: 829005 | G18: =(F18/$E18)*100 -> 40.619142
A19: Region VII - Central Visayas | B19: ='Estimated Totals'!B17 -> 1820052 | C19: 186621 | D19: =(C19/$B19)*100 -> 10.253608 | E19: 2077216 | F19: 868012 | G19: =(F19/$E19)*100 -> 41.787277
A20: Region VIII - Eastern Visayas | B20: ='Estimated Totals'!B18 -> 1042723 | C20: 173539 | D20: =(C20/$B20)*100 -> 16.642867 | E20: 1200913 | F20: 410873 | G20: =(F20/$E20)*100 -> 34.213386
... A26: Bangsamoro Autonomous Region in Muslim Mindanao | B26: ='Estimated Totals'!B24 -> 521349 | C26: 23580 | D26: =(C26/$B26)*100 -> 4.522882 | E26: 846042 | F26: 234671 | G26: =(F26/$E26)*100 -> 27.737512
A29: Notes:
A30: Details may not add up to totals due to rounding.
A31: p Estimates are preliminary and may change
A32: Source of data: Philippine Statistics Authority, 2024 National Information and Communications Technology Household Survey.

Sheet C34_a to C34_f
A1: BACK TO LIST
A2: Table #. Number and Proportion of Households With Access to the Internet at Home by Usage of Internet and Region, Philippines: 2019r and 2024p
A4: Region | B4: 2019 | M4: 2024
B5: With Access to the Internet at Home | C5: Usage of Internet | M5: With Access to the Internet at Home | N5: Usage of Internet
C6: Work/Business | E6: Studies | G6: Social Media | I6: Entertainment | K6: Others | N6: Work | P6: Business | R6: Studies | T6: Social Media | V6: Entertainment | X6: Others
C7: Number | D7: Proportion | E7: Number | F7: Proportion | G7: Number | H7: Proportion | I7: Number | J7: Proportion | K7: Number | L7: Proportion | N7: Number | O7: Proportion | P7: Number | Q7: Proportion | R7: Number | S7: Proportion | T7: Number | U7: Proportion | V7: Number | W7: Proportion | X7: Number | Y7: Proportion
A9: PHILIPPINES | B9: ='c32'!C9 -> 4123881 | C9: 2127825 | D9: =(C9/$B9)*100 -> 51.597633 | E9: 2737277 | F9: =(E9/$B9)*100 -> 66.376236 | G9: 3719094 | H9: =(G9/$B9)*100 -> 90.184319 | I9: 2767617 | J9: =(I9/$B9)*100 -> 67.111951 | K9: 11096.848 | L9: =(K9/$B9)*100 -> 0.26908748 | M9: 13555873 | N9: 4895966 | O9: =(N9/$M9)*100 -> 36.116936 | P9: 1449842 | Q9: =(P9/$M9)*100 -> 10.695305 | R9: 8242948 | S9: =(R9/$M9)*100 -> 60.807209 | T9: 13265291 | U9: =(T9/$M9)*100 -> 97.856412 | V9: 11750129 | W9: =(V9/$M9)*100 -> 86.67925 | X9: 6413 | Y9: *
A10: National Capital Region | B10: ='c32'!C10 -> 1000671 | C10: 594192 | D10: =(C10/$B10)*100 -> 59.379356 | E10: 674681 | F10: =(E10/$B10)*100 -> 67.422859 | G10: 917495 | H10: =(G10/$B10)*100 -> 91.687977 | I10: 736918 | J10: =(I10/$B10)*100 -> 73.642386 | K10: 0 | L10: =(K10/$B10)*100 -> 0 | M10: 2518277 | N10: 1148019 | O10: =(N10/$M10)*100 -> 45.587479 | P10: 235216 | Q10: =(P10/$M10)*100 -> 9.3403545 | R10: 1460003 | S10: =(R10/$M10)*100 -> 57.976267 | T10: 2471017 | U10: =(T10/$M10)*100 -> 98.12332 | V10: 2289281 | W10: =(V10/$M10)*100 -> 90.90664 | X10: 0 | Y10: =(X10/$M10)*100 -> 0
A11: Cordillera Administrative Region | B11: ='c32'!C11 -> 115495 | C11: 34046 | D11: =(C11/$B11)*100 -> 29.478332 | E11: 53438 | F11: =(E11/$B11)*100 -> 46.26867 | G11: 109206 | H11: =(G11/$B11)*100 -> 94.554743 | I11: 39078 | J11: =(I11/$B11)*100 -> 33.835231 | K11: 0 | L11: =(K11/$B11)*100 -> 0 | M11: 249276 | N11: 75936 | O11: =(N11/$M11)*100 -> 30.46262 | P11: 21943 | Q11: =(P11/$M11)*100 -> 8.8026926 | R11: 143788 | S11: =(R11/$M11)*100 -> 57.682248 | T11: 245958 | U11: =(T11/$M11)*100 -> 98.668945 | V11: 224541 | W11: =(V11/$M11)*100 -> 90.077264 | X11: 0 | Y11: =(X11/$M11)*100 -> 0
A12: Region I - Ilocos Region | B12: ='c32'!C12 -> 224947 | C12: 92932 | D12: =(C12/$B12)*100 -> 41.312843 | E12: 153384 | F12: =(E12/$B12)*100 -> 68.186728 | G12: 199461 | H12: =(G12/$B12)*100 -> 88.67022 | I12: 144640 | J12: =(I12/$B12)*100 -> 64.299591 | K12: 488.64999 | L12: =(K12/$B12)*100 -> 0.21722894 | M12: 766431 | N12: 214363 | O12: =(N12/$M12)*100 -> 27.968989 | P12: 49296 | Q12: =(P12/$M12)*100 -> 6.4318902 | R12: 498147 | S12: =(R12/$M12)*100 -> 64.995675 | T12: 759631 | U12: =(T12/$M12)*100 -> 99.112771 | V12: 628291 | W12: =(V12/$M12)*100 -> 81.976199 | X12: 1591 | Y12: =(X12/$M12)*100 -> 0.20758555
A13: Region II - Cagayan Valley | B13: ='c32'!C13 -> 154330 | C13: 38717 | D13: =(C13/$B13)*100 -> 25.087151 | E13: 83322 | F13: =(E13/$B13)*100 -> 53.989503 | G13: 119898 | H13: =(G13/$B13)*100 -> 77.689367 | I13: 60461 | J13: =(I13/$B13)*100 -> 39.17644 | K13: 0 | L13: =(K13/$B13)*100 -> 0 | M13: 520744 | N13: 154365 | O13: =(N13/$M13)*100 -> 29.643164 | P13: 56709 | Q13: =(P13/$M13)*100 -> 10.889996 | R13: 327449 | S13: =(R13/$M13)*100 -> 62.880993 | T13: 512053 | U13: =(T13/$M13)*100 -> 98.331042 | V13: 439593 | W13: =(V13/$M13)*100 -> 84.416335 | X13: 0 | Y13: =(X13/$M13)*100 -> 0
A14: Region III - Central Luzon | B14: ='c32'!C14 -> 663095 | C14: 396413 | D14: =(C14/$B14)*100 -> 59.782233 | E14: 484677 | F14: =(E14/$B14)*100 -> 73.093147 | G14: 639674 | H14: =(G14/$B14)*100 -> 96.467927 | I14: 549292 | J14: =(I14/$B14)*100 -> 82.837602 | K14: 118.58422 | L14: =(K14/$B14)*100 -> 0.017883444 | M14: 1939705 | N14: 549933 | O14: =(N14/$M14)*100 -> 28.351373 | P14: 182582 | Q14: =(P14/$M14)*100 -> 9.4128746 | R14: 1239163 | S14: =(R14/$M14)*100 -> 63.884096 | T14: 1908268 | U14: =(T14/$M14)*100 -> 98.37929 | V14: 1697412 | W14: =(V14/$M14)*100 -> 87.508771 | X14: 0 | Y14: =(X14/$M14)*100 -> 0
A15: Region IV-A - CALABARZON | B15: ='c32'!C15 -> 844147 | C15: 461056 | D15: =(C15/$B15)*100 -> 54.617975 | E15: 568172 | F15: =(E15/$B15)*100 -> 67.307234 | G15: 780607 | H15: =(G15/$B15)*100 -> 92.472875 | I15: 621989 | J15: =(I15/$B15)*100 -> 73.682546 | K15: 6680.6654 | L15: =(K15/$B15)*100 -> 0.7914102 | M15: 2323365 | N15: 979120 | O15: =(N15/$M15)*100 -> 42.142324 | P15: 248710 | Q15: =(P15/$M15)*100 -> 10.704732 | R15: 1259549 | S15: =(R15/$M15)*100 -> 54.212274 | T15: 2277446 | U15: =(T15/$M15)*100 -> 98.023599 | V15: 2125966 | W15: =(V15/$M15)*100 -> 91.503746 | X15: 0 | Y15: =(X15/$M15)*100 -> 0
A16: MIMAROPA Region | B16: ='c32'!C16 -> 52140 | C16: 26170 | D16: =(C16/$B16)*100 -> 50.191791 | E16: 35133 | F16: =(E16/$B16)*100 -> 67.382048 | G16: 45338 | H16: =(G16/$B16)*100 -> 86.954354 | I16: 35959 | J16: =(I16/$B16)*100 -> 68.966245 | K16: 544.17407 | L16: =(K16/$B16)*100 -> 1.0436787 | M16: 256021 | N16: 83914 | O16: =(N16/$M16)*100 -> 32.776218 | P16: 38403 | Q16: =(P16/$M16)*100 -> 14.999941 | R16: 174675 | S16: =(R16/$M16)*100 -> 68.226825 | T16: 246879 | U16: =(T16/$M16)*100 -> 96.429199 | V16: 224666 | W16: =(V16/$M16)*100 -> 87.752958 | X16: 0 | Y16: =(X16/$M16)*100 -> 0
A17: Region V - Bicol Region | B17: ='c32'!C17 -> 75063 | C17: 35103 | D17: =(C17/$B17)*100 -> 46.764718 | E17: 55388 | F17: =(E17/$B17)*100 -> 73.788684 | G17: 52313 | H17: =(G17/$B17)*100 -> 69.692125 | I17: 32011 | J17: =(I17/$B17)*100 -> 42.645511 | K17: 0 | L17: =(K17/$B17)*100 -> 0 | M17: 564663 | N17: 174509 | O17: =(N17/$M17)*100 -> 30.904982 | P17: 91233 | Q17: =(P17/$M17)*100 -> 16.157071 | R17: 394438 | S17: =(R17/$M17)*100 -> 69.8537 | T17: 543462 | U17: =(T17/$M17)*100 -> 96.245371 | V17: 457529 | W17: =(V17/$M17)*100 -> 81.026913 | X17: 0 | Y17: =(X17/$M17)*100 -> 0
A18: Region VI - Western Visayas | B18: ='c32'!C18 -> 177260 | C18: 92607 | D18: =(C18/$B18)*100 -> 52.243597 | E18: 111977 | F18: =(E18/$B18)*100 -> 63.171048 | G18: 158549 | H18: =(G18/$B18)*100 -> 89.444319 | I18: 101248 | J18: =(I18/$B18)*100 -> 57.118357 | K18: 395 | L18: =(K18/$B18)*100 -> 0.22283651 | M18: 829005 | N18: 322893 | O18: =(N18/$M18)*100 -> 38.949464 | P18: 114055 | Q18: =(P18/$M18)*100 -> 13.758059 | R18: 517800 | S18: =(R18/$M18)*100 -> 62.460419 | T18: 808078 | U18: =(T18/$M18)*100 -> 97.475649 | V18: 686533 | W18: =(V18/$M18)*100 -> 82.814096 | X18: 1179 | Y18: =(X18/$M18)*100 -> 0.14221868
A19: Region VII - Central Visayas | B19: ='c32'!C19 -> 186621 | C19: 96712 | D19: =(C19/$B19)*100 -> 51.822678 | E19: 99097 | F19: =(E19/$B19)*100 -> 53.100669 | G19: 171948 | H19: =(G19/$B19)*100 -> 92.137541 | I19: 121885 | J19: =(I19/$B19)*100 -> 65.311514 | K19: 329.9516 | L19: =(K19/$B19)*100 -> 0.17680304 | M19: 868012 | N19: 349593 | O19: =(N19/$M19)*100 -> 40.275134 | P19: 103805 | Q19: =(P19/$M19)*100 -> 11.958936 | R19: 524383 | S19: =(R19/$M19)*100 -> 60.411953 | T19: 842679 | U19: =(T19/$M19)*100 -> 97.081492 | V19: 763650 | W19: =(V19/$M19)*100 -> 87.976894 | X19: 0 | Y19: =(X19/$M19)*100 -> 0
A20: Region VIII - Eastern Visayas | B20: ='c32'!C20 -> 173539 | C20: 46536 | D20: =(C20/$B20)*100 -> 26.815874 | E20: 103528 | F20: =(E20/$B20)*100 -> 59.656907 | G20: 159376 | H20: =(G20/$B20)*100 -> 91.838722 | I20: 73251 | J20: =(I20/$B20)*100 -> 42.210108 | K20: 2539.8222 | L20: =(K20/$B20)*100 -> 1.4635455 | M20: 410873 | N20: 150191 | O20: =(N20/$M20)*100 -> 36.554118 | P20: 51620 | Q20: =(P20/$M20)*100 -> 12.563493 | R20: 298181 | S20: =(R20/$M20)*100 -> 72.572547 | T20: 394730 | U20: =(T20/$M20)*100 -> 96.071049 | V20: 365865 | W20: =(V20/$M20)*100 -> 89.045764 | X20: 931 | Y20: =(X20/$M20)*100 -> 0.2265907
A21: Region IX - Zamboanga Peninsula | B21: ='c32'!C21 -> 46424 | C21: 23025 | D21: =(C21/$B21)*100 -> 49.597191 | E21: 31489 | F21: =(E21/$B21)*100 -> 67.82914 | G21: 39979 | H21: =(G21/$B21)*100 -> 86.117095 | I21: 24374 | J21: =(I21/$B21)*100 -> 52.503016 | K21: 0 | L21: =(K21/$B21)*100 -> 0 | M21: 191638 | N21: 78402 | O21: =(N21/$M21)*100 -> 40.91151 | P21: 34093 | Q21: =(P21/$M21)*100 -> 17.790313 | R21: 136524 | S21: =(R21/$M21)*100 -> 71.240568 | T21: 181234 | U21: =(T21/$M21)*100 -> 94.571014 | V21: 148486 | W21: =(V21/$M21)*100 -> 77.482545 | X21: 709 | Y21: =(X21/$M21)*100 -> 0.36996838
... A26: Bangsamoro Autonomous Region in Muslim Mindanao | B26: ='c32'!C26 -> 23580 | C26: 2671 | D26: =(C26/$B26)*100 -> 11.327396 | E26: 11481 | F26: =(E26/$B26)*100 -> 48.689567 | G26: 15714 | H26: =(G26/$B26)*100 -> 66.641221 | I26: 4177 | J26: =(I26/$B26)*100 -> 17.714165 | K26: 0 | L26: =(K26/$B26)*100 -> 0 | M26: 234671 | N26: 49982 | O26: =(N26/$M26)*100 -> 21.298754 | P26: 41494 | Q26: =(P26/$M26)*100 -> 17.681776 | R26: 110267 | S26: =(R26/$M26)*100 -> 46.987911 | T26: 225765 | U26: =(T26/$M26)*100 -> 96.2049 | V26: 167373 | W26: =(V26/$M26)*100 -> 71.322405 | X26: 1127 | Y26: =(X26/$M26)*100 -> 0.48024681
A29: Notes:
A30: Details may not add up to totals due to rounding.
A31: p Estimates are preliminary and may change
A32: r Revised
A33: Source of data: Philippine Statistics Authority, 2024 National Information and Communications Technology Household Survey.

Sheet C35
A1: BACK TO LIST
A2: Table #. Households Average Monthly Spending on Internet by Region, Philippines: 2019 and 2024p
A4: Region | B4: Average Monthly Spending
B5: 2019 | C5: 2024
A7: PHILIPPINES | B7: 1280.59 | C7: 1069.1
A8: National Capital Region | B8: 1505.08 | C8: 1290.9
A9: Cordillera Administrative Region | B9: 1057.47 | C9: 959.7
A10: Region I - Ilocos Region | B10: 1127.49 | C10: 981.2
A11: Region II - Cagayan Valley | B11: 770.86 | C11: 814.9
A12: Region III - Central Luzon | B12: 1192.08 | C12: 1009.2
A13: Region IV-A - CALABARZON | B13: 1453.23 | C13: 1244.2
A14: MIMAROPA Region | B14: 942.62 | C14: 999
A15: Region V - Bicol Region | B15: 1042.11 | C15: 960.9
A16: Region VI - Western Visayas | B16: 1111.66 | C16: 1036
A17: Region VII - Central Visayas | B17: 1538.36 | C17: 1167.8
A18: Region VIII - Eastern Visayas | B18: 704.95 | C18: 936
... A24: Bangsamoro Autonomous Region in Muslim Mindanao | B24: 395.25 | C24: 583
A27: Notes:
A28: p Estimates are preliminary and may change
A29: Source of data: Philippine Statistics Authority, 2024 National Information and Communications Technology Household Survey.

Sheet i_C21&23
A1: BACK TO LIST
A2: Table #. Number and Proportion of Individuals Using the Internet by Type of Device Used and Region, Philippines: 2019r and 2024p
A4: Region | B4: 2019
B5: Total Individuals | C5: Internet User | E5: Type of Device Used
E6: Desktop | G6: Laptop | I6: Tablet or Similar Device | K6: Cellphone | M6: Gaming Console | O6: Television | Q6: Others
C7: Number | D7: Proportion | E7: Number | F7: Proportion | G7: Number | H7: Proportion | I7: Number | J7: Proportion | K7: Number | L7: Proportion | M7: Number | N7: Proportion | O7: Number | P7: Proportion | Q7: Number | R7: Proportion
A9: PHILIPPINES | B9: ='Estimated Totals'!D7 -> 83258836 | C9: 21118015 | D9: =C9/B9*100 -> 25.364293 | E9: 6283612 | F9: =E9/$C9*100 -> 29.754747 | G9: 4080144 | H9: =G9/$C9*100 -> 19.320679 | I9: 1554805 | J9: =I9/$C9*100 -> 7.362458 | K9: 17968016 | L9: =K9/$C9*100 -> 85.083829 | M9: 90799 | N9: =M9/$C9*100 -> 0.42995991 | O9: 120298 | P9: =O9/$C9*100 -> 0.56964634 | Q9: 71175 | R9: =Q9/$C9*100 -> 0.33703451
A10: National Capital Region | B10: ='Estimated Totals'!D8 -> 11005073 | C10: 4434947.7 | D10: =C10/B10*100 -> 40.299121 | E10: 1435017 | F10: =E10/$C10*100 -> 32.357022 | G10: 1080722 | H10: =G10/$C10*100 -> 24.368315 | I10: 268963 | J10: =I10/$C10*100 -> 6.0646262 | K10: 3977919 | L10: =K10/$C10*100 -> 89.694835 | M10: 13887 | N10: =M10/$C10*100 -> 0.31312658 | O10: 23088 | P10: =O10/$C10*100 -> 0.52059239 | Q10: 495 | R10: =Q10/$C10*100 -> 0.011161349
A11: Cordillera Administrative Region | B11: ='Estimated Totals'!D9 -> 1394660 | C11: 322391.19 | D11: =C11/B11*100 -> 23.116114 | E11: 80940 | F11: =E11/$C11*100 -> 25.106145 | G11: 58544 | H11: =G11/$C11*100 -> 18.159305 | I11: 15156 | J11: =I11/$C11*100 -> 4.701121 | K11: 271506 | L11: =K11/$C11*100 -> 84.21632 | M11: 215 | N11: =M11/$C11*100 -> 0.066689167 | O11: 0 | P11: =O11/$C11*100 -> 0 | Q11: 0 | R11: =Q11/$C11*100 -> 0
A12: Region I - Ilocos Region | B12: ='Estimated Totals'!D10 -> 4063052 | C12: 1269147.6 | D12: =C12/B12*100 -> 31.236312 | E12: 134704 | F12: =E12/$C12*100 -> 10.613738 | G12: 191607 | H12: =G12/$C12*100 -> 15.097298 | I12: 119249 | J12: =I12/$C12*100 -> 9.3959915 | K12: 1184048 | L12: =K12/$C12*100 -> 93.294744 | M12: 2480 | N12: =M12/$C12*100 -> 0.19540674 | O12: 2975 | P12: =O12/$C12*100 -> 0.2344093 | Q12: 58880 | R12: =Q12/$C12*100 -> 4.6393343
A13: Region II - Cagayan Valley | B13: ='Estimated Totals'!D11 -> 2820240 | C13: 608713.36 | D13: =C13/B13*100 -> 21.583743 | E13: 62439 | F13: =E13/$C13*100 -> 10.257537 | G13: 119181 | H13: =G13/$C13*100 -> 19.579166 | I13: 28414 | J13: =I13/$C13*100 -> 4.6678785 | K13: 499337 | L13: =K13/$C13*100 -> 82.031549 | M13: 0 | N13: =M13/$C13*100 -> 0 | O13: 0 | P13: =O13/$C13*100 -> 0 | Q13: 0 | R13: =Q13/$C13*100 -> 0
A14: Region III - Central Luzon | B14: ='Estimated Totals'!D12 -> 9585315 | C14: 3210821.1 | D14: =C14/B14*100 -> 33.497293 | E14: 589483 | F14: =E14/$C14*100 -> 18.35926 | G14: 472449 | H14: =G14/$C14*100 -> 14.714274 | I14: 254745 | J14: =I14/$C14*100 -> 7.933952 | K14: 2954872 | L14: =K14/$C14*100 -> 92.028548 | M14: 538 | N14: =M14/$C14*100 -> 0.016755839 | O14: 0 | P14: =O14/$C14*100 -> 0 | Q14: 3736 | R14: =Q14/$C14*100 -> 0.11635653
A15: Region IV-A - CALABARZON | B15: ='Estimated Totals'!D13 -> 12457452 | C15: 4117581.3 | D15: =C15/B15*100 -> 33.053158 | E15: 1418151 | F15: =E15/$C15*100 -> 34.44136 | G15: 809043 | H15: =G15/$C15*100 -> 19.648501 | I15: 252285 | J15: =I15/$C15*100 -> 6.1270193 | K15: 3586802 | L15: =K15/$C15*100 -> 87.10944 | M15: 18011 | N15: =M15/$C15*100 -> 0.43741699 | O15: 42216 | P15: =O15/$C15*100 -> 1.0252621 | Q15: 1294 | R15: =Q15/$C15*100 -> 0.031426216
A16: MIMAROPA Region | B16: ='Estimated Totals'!D14 -> 2347582 | C16: 437023.26 | D16: =C16/B16*100 -> 18.615889 | E16: 102369 | F16: =E16/$C16*100 -> 23.424154 | G16: 80926 | H16: =G16/$C16*100 -> 18.51755 | I16: 30435 | J16: =I16/$C16*100 -> 6.9641602 | K16: 390569 | L16: =K16/$C16*100 -> 89.370301 | M16: 329 | N16: =M16/$C16*100 -> 0.075282035 | O16: 4385 | P16: =O16/$C16*100 -> 1.0033791 | Q16: 750 | R16: =Q16/$C16*100 -> 0.17161558
A17: Region V - Bicol Region | B17: ='Estimated Totals'!D15 -> 4528646 | C17: 795978.54 | D17: =C17/B17*100 -> 17.576524 | E17: 385324 | F17: =E17/$C17*100 -> 48.408843 | G17: 237671 | H17: =G17/$C17*100 -> 29.858971 | I17: 132115 | J17: =I17/$C17*100 -> 16.597809 | K17: 550822 | L17: =K17/$C17*100 -> 69.20061 | M17: 418 | N17: =M17/$C17*100 -> 0.052513979 | O17: 2357 | P17: =O17/$C17*100 -> 0.29611351 | Q17: 0 | R17: =Q17/$C17*100 -> 0
A18: Region VI - Western Visayas | B18: ='Estimated Totals'!D16 -> 6087553 | C18: 1148816 | D18: =C18/B18*100 -> 18.871557 | E18: 298164 | F18: =E18/$C18*100 -> 25.954025 | G18: 204659 | H18: =G18/$C18*100 -> 17.814776 | I18: 96883 | J18: =I18/$C18*100 -> 8.4332911 | K18: 929207 | L18: =K18/$C18*100 -> 80.883882 | M18: 0 | N18: =M18/$C18*100 -> 0 | O18: 2131 | P18: =O18/$C18*100 -> 0.18549532 | Q18: 0 | R18: =Q18/$C18*100 -> 0
A19: Region VII - Central Visayas | B19: ='Estimated Totals'!D17 -> 6058752 | C19: 847079.18 | D19: =C19/B19*100 -> 13.981084 | E19: 375014 | F19: =E19/$C19*100 -> 44.271422 | G19: 172865 | H19: =G19/$C19*100 -> 20.407183 | I19: 91573 | J19: =I19/$C19*100 -> 10.810442 | K19: 575454 | L19: =K19/$C19*100 -> 67.933909 | M19: 10113 | N19: =M19/$C19*100 -> 1.1938671 | O19: 24631 | P19: =O19/$C19*100 -> 2.9077565 | Q19: 2394 | R19: =Q19/$C19*100 -> 0.28261821
A20: Region VIII - Eastern Visayas | B20: ='Estimated Totals'!D18 -> 3529248 | C20: 1032784.7 | D20: =C20/B20*100 -> 29.26359 | E20: 227143 | F20: =E20/$C20*100 -> 21.993258 | G20: 169253 | H20: =G20/$C20*100 -> 16.388024 | I20: 60538 | J20: =I20/$C20*100 -> 5.8616284 | K20: 859250 | L20: =K20/$C20*100 -> 83.1974 | M20: 2026 | N20: =M20/$C20*100 -> 0.19616867 | O20: 0 | P20: =O20/$C20*100 -> 0 | Q20: 2782 | R20: =Q20/$C20*100 -> 0.26936883
... A26: Bangsamoro Autonomous Region in Muslim Mindanao | B26: ='Estimated Totals'!D24 -> 2943119 | C26: 130981.06 | D26: =C26/B26*100 -> 4.4504169 | E26: 9231 | F26: =E26/$C26*100 -> 7.0475836 | G26: 8921 | H26: =G26/$C26*100 -> 6.8109082 | I26: 7260 | J26: =I26/$C26*100 -> 5.5427859 | K26: 114832 | L26: =K26/$C26*100 -> 87.670688 | M26: 571 | N26: =M26/$C26*100 -> 0.43594088 | O26: 0 | P26: =O26/$C26*100 -> 0 | Q26: 0 | R26: =Q26/$C26*100 -> 0
A29: Region | B29: 2024
B30: Total Individuals | C30: Internet User | E30: Type of Device Used
E31: Desktop | G31: Laptop | I31: Tablet or Similar Device | K31: Cellphone | M31: Gaming Console | O31: Smart TV/Set Top Box | Q31: Others
C32: Number | D32: Proportion | E32: Number | F32: Proportion | G32: Number | H32: Proportion | I32: Number | J32: Proportion | K32: Number | L32: Proportion | M32: Number | N32: Proportion | O32: Number | P32: Proportion | Q32: Number | R32: Proportion
A34: PHILIPPINES | B34: 91383228 | C34: 61457081 | D34: =(C34/B34)*100 -> 67.252036 | E34: 6145236 | F34: =(E34/$C34)*100 -> 9.9992318 | G34: 9010693 | H34: =(G34/$C34)*100 -> 14.661765 | I34: 2575672 | J34: =(I34/$C34)*100 -> 4.1910093 | K34: 60735509 | L34: =(K34/$C34)*100 -> 98.825893 | M34: 1448856 | N34: =(M34/$C34)*100 -> 2.3575086 | O34: 6921298 | P34: =(O34/$C34)*100 -> 11.262002 | Q34: 70990 | R34: =(Q34/$C34)*100 -> 0.11551151
A35: National Capital Region | B35: 11919468 | C35: 9448296 | D35: =(C35/B35)*100 -> 79.267766 | E35: 1397898 | F35: =(E35/$C35)*100 -> 14.795239 | G35: 2085971 | H35: =(G35/$C35)*100 -> 22.077748 | I35: 600093 | J35: =(I35/$C35)*100 -> 6.3513357 | K35: 9311668 | L35: =(K35/$C35)*100 -> 98.55394 | M35: 393095 | N35: =(M35/$C35)*100 -> 4.1604857 | O35: 2512366 | P35: =(O35/$C35)*100 -> 26.590678 | Q35: 0 | R35: =(Q35/$C35)*100 -> 0
A36: Cordillera Administrative Region | B36: 1496049 | C36: 1074349 | D36: =(C36/B36)*100 -> 71.812421 | E36: 98298 | F36: =(E36/$C36)*100 -> 9.1495408 | G36: 148652 | H36: =(G36/$C36)*100 -> 13.836472 | I36: 40251 | J36: =(I36/$C36)*100 -> 3.7465479 | K36: 1066606 | L36: =(K36/$C36)*100 -> 99.279284 | M36: 14579 | N36: =(M36/$C36)*100 -> 1.3570078 | O36: 51019 | P36: =(O36/$C36)*100 -> 4.7488293 | Q36: 0 | R36: =(Q36/$C36)*100 -> 0
A37: Region I - Ilocos Region | B37: 4389510 | C37: 3260630 | D37: =(C37/B37)*100 -> 74.282323 | E37: 266545 | F37: =(E37/$C37)*100 -> 8.1746472 | G37: 334970 | H37: =(G37/$C37)*100 -> 10.273168 | I37: 150418 | J37: =(I37/$C37)*100 -> 4.6131576 | K37: 3232401 | L37: =(K37/$C37)*100 -> 99.134247 | M37: 63718 | N37: =(M37/$C37)*100 -> 1.9541622 | O37: 88812 | P37: =(O37/$C37)*100 -> 2.7237681 | Q37: 0 | R37: =(Q37/$C37)*100 -> 0
A38: Region II - Cagayan Valley | B38: 3055894 | C38: 2290016 | D38: =(C38/B38)*100 -> 74.937678 | E38: 136204 | F38: =(E38/$C38)*100 -> 5.9477314 | G38: 338756 | H38: =(G38/$C38)*100 -> 14.792735 | I38: 96576 | J38: =(I38/$C38)*100 -> 4.2172631 | K38: 2275838 | L38: =(K38/$C38)*100 -> 99.380878 | M38: 13952 | N38: =(M38/$C38)*100 -> 0.60925339 | O38: 137545 | P38: =(O38/$C38)*100 -> 6.0062899 | Q38: 8299 | R38: =(Q38/$C38)*100 -> 0.36239921
A39: Region III - Central Luzon | B39: 10708290 | C39: 7926396 | D39: =(C39/B39)*100 -> 74.021118 | E39: 619467 | F39: =(E39/$C39)*100 -> 7.8152416 | G39: 1180215 | H39: =(G39/$C39)*100 -> 14.88968 | I39: 321406 | J39: =(I39/$C39)*100 -> 4.0548819 | K39: 7871966 | L39: =(K39/$C39)*100 -> 99.313307 | M39: 190658 | N39: =(M39/$C39)*100 -> 2.4053555 | O39: 1123239 | P39: =(O39/$C39)*100 -> 14.170867 | Q39: 0 | R39: =(Q39/$C39)*100 -> 0
A40: Region IV-A - CALABARZON | B40: 13985526 | C40: 9979157 | D40: =(C40/B40)*100 -> 71.353462 | E40: 1429906 | F40: =(E40/$C40)*100 -> 14.328926 | G40: 1650443 | H40: =(G40/$C40)*100 -> 16.538902 | I40: 366898 | J40: =(I40/$C40)*100 -> 3.6766432 | K40: 9828802 | L40: =(K40/$C40)*100 -> 98.49331 | M40: 236363 | N40: =(M40/$C40)*100 -> 2.3685668 | O40: 1150017 | P40: =(O40/$C40)*100 -> 11.52419 | Q40: 0 | R40: =(Q40/$C40)*100 -> 0
A41: MIMAROPA Region | B41: 2538126 | C41: 1614249 | D41: =(C41/B41)*100 -> 63.600034 | E41: 90398 | F41: =(E41/$C41)*100 -> 5.6000035 | G41: 222153 | H41: =(G41/$C41)*100 -> 13.762003 | I41: 75910 | J41: =(I41/$C41)*100 -> 4.7024963 | K41: 1608746 | L41: =(K41/$C41)*100 -> 99.659098 | M41: 24756 | N41: =(M41/$C41)*100 -> 1.5335924 | O41: 53174 | P41: =(O41/$C41)*100 -> 3.2940395 | Q41: 2228 | R41: =(Q41/$C41)*100 -> 0.13802084
A42: Region V - Bicol Region | B42: 4884805 | C42: 3094742 | D42: =(C42/B42)*100 -> 63.354463 | E42: 178358 | F42: =(E42/$C42)*100 -> 5.7632591 | G42: 411879 | H42: =(G42/$C42)*100 -> 13.308993 | I42: 101037 | J42: =(I42/$C42)*100 -> 3.2647956 | K42: 3066470 | L42: =(K42/$C42)*100 -> 99.08645 | M42: 51794 | N42: =(M42/$C42)*100 -> 1.6736129 | O42: 271997 | P42: =(O42/$C42)*100 -> 8.7890041 | Q42: 1435 | R42: =(Q42/$C42)*100 -> 0.04636897
A43: Region VI - Western Visayas | B43: 6586874 | C43: 4053706 | D43: =(C43/B43)*100 -> 61.542182 | E43: 284849 | F43: =(E43/$C43)*100 -> 7.0268786 | G43: 372957 | H43: =(G43/$C43)*100 -> 9.2003959 | I43: 154306 | J43: =(I43/$C43)*100 -> 3.8065415 | K43: 4003423 | L43: =(K43/$C43)*100 -> 98.75958 | M43: 43718 | N43: =(M43/$C43)*100 -> 1.0784699 | O43: 232847 | P43: =(O43/$C43)*100 -> 5.7440525 | Q43: 14295 | R43: =(Q43/$C43)*100 -> 0.35264028
A44: Region VII - Central Visayas | B44: 6668940 | C44: 4522717 | D44: =(C44/B44)*100 -> 67.817629 | E44: 570485 | F44: =(E44/$C44)*100 -> 12.613767 | G44: 682442 | H44: =(G44/$C44)*100 -> 15.089204 | I44: 219592 | J44: =(I44/$C44)*100 -> 4.8553115 | K44: 4446710 | L44: =(K44/$C44)*100 -> 98.319439 | M44: 146972 | N44: =(M44/$C44)*100 -> 3.2496395 | O44: 461730 | P44: =(O44/$C44)*100 -> 10.209129 | Q44: 21546 | R44: =(Q44/$C44)*100 -> 0.47639505
A45: Region VIII - Eastern Visayas | B45: 3864215 | C45: 2570726 | D45: =(C45/B45)*100 -> 66.526474 | E45: 175716 | F45: =(E45/$C45)*100 -> 6.8352675 | G45: 348655 | H45: =(G45/$C45)*100 -> 13.562511 | I45: 70629 | J45: =(I45/$C45)*100 -> 2.747434 | K45: 2540348 | L45: =(K45/$C45)*100 -> 98.81831 | M45: 32451 | N45: =(M45/$C45)*100 -> 1.2623282 | O45: 122791 | P45: =(O45/$C45)*100 -> 4.7765106 | Q45: 3601 | R45: =(Q45/$C45)*100 -> 0.14007716
... A51: Bangsamoro Autonomous Region in Muslim Mindanao | B51: 3746618 | C51: 1496986 | D51: =(C51/B51)*100 -> 39.955661 | E51: 49794 | F51: =(E51/$C51)*100 -> 3.3262836 | G51: 115651 | H51: =(G51/$C51)*100 -> 7.72559 | I51: 40002 | J51: =(I51/$C51)*100 -> 2.6721693 | K51: 1483679 | L51: =(K51/$C51)*100 -> 99.111081 | M51: 34637 | N51: =(M51/$C51)*100 -> 2.3137825 | O51: 17044 | P51: =(O51/$C51)*100 -> 1.1385544 | Q51: 0 | R51: =(Q51/$C51)*100 -> 0
A54: Notes:
A55: Details may not add up to totals due to rounding.
A56: p Estimates are preliminary and may change
A57: r Revised
A58: Source of data: Philippine Statistics Authority, 2024 National Information and Communications Technology Household Survey.

Sheet i_C21&24
A1: BACK TO LIST
A2: Table #. Number and Proportion of Individuals Using the Internet by Access Location and Region, Philippines: 2019r and 2024p
A4: Region | B4: 2019
B5: Internet User | C5: Access Location
C6: Home | E6: Work | G6: Place of Education | I6: In Another Person's Home | K6: In Public Access Venues | M6: In Commercial Establishments | O6: In Mobility
C7: Number | D7: Proportion | E7: Number | F7: Proportion | G7: Number | H7: Proportion | I7: Number | J7: Proportion | K7: Number | L7: Proportion | M7: Number | N7: Proportion | O7: Number | P7: Proportion
A9: PHILIPPINES | B9: ='i_C21&23'!C9 -> 21118015 | C9: 8375825.5 | D9: =(C9/$B9)*100 -> 39.661992 | E9: 3055604.7 | F9: =(E9/$B9)*100 -> 14.469185 | G9: 2423682.3 | H9: =(G9/$B9)*100 -> 11.476847 | I9: 2794963.7 | J9: =(I9/$B9)*100 -> 13.234974 | K9: 1521504 | L9: =(K9/$B9)*100 -> 7.204768 | M9: 5592125.4 | N9: =(M9/$B9)*100 -> 26.480355 | O9: 13397390 | P9: =(O9/$B9)*100 -> 63.440572
A10: National Capital Region | B10: ='i_C21&23'!C10 -> 4434947.7 | C10: 2192868.9 | D10: =(C10/$B10)*100 -> 49.445203 | E10: 941528.37 | F10: =(E10/$B10)*100 -> 21.229751 | G10: 680678.79 | H10: =(G10/$B10)*100 -> 15.348068 | I10: 930841.16 | J10: =(I10/$B10)*100 -> 20.988774 | K10: 592673.4 | L10: =(K10/$B10)*100 -> 13.363707 | M10: 1503100.1 | N10: =(M10/$B10)*100 -> 33.892171 | O10: 2617759.1 | P10: =(O10/$B10)*100 -> 59.025705
A11: Cordillera Administrative Region | B11: ='i_C21&23'!C11 -> 322391.19 | C11: 114184.86 | D11: =(C11/$B11)*100 -> 35.418108 | E11: 27823.264 | F11: =(E11/$B11)*100 -> 8.6302804 | G11: 12894.186 | H11: =(G11/$B11)*100 -> 3.9995465 | I11: 3953.3329 | J11: =(I11/$B11)*100 -> 1.2262534 | K11: 2810.6596 | L11: =(K11/$B11)*100 -> 0.8718165 | M11: 48344.353 | N11: =(M11/$B11)*100 -> 14.995556 | O11: 214110.48 | P11: =(O11/$B11)*100 -> 66.413253
A12: Region I - Ilocos Region | B12: ='i_C21&23'!C12 -> 1269147.6 | C12: 475743.79 | D12: =(C12/$B12)*100 -> 37.4853 | E12: 126948.57 | F12: =(E12/$B12)*100 -> 10.002664 | G12: 111673.32 | H12: =(G12/$B12)*100 -> 8.7990802 | I12: 105481.71 | J12: =(I12/$B12)*100 -> 8.311225 | K12: 13065.392 | L12: =(K12/$B12)*100 -> 1.029462 | M12: 258051.95 | N12: =(M12/$B12)*100 -> 20.332698 | O12: 1091161.5 | P12: =(O12/$B12)*100 -> 85.975937
A13: Region II - Cagayan Valley | B13: ='i_C21&23'!C13 -> 608713.36 | C13: 277188.05 | D13: =(C13/$B13)*100 -> 45.536711 | E13: 82261.159 | F13: =(E13/$B13)*100 -> 13.51394 | G13: 56380.325 | H13: =(G13/$B13)*100 -> 9.2622125 | I13: 47575.344 | J13: =(I13/$B13)*100 -> 7.815722 | K13: 40327.915 | L13: =(K13/$B13)*100 -> 6.6251076 | M13: 65460.527 | N13: =(M13/$B13)*100 -> 10.753917 | O13: 236469.64 | P13: =(O13/$B13)*100 -> 38.847453
A14: Region III - Central Luzon | B14: ='i_C21&23'!C14 -> 3210821.1 | C14: 1634298.8 | D14: =(C14/$B14)*100 -> 50.899715 | E14: 422842.27 | F14: =(E14/$B14)*100 -> 13.169288 | G14: 205561.05 | H14: =(G14/$B14)*100 -> 6.4021336 | I14: 265172.43 | J14: =(I14/$B14)*100 -> 8.2587111 | K14: 127447.26 | L14: =(K14/$B14)*100 -> 3.9693045 | M14: 514199.27 | N14: =(M14/$B14)*100 -> 16.014573 | O14: 2114364.8 | P14: =(O14/$B14)*100 -> 65.85122
A15: Region IV-A - CALABARZON | B15: ='i_C21&23'!C15 -> 4117581.3 | C15: 1344288.9 | D15: =(C15/$B15)*100 -> 32.647537 | E15: 671302.11 | F15: =(E15/$B15)*100 -> 16.303312 | G15: 484596.72 | H15: =(G15/$B15)*100 -> 11.768966 | I15: 905544.89 | J15: =(I15/$B15)*100 -> 21.992156 | K15: 299580.9 | L15: =(K15/$B15)*100 -> 7.2756524 | M15: 1150761.4 | N15: =(M15/$B15)*100 -> 27.947508 | O15: 2645469.2 | P15: =(O15/$B15)*100 -> 64.248135
A16: MIMAROPA Region | B16: ='i_C21&23'!C16 -> 437023.26 | C16: 107860.24 | D16: =(C16/$B16)*100 -> 24.680665 | E16: 53016.298 | F16: =(E16/$B16)*100 -> 12.13123 | G16: 55385.07 | H16: =(G16/$B16)*100 -> 12.673254 | I16: 77964.294 | J16: =(I16/$B16)*100 -> 17.83985 | K16: 38003.907 | L16: =(K16/$B16)*100 -> 8.6960835 | M16: 71587.485 | N16: =(M16/$B16)*100 -> 16.380704 | O16: 356521.32 | P16: =(O16/$B16)*100 -> 81.579485
A17: Region V - Bicol Region | B17: ='i_C21&23'!C17 -> 795978.54 | C17: 375031.53 | D17: =(C17/$B17)*100 -> 47.115785 | E17: 115111.58 | F17: =(E17/$B17)*100 -> 14.461643 | G17: 180700.52 | H17: =(G17/$B17)*100 -> 22.701682 | I17: 89184.255 | J17: =(I17/$B17)*100 -> 11.204354 | K17: 100587.72 | L17: =(K17/$B17)*100 -> 12.636989 | M17: 239510.18 | N17: =(M17/$B17)*100 -> 30.09003 | O17: 368780.13 | P17: =(O17/$B17)*100 -> 46.330412
A18: Region VI - Western Visayas | B18: ='i_C21&23'!C18 -> 1148816 | C18: 419424.22 | D18: =(C18/$B18)*100 -> 36.509259 | E18: 126801.41 | F18: =(E18/$B18)*100 -> 11.037573 | G18: 207853.68 | H18: =(G18/$B18)*100 -> 18.09286 | I18: 69549.336 | J18: =(I18/$B18)*100 -> 6.0540012 | K18: 109371.76 | L18: =(K18/$B18)*100 -> 9.5203895 | M18: 194665.23 | N18: =(M18/$B18)*100 -> 16.944857 | O18: 701556.24 | P18: =(O18/$B18)*100 -> 61.067762
A19: Region VII - Central Visayas | B19: ='i_C21&23'!C19 -> 847079.18 | C19: 359267.69 | D19: =(C19/$B19)*100 -> 42.412528 | E19: 95244.991 | F19: =(E19/$B19)*100 -> 11.24393 | G19: 64656.051 | H19: =(G19/$B19)*100 -> 7.6328226 | I19: 45227.328 | J19: =(I19/$B19)*100 -> 5.339209 | K19: 23488.375 | L19: =(K19/$B19)*100 -> 2.7728665 | M19: 311689.78 | N19: =(M19/$B19)*100 -> 36.795826 | O19: 430883.18 | P19: =(O19/$B19)*100 -> 50.86693
A20: Region VIII - Eastern Visayas | B20: ='i_C21&23'!C20 -> 1032784.7 | C20: 239892.2 | D20: =(C20/$B20)*100 -> 23.227707 | E20: 80697.893 | F20: =(E20/$B20)*100 -> 7.8136222 | G20: 74504.507 | H20: =(G20/$B20)*100 -> 7.2139439 | I20: 44020.257 | J20: =(I20/$B20)*100 -> 4.262288 | K20: 30009.952 | L20: =(K20/$B20)*100 -> 2.9057317 | M20: 206471.89 | N20: =(M20/$B20)*100 -> 19.991765 | O20: 766116.92 | P20: =(O20/$B20)*100 -> 74.179734
... A26: Bangsamoro Autonomous Region in Muslim Mindanao | B26: ='i_C21&23'!C26 -> 130981.06 | C26: 44725.117 | D26: =(C26/$B26)*100 -> 34.146247 | E26: 6736.1782 | F26: =(E26/$B26)*100 -> 5.1428641 | G26: 7088.4192 | H26: =(G26/$B26)*100 -> 5.4117893 | I26: 10309.337 | J26: =(I26/$B26)*100 -> 7.870861 | K26: 10052.566 | L26: =(K26/$B26)*100 -> 7.6748237 | M26: 4570.376 | N26: =(M26/$B26)*100 -> 3.4893411 | O26: 78007.001 | P26: =(O26/$B26)*100 -> 59.555938
A29: Region | B29: 2024
B30: Internet User | C30: Access Location
C31: Home | E31: Work | G31: Place of Education | I31: In Another Person's Home | K31: In Public Access Venues | M31: In Commercial Establishments | O31: In Mobility
C32: Number | D32: Proportion | E32: Number | F32: Proportion | G32: Number | H32: Proportion | I32: Number | J32: Proportion | K32: Number | L32: Proportion | M32: Number | N32: Proportion | O32: Number | P32: Proportion
A34: PHILIPPINES | B34: 61457081 | C34: 44943573 | D34: =(C34/$B34)*100 -> 73.130016 | E34: 12244617 | F34: =(E34/$B34)*100 -> 19.923851 | G34: 9281896 | H34: =(G34/$B34)*100 -> 15.103054 | I34: 22663051 | J34: =(I34/$B34)*100 -> 36.876224 | K34: 7083397 | L34: =(K34/$B34)*100 -> 11.525762 | M34: 18551656 | N34: =(M34/$B34)*100 -> 30.18636 | O34: 16822430 | P34: =(O34/$B34)*100 -> 27.372647
A35: National Capital Region | B35: 9448296 | C35: 8100695 | D35: =(C35/$B35)*100 -> 85.7371 | E35: 2660169 | F35: =(E35/$B35)*100 -> 28.155013 | G35: 832377 | H35: =(G35/$B35)*100 -> 8.8098108 | I35: 2672814 | J35: =(I35/$B35)*100 -> 28.288847 | K35: 615473 | L35: =(K35/$B35)*100 -> 6.5141164 | M35: 1621505 | N35: =(M35/$B35)*100 -> 17.161878 | O35: 3699942 | P35: =(O35/$B35)*100 -> 39.159887
A36: Cordillera Administrative Region | B36: 1074349 | C36: 729281 | D36: =(C36/$B36)*100 -> 67.881201 | E36: 197956 | F36: =(E36/$B36)*100 -> 18.42567 | G36: 216180 | H36: =(G36/$B36)*100 -> 20.121953 | I36: 469944 | J36: =(I36/$B36)*100 -> 43.74221 | K36: 282748 | L36: =(K36/$B36)*100 -> 26.318077 | M36: 259930 | N36: =(M36/$B36)*100 -> 24.194186 | O36: 455765 | P36: =(O36/$B36)*100 -> 42.422434
A37: Region I - Ilocos Region | B37: 3260630 | C37: 2700608 | D37: =(C37/$B37)*100 -> 82.82473 | E37: 664372 | F37: =(E37/$B37)*100 -> 20.375572 | G37: 816363 | H37: =(G37/$B37)*100 -> 25.036971 | I37: 1815028 | J37: =(I37/$B37)*100 -> 55.664948 | K37: 756020 | L37: =(K37/$B37)*100 -> 23.186317 | M37: 699960 | N37: =(M37/$B37)*100 -> 21.467017 | O37: 559252 | P37: =(O37/$B37)*100 -> 17.151655
A38: Region II - Cagayan Valley | B38: 2290016 | C38: 1884107 | D38: =(C38/$B38)*100 -> 82.27484 | E38: 477439 | F38: =(E38/$B38)*100 -> 20.848719 | G38: 465572 | H38: =(G38/$B38)*100 -> 20.330513 | I38: 759885 | J38: =(I38/$B38)*100 -> 33.182519 | K38: 344838 | L38: =(K38/$B38)*100 -> 15.058323 | M38: 382990 | N38: =(M38/$B38)*100 -> 16.724337 | O38: 906310 | P38: =(O38/$B38)*100 -> 39.576579
A39: Region III - Central Luzon | B39: 7926396 | C39: 6753644 | D39: =(C39/$B39)*100 -> 85.204474 | E39: 1359893 | F39: =(E39/$B39)*100 -> 17.156511 | G39: 1001581 | H39: =(G39/$B39)*100 -> 12.63602 | I39: 3022496 | J39: =(I39/$B39)*100 -> 38.132034 | K39: 826556 | L39: =(K39/$B39)*100 -> 10.427892 | M39: 1551486 | N39: =(M39/$B39)*100 -> 19.573662 | O39: 1954574 | P39: =(O39/$B39)*100 -> 24.659051
A40: Region IV-A - CALABARZON | B40: 9979157 | C40: 7268535 | D40: =(C40/$B40)*100 -> 72.837165 | E40: 2341586 | F40: =(E40/$B40)*100 -> 23.464768 | G40: 1338277 | H40: =(G40/$B40)*100 -> 13.410722 | I40: 4052375 | J40: =(I40/$B40)*100 -> 40.60839 | K40: 998360 | L40: =(K40/$B40)*100 -> 10.004452 | M40: 2417919 | N40: =(M40/$B40)*100 -> 24.229692 | O40: 3177002 | P40: =(O40/$B40)*100 -> 31.836377
A41: MIMAROPA Region | B41: 1614249 | C41: 986584 | D41: =(C41/$B41)*100 -> 61.117213 | E41: 266244 | F41: =(E41/$B41)*100 -> 16.493366 | G41: 244214 | H41: =(G41/$B41)*100 -> 15.128645 | I41: 722632 | J41: =(I41/$B41)*100 -> 44.765832 | K41: 229261 | L41: =(K41/$B41)*100 -> 14.202332 | M41: 496846 | N41: =(M41/$B41)*100 -> 30.778771 | O41: 155407 | P41: =(O41/$B41)*100 -> 9.6272013
A42: Region V - Bicol Region | B42: 3094742 | C42: 1815882 | D42: =(C42/$B42)*100 -> 58.676361 | E42: 408716 | F42: =(E42/$B42)*100 -> 13.206788 | G42: 470286 | H42: =(G42/$B42)*100 -> 15.196291 | I42: 920843 | J42: =(I42/$B42)*100 -> 29.755081 | K42: 329174 | L42: =(K42/$B42)*100 -> 10.636557 | M42: 1413544 | N42: =(M42/$B42)*100 -> 45.675665 | O42: 967117 | P42: =(O42/$B42)*100 -> 31.250327
A43: Region VI - Western Visayas | B43: 4053706 | C43: 2889155 | D43: =(C43/$B43)*100 -> 71.271942 | E43: 780799 | F43: =(E43/$B43)*100 -> 19.261362 | G43: 817589 | H43: =(G43/$B43)*100 -> 20.168927 | I43: 1179214 | J43: =(I43/$B43)*100 -> 29.089776 | K43: 620407 | L43: =(K43/$B43)*100 -> 15.304687 | M43: 1460028 | N43: =(M43/$B43)*100 -> 36.017116 | O43: 627464 | P43: =(O43/$B43)*100 -> 15.478774
A44: Region VII - Central Visayas | B44: 4522717 | C44: 3056236 | D44: =(C44/$B44)*100 -> 67.575221 | E44: 947528 | F44: =(E44/$B44)*100 -> 20.950415 | G44: 700238 | H44: =(G44/$B44)*100 -> 15.482684 | I44: 1512763 | J44: =(I44/$B44)*100 -> 33.448102 | K44: 588888 | L44: =(K44/$B44)*100 -> 13.020669 | M44: 1776698 | N44: =(M44/$B44)*100 -> 39.283864 | O44: 1848332 | P44: =(O44/$B44)*100 -> 40.867735
A45: Region VIII - Eastern Visayas | B45: 2570726 | C45: 1479729 | D45: =(C45/$B45)*100 -> 57.560744 | E45: 427711 | F45: =(E45/$B45)*100 -> 16.637751 | G45: 417050 | H45: =(G45/$B45)*100 -> 16.223044 | I45: 497985 | J45: =(I45/$B45)*100 -> 19.371376 | K45: 183547 | L45: =(K45/$B45)*100 -> 7.1398897 | M45: 1208656 | N45: =(M45/$B45)*100 -> 47.016135 | O45: 517560 | P45: =(O45/$B45)*100 -> 20.132834
... A51: Bangsamoro Autonomous Region in Muslim Mindanao | B51: 1496986 | C51: 776758 | D51: =(C51/$B51)*100 -> 51.888127 | E51: 132219 | F51: =(E51/$B51)*100 -> 8.8323471 | G51: 270140 | H51: =(G51/$B51)*100 -> 18.045593 | I51: 599523 | J51: =(I51/$B51)*100 -> 40.048671 | K51: 205979 | L51: =(K51/$B51)*100 -> 13.759581 | M51: 748271 | N51: =(M51/$B51)*100 -> 49.98517 | O51: 282053 | P51: =(O51/$B51)*100 -> 18.841392
A54: Notes:
A55: Details may not add up to totals due to rounding.
A56: p Estimates are preliminary and may change
A57: r Revised
A58: Source of data: Philippine Statistics Authority, 2024 National Information and Communications Technology Household Survey.

Sheet i_C21&25
A1: BACK TO LIST
A2: Table #. Number and Proportion of Individuals Using the Internet by Frequency of Access and Region, Philippines: 2019r and 2024p
A4: Region | B4: 2019 | K4: 2024
B5: Internet User | C5: Frequency of Access | K5: Internet User | L5: Frequency of Access
C6: Daily/Every day | E6: Weekly but Not Every day | G6: Monthly but Not Weekly | I6: Not Regular, Only When Needed | L6: Daily/Every day | N6: Weekly but Not Every day | P6: Monthly but Not Weekly | R6: Not Regular, Only When Needed
C7: Number | D7: Proportion | E7: Number | F7: Proportion | G7: Number | H7: Proportion | I7: Number | J7: Proportion | L7: Number | M7: Proportion | N7: Number | O7: Proportion | P7: Number | Q7: Proportion | R7: Number | S7: Proportion
A9: PHILIPPINES | B9: ='i_C21&23'!C9 -> 21118015 | C9: 11799971 | D9: =(C9/$B9)*100 -> 55.876326 | E9: 5400799.8 | F9: =(E9/$B9)*100 -> 25.574372 | G9: 483663.51 | H9: =(G9/$B9)*100 -> 2.2902887 | I9: 3433580.9 | J9: =(I9/$B9)*100 -> 16.259013 | K9: 61457081 | L9: 47244508 | M9: =(L9/$K9)*100 -> 76.873986 | N9: 10064889 | O9: =(N9/$K9)*100 -> 16.377102 | P9: 612285 | Q9: =(P9/$K9)*100 -> 0.99628064 | R9: 3535398 | S9: =(R9/$K9)*100 -> 5.7526292
A10: National Capital Region | B10: ='i_C21&23'!C10 -> 4434947.7 | C10: 3092485.6 | D10: =(C10/$B10)*100 -> 69.729922 | E10: 839110.31 | F10: =(E10/$B10)*100 -> 18.920411 | G10: 70341.905 | H10: =(G10/$B10)*100 -> 1.586082 | I10: 433009.9 | J10: =(I10/$B10)*100 -> 9.7635854 | K10: 9448296 | L10: 8598204 | M10: =(L10/$K10)*100 -> 91.002695 | N10: 537657 | O10: =(N10/$K10)*100 -> 5.6905182 | P10: 30069 | Q10: =(P10/$K10)*100 -> 0.31824786 | R10: 282365 | S10: =(R10/$K10)*100 -> 2.9885283
A11: Cordillera Administrative Region | B11: ='i_C21&23'!C11 -> 322391.19 | C11: 178879.81 | D11: =(C11/$B11)*100 -> 55.485328 | E11: 77849.008 | F11: =(E11/$B11)*100 -> 24.147374 | G11: 12378.929 | H11: =(G11/$B11)*100 -> 3.839723 | I11: 53283.447 | J11: =(I11/$B11)*100 -> 16.527575 | K11: 1074349 | L11: 773775 | M11: =(L11/$K11)*100 -> 72.022685 | N11: 210970 | O11: =(N11/$K11)*100 -> 19.637008 | P11: 11897 | Q11: =(P11/$K11)*100 -> 1.1073683 | R11: 77708 | S11: =(R11/$K11)*100 -> 7.2330314
A12: Region I - Ilocos Region | B12: ='i_C21&23'!C12 -> 1269147.6 | C12: 796818.3 | D12: =(C12/$B12)*100 -> 62.783737 | E12: 443613.25 | F12: =(E12/$B12)*100 -> 34.953638 | G12: 12907.723 | H12: =(G12/$B12)*100 -> 1.0170388 | I12: 15808.328 | J12: =(I12/$B12)*100 -> 1.2455863 | K12: 3260630 | L12: 2567140 | M12: =(L12/$K12)*100 -> 78.731411 | N12: 680854 | O12: =(N12/$K12)*100 -> 20.881057 | P12: 2000 | Q12: =(P12/$K12)*100 -> 0.06133784 | R12: 10636 | S12: =(R12/$K12)*100 -> 0.32619463
A13: Region II - Cagayan Valley | B13: ='i_C21&23'!C13 -> 608713.36 | C13: 227025.86 | D13: =(C13/$B13)*100 -> 37.296021 | E13: 121346.14 | F13: =(E13/$B13)*100 -> 19.934857 | G13: 3303.4437 | H13: =(G13/$B13)*100 -> 0.54269282 | I13: 257037.92 | J13: =(I13/$B13)*100 -> 42.226429 | K13: 2290016 | L13: 1702564 | M13: =(L13/$K13)*100 -> 74.347253 | N13: 466299 | O13: =(N13/$K13)*100 -> 20.362259 | P13: 54132 | Q13: =(P13/$K13)*100 -> 2.3638263 | R13: 67020 | S13: =(R13/$K13)*100 -> 2.9266171
A14: Region III - Central Luzon | B14: ='i_C21&23'!C14 -> 3210821.1 | C14: 1954920.6 | D14: =(C14/$B14)*100 -> 60.885381 | E14: 943050.85 | F14: =(E14/$B14)*100 -> 29.371019 | G14: 21204.94 | H14: =(G14/$B14)*100 -> 0.6604211 | I14: 291644.64 | J14: =(I14/$B14)*100 -> 9.0831797 | K14: 7926396 | L14: 6305933 | M14: =(L14/$K14)*100 -> 79.556119 | N14: 1023354 | O14: =(N14/$K14)*100 -> 12.91071 | P14: 111940 | Q14: =(P14/$K14)*100 -> 1.4122433 | R14: 485170 | S14: =(R14/$K14)*100 -> 6.1209407
A15: Region IV-A - CALABARZON | B15: ='i_C21&23'!C15 -> 4117581.3 | C15: 2540449.1 | D15: =(C15/$B15)*100 -> 61.697608 | E15: 502738.19 | F15: =(E15/$B15)*100 -> 12.209551 | G15: 19000.744 | H15: =(G15/$B15)*100 -> 0.46145402 | I15: 1055393.2 | J15: =(I15/$B15)*100 -> 25.631387 | K15: 9979157 | L15: 7838006 | M15: =(L15/$K15)*100 -> 78.543769 | N15: 1313264 | O15: =(N15/$K15)*100 -> 13.16007 | P15: 43041 | Q15: =(P15/$K15)*100 -> 0.43130898 | R15: 784846 | S15: =(R15/$K15)*100 -> 7.8648527
A16: MIMAROPA Region | B16: ='i_C21&23'!C16 -> 437023.26 | C16: 229632.71 | D16: =(C16/$B16)*100 -> 52.544735 | E16: 96614.972 | F16: =(E16/$B16)*100 -> 22.107513 | G16: 20582.456 | H16: =(G16/$B16)*100 -> 4.7096934 | I16: 90193.116 | J16: =(I16/$B16)*100 -> 20.638059 | K16: 1614249 | L16: 1072207 | M16: =(L16/$K16)*100 -> 66.421413 | N16: 449175 | O16: =(N16/$K16)*100 -> 27.825633 | P16: 17492 | Q16: =(P16/$K16)*100 -> 1.0835999 | R16: 75374 | S16: =(R16/$K16)*100 -> 4.669292
A17: Region V - Bicol Region | B17: ='i_C21&23'!C17 -> 795978.54 | C17: 359417.77 | D17: =(C17/$B17)*100 -> 45.154204 | E17: 111153.85 | F17: =(E17/$B17)*100 -> 13.964428 | G17: 9339.712 | H17: =(G17/$B17)*100 -> 1.1733623 | I17: 316067.2 | J17: =(I17/$B17)*100 -> 39.708006 | K17: 3094742 | L17: 2086984 | M17: =(L17/$K17)*100 -> 67.436445 | N17: 729544 | O17: =(N17/$K17)*100 -> 23.573661 | P17: 45397 | Q17: =(P17/$K17)*100 -> 1.4669074 | R17: 232817 | S17: =(R17/$K17)*100 -> 7.5229858
A18: Region VI - Western Visayas | B18: ='i_C21&23'!C18 -> 1148816 | C18: 555140.89 | D18: =(C18/$B18)*100 -> 48.322872 | E18: 399396.82 | F18: =(E18/$B18)*100 -> 34.765951 | G18: 16861.025 | H18: =(G18/$B18)*100 -> 1.4676871 | I18: 177417.29 | J18: =(I18/$B18)*100 -> 15.44349 | K18: 4053706 | L18: 3088204 | M18: =(L18/$K18)*100 -> 76.182239 | N18: 727075 | O18: =(N18/$K18)*100 -> 17.936057 | P18: 28152 | Q18: =(P18/$K18)*100 -> 0.69447562 | R18: 210276 | S18: =(R18/$K18)*100 -> 5.1872533
A19: Region VII - Central Visayas | B19: ='i_C21&23'!C19 -> 847079.18 | C19: 445568.22 | D19: =(C19/$B19)*100 -> 52.60054 | E19: 261324 | F19: =(E19/$B19)*100 -> 30.850008 | G19: 22361.95 | H19: =(G19/$B19)*100 -> 2.639889 | I19: 117825.01 | J19: =(I19/$B19)*100 -> 13.909563 | K19: 4522717 | L19: 3533008 | M19: =(L19/$K19)*100 -> 78.116937 | N19: 770565 | O19: =(N19/$K19)*100 -> 17.037657 | P19: 37778 | Q19: =(P19/$K19)*100 -> 0.83529436 | R19: 181366 | S19: =(R19/$K19)*100 -> 4.0101116
A20: Region VIII - Eastern Visayas | B20: ='i_C21&23'!C20 -> 1032784.7 | C20: 325305.2 | D20: =(C20/$B20)*100 -> 31.497873 | E20: 489733.92 | F20: =(E20/$B20)*100 -> 47.418783 | G20: 79960.426 | H20: =(G20/$B20)*100 -> 7.7422166 | I20: 137785.12 | J20: =(I20/$B20)*100 -> 13.341128 | K20: 2570726 | L20: 1909975 | M20: =(L20/$K20)*100 -> 74.297105 | N20: 540423 | O20: =(N20/$K20)*100 -> 21.022194 | P20: 35118 | Q20: =(P20/$K20)*100 -> 1.3660732 | R20: 85210 | S20: =(R20/$K20)*100 -> 3.3146279
... A26: Bangsamoro Autonomous Region in Muslim Mindanao | B26: ='i_C21&23'!C26 -> 130981.06 | C26: 33313.407 | D26: =(C26/$B26)*100 -> 25.433758 | E26: 79720.077 | F26: =(E26/$B26)*100 -> 60.863818 | G26: 4464.5468 | H26: =(G26/$B26)*100 -> 3.4085437 | I26: 13483.034 | J26: =(I26/$B26)*100 -> 10.29388 | K26: 1496986 | L26: 874641 | M26: =(L26/$K26)*100 -> 58.426799 | N26: 506273 | O26: =(N26/$K26)*100 -> 33.819488 | P26: 17656 | Q26: =(P26/$K26)*100 -> 1.1794365 | R26: 98416 | S26: =(R26/$K26)*100 -> 6.5742766
A29: Notes:
A30: Details may not add up to totals due to rounding.
A31: p Estimates are preliminary and may change
A32: r Revised
A33: Source of data: Philippine Statistics Authority, 2024 National Information and Communications Technology Household Survey.

Sheet i_C21&27
A1: BACK TO LIST
A2: Table #. Number and Proportion of Individual Using the Internet in by Purpose of Using the Internet and Region, Philippines: 2024p
A4: Region | B4: Internet User | C4: Purpose of Use
C5: Getting Information About Goods or Services | E5: Seeking Health-Related Information | G5: Getting Information from General Government Organizations | I5: Using Services Related to Travel or Travel Related Accommodation | K5: Downloading of Software and/or Application | M5: Reading or Downloading Newspapers, Magazines, or Electronic Books in a Digital Format | O5: Sending or Receiving E-Mail | Q5: Making Calls via the Internet | S5: Participating in Social Networks, Creating User Profile, Posting Messages or Other Contributions | U5: Making an Appointment with a Health Practitioner via the Internet | W5: Interacting with Government Organizations | Y5: Attending an Online Class/Online Course | AA5: Consulting Websites for Formal or Informal Learning Purposes like Wikis, Online Encyclopedias | AC5: Looking for a Job, or Sending/Submitting a Job Application | AE5: Participating in Professional Networks | AG5: Listening to Web Radio | AI5: Watching Web Television | AK5: Streaming or Downloading Web Images, Movies, Videos, or Music | AM5: Playing or Downloading Games | AO5: Uploading Self/User Created Content to a Website to be Shared | AQ5: Using Storage Space on the Internet to Save Documents, Pictures, Music, Video or Other Files | AS5: Using Software that Runs Over the Internet for Editing Text Documents, Spreadsheets, or Presentations
C6: Number | D6: Proportion | E6: Number | F6: Proportion | G6: Number | H6: Proportion | I6: Number | J6: Proportion | K6: Number | L6: Proportion | M6: Number | N6: Proportion | O6: Number | P6: Proportion | Q6: Number | R6: Proportion | S6: Number | T6: Proportion | U6: Number | V6: Proportion | W6: Number | X6: Proportion | Y6: Number | Z6: Proportion | AA6: Number | AB6: Proportion | AC6: Number | AD6: Proportion | AE6: Number | AF6: Proportion | AG6: Number | AH6: Proportion | AI6: Number | AJ6: Proportion | AK6: Number | AL6: Proportion | AM6: Number | AN6: Proportion | AO6: Number | AP6: Proportion | AQ6: Number | AR6: Proportion | AS6: Number | AT6: Proportion
A8: PHILIPPINES | B8: 61457081 | C8: 25486632 | D8: =(C8/$B8)*100 -> 41.470619 | E8: 13217645 | F8: =(E8/$B8)*100 -> 21.507115 | G8: 12803635 | H8: =(G8/$B8)*100 -> 20.833458 | I8: 5347249 | J8: =(I8/$B8)*100 -> 8.7007858 | K8: 17384401 | L8: =(K8/$B8)*100 -> 28.287059 | M8: 5257592 | N8: =(M8/$B8)*100 -> 8.5549003 | O8: 26684342 | P8: =(O8/$B8)*100 -> 43.419475 | Q8: 57898601 | R8: =(Q8/$B8)*100 -> 94.209813 | S8: 53639858 | T8: =(S8/$B8)*100 -> 87.280192 | U8: 3329662 | V8: =(U8/$B8)*100 -> 5.4178655 | W8: 5765219 | X8: =(W8/$B8)*100 -> 9.3808865 | Y8: 5532837 | Z8: =(Y8/$B8)*100 -> 9.0027657 | AA8: 7904443 | AB8: =(AA8/$B8)*100 -> 12.861729 | AC8: 4049303 | AD8: =(AC8/$B8)*100 -> 6.5888307 | AE8: 2726701 | AF8: =(AE8/$B8)*100 -> 4.4367564 | AG8: 5458642 | AH8: =(AG8/$B8)*100 -> 8.8820392 | AI8: 12613635 | AJ8: =(AI8/$B8)*100 -> 20.524299 | AK8: 39077966 | AL8: =(AK8/$B8)*100 -> 63.585783 | AM8: 21655882 | AN8: =(AM8/$B8)*100 -> 35.237407 | AO8: 21051723 | AP8: =(AO8/$B8)*100 -> 34.254349 | AQ8: 10172063 | AR8: =(AQ8/$B8)*100 -> 16.551491 | AS8: 5172029 | AT8: =(AS8/$B8)*100 -> 8.4156763
A9: National Capital Region | B9: 9448296 | C9: 4798479 | D9: =(C9/$B9)*100 -> 50.786713 | E9: 3461158 | F9: =(E9/$B9)*100 -> 36.632616 | G9: 2581902 | H9: =(G9/$B9)*100 -> 27.326642 | I9: 1430393 | J9: =(I9/$B9)*100 -> 15.139164 | K9: 3013475 | L9: =(K9/$B9)*100 -> 31.894375 | M9: 1020887 | N9: =(M9/$B9)*100 -> 10.804985 | O9: 5592552 | P9: =(O9/$B9)*100 -> 59.191118 | Q9: 9110448 | R9: =(Q9/$B9)*100 -> 96.424244 | S9: 7968885 | T9: =(S9/$B9)*100 -> 84.342034 | U9: 975171 | V9: =(U9/$B9)*100 -> 10.321131 | W9: 1389087 | X9: =(W9/$B9)*100 -> 14.701984 | Y9: 1329197 | Z9: =(Y9/$B9)*100 -> 14.068113 | AA9: 1314647 | AB9: =(AA9/$B9)*100 -> 13.914117 | AC9: 814188 | AD9: =(AC9/$B9)*100 -> 8.6172999 | AE9: 553639 | AF9: =(AE9/$B9)*100 -> 5.8596704 | AG9: 1433192 | AH9: =(AG9/$B9)*100 -> 15.168788 | AI9: 3162674 | AJ9: =(AI9/$B9)*100 -> 33.473486 | AK9: 5982118 | AL9: =(AK9/$B9)*100 -> 63.314253 | AM9: 4006462 | AN9: =(AM9/$B9)*100 -> 42.404069 | AO9: 3293070 | AP9: =(AO9/$B9)*100 -> 34.853586 | AQ9: 2241064 | AR9: =(AQ9/$B9)*100 -> 23.71924 | AS9: 1082616 | AT9: =(AS9/$B9)*100 -> 11.45832
A10: Cordillera Administrative Region | B10: 1074349 | C10: 550475 | D10: =(C10/$B10)*100 -> 51.238006 | E10: 206142 | F10: =(E10/$B10)*100 -> 19.18762 | G10: 309872 | H10: =(G10/$B10)*100 -> 28.842769 | I10: 79828 | J10: =(I10/$B10)*100 -> 7.4303602 | K10: 421842 | L10: =(K10/$B10)*100 -> 39.264894 | M10: 113015 | N10: =(M10/$B10)*100 -> 10.519394 | O10: 393398 | P10: =(O10/$B10)*100 -> 36.617338 | Q10: 1001751 | R10: =(Q10/$B10)*100 -> 93.242606 | S10: 933541 | T10: =(S10/$B10)*100 -> 86.893644 | U10: 38773 | V10: =(U10/$B10)*100 -> 3.6089762 | W10: 92337 | X10: =(W10/$B10)*100 -> 8.5946932 | Y10: 57012 | Z10: =(Y10/$B10)*100 -> 5.3066555 | AA10: 199935 | AB10: =(AA10/$B10)*100 -> 18.609874 | AC10: 58393 | AD10: =(AC10/$B10)*100 -> 5.4351984 | AE10: 46443 | AF10: =(AE10/$B10)*100 -> 4.3228969 | AG10: 97103 | AH10: =(AG10/$B10)*100 -> 9.0383106 | AI10: 216979 | AJ10: =(AI10/$B10)*100 -> 20.196324 | AK10: 777966 | AL10: =(AK10/$B10)*100 -> 72.412782 | AM10: 432382 | AN10: =(AM10/$B10)*100 -> 40.245954 | AO10: 368951 | AP10: =(AO10/$B10)*100 -> 34.34182 | AQ10: 145015 | AR10: =(AQ10/$B10)*100 -> 13.497942 | AS10: 96886 | AT10: =(AS10/$B10)*100 -> 9.0181124
A11: Region I - Ilocos Region | B11: 3260630 | C11: 1160436 | D11: =(C11/$B11)*100 -> 35.589319 | E11: 342753 | F11: =(E11/$B11)*100 -> 10.511864 | G11: 436025 | H11: =(G11/$B11)*100 -> 13.372416 | I11: 216967 | J11: =(I11/$B11)*100 -> 6.6541435 | K11: 1064327 | L11: =(K11/$B11)*100 -> 32.641759 | M11: 229947 | N11: =(M11/$B11)*100 -> 7.0522261 | O11: 1630375 | P11: =(O11/$B11)*100 -> 50.00184 | Q11: 3165356 | R11: =(Q11/$B11)*100 -> 97.078049 | S11: 2785650 | T11: =(S11/$B11)*100 -> 85.432876 | U11: 200717 | V11: =(U11/$B11)*100 -> 6.1557736 | W11: 221653 | X11: =(W11/$B11)*100 -> 6.7978581 | Y11: 311233 | Z11: =(Y11/$B11)*100 -> 9.5451799 | AA11: 421025 | AB11: =(AA11/$B11)*100 -> 12.912382 | AC11: 112011 | AD11: =(AC11/$B11)*100 -> 3.4352564 | AE11: 78754 | AF11: =(AE11/$B11)*100 -> 2.4153001 | AG11: 175881 | AH11: =(AG11/$B11)*100 -> 5.3940803 | AI11: 418526 | AJ11: =(AI11/$B11)*100 -> 12.83574 | AK11: 1850572 | AL11: =(AK11/$B11)*100 -> 56.755044 | AM11: 1194688 | AN11: =(AM11/$B11)*100 -> 36.63979 | AO11: 1083626 | AP11: =(AO11/$B11)*100 -> 33.233639 | AQ11: 290483 | AR11: =(AQ11/$B11)*100 -> 8.9087998 | AS11: 166444 | AT11: =(AS11/$B11)*100 -> 5.1046577
A12: Region II - Cagayan Valley | B12: 2290016 | C12: 916041 | D12: =(C12/$B12)*100 -> 40.001511 | E12: 567363 | F12: =(E12/$B12)*100 -> 24.775504 | G12: 655604 | H12: =(G12/$B12)*100 -> 28.628796 | I12: 108301 | J12: =(I12/$B12)*100 -> 4.7292683 | K12: 567877 | L12: =(K12/$B12)*100 -> 24.797949 | M12: 120854 | N12: =(M12/$B12)*100 -> 5.2774304 | O12: 637827 | P12: =(O12/$B12)*100 -> 27.852513 | Q12: 2151585 | R12: =(Q12/$B12)*100 -> 93.95502 | S12: 2001244 | T12: =(S12/$B12)*100 -> 87.389957 | U12: 61492 | V12: =(U12/$B12)*100 -> 2.6852214 | W12: 168489 | X12: =(W12/$B12)*100 -> 7.3575468 | Y12: 146235 | Z12: =(Y12/$B12)*100 -> 6.3857632 | AA12: 325146 | AB12: =(AA12/$B12)*100 -> 14.198416 | AC12: 102477 | AD12: =(AC12/$B12)*100 -> 4.4749469 | AE12: 81860 | AF12: =(AE12/$B12)*100 -> 3.5746475 | AG12: 95105 | AH12: =(AG12/$B12)*100 -> 4.1530278 | AI12: 463058 | AJ12: =(AI12/$B12)*100 -> 20.220732 | AK12: 1370865 | AL12: =(AK12/$B12)*100 -> 59.862682 | AM12: 736774 | AN12: =(AM12/$B12)*100 -> 32.173312 | AO12: 727172 | AP12: =(AO12/$B12)*100 -> 31.754014 | AQ12: 343301 | AR12: =(AQ12/$B12)*100 -> 14.991205 | AS12: 191398 | AT12: =(AS12/$B12)*100 -> 8.3579329
A13: Region III - Central Luzon | B13: 7926396 | C13: 3208000 | D13: =(C13/$B13)*100 -> 40.472366 | E13: 1248075 | F13: =(E13/$B13)*100 -> 15.745807 | G13: 1353001 | H13: =(G13/$B13)*100 -> 17.069561 | I13: 492426 | J13: =(I13/$B13)*100 -> 6.2124829 | K13: 2405742 | L13: =(K13/$B13)*100 -> 30.35102 | M13: 598238 | N13: =(M13/$B13)*100 -> 7.547415 | O13: 3409092 | P13: =(O13/$B13)*100 -> 43.009358 | Q13: 7353767 | R13: =(Q13/$B13)*100 -> 92.77567 | S13: 7006467 | T13: =(S13/$B13)*100 -> 88.394107 | U13: 369702 | V13: =(U13/$B13)*100 -> 4.6641879 | W13: 558466 | X13: =(W13/$B13)*100 -> 7.0456485 | Y13: 706561 | Z13: =(Y13/$B13)*100 -> 8.914026 | AA13: 808822 | AB13: =(AA13/$B13)*100 -> 10.204158 | AC13: 473234 | AD13: =(AC13/$B13)*100 -> 5.9703553 | AE13: 293262 | AF13: =(AE13/$B13)*100 -> 3.6998151 | AG13: 946138 | AH13: =(AG13/$B13)*100 -> 11.936547 | AI13: 2001021 | AJ13: =(AI13/$B13)*100 -> 25.245029 | AK13: 4804780 | AL13: =(AK13/$B13)*100 -> 60.617461 | AM13: 2830556 | AN13: =(AM13/$B13)*100 -> 35.710504 | AO13: 2320631 | AP13: =(AO13/$B13)*100 -> 29.277253 | AQ13: 1160203 | AR13: =(AQ13/$B13)*100 -> 14.637207 | AS13: 602571 | AT13: =(AS13/$B13)*100 -> 7.6020804
A14: Region IV-A - CALABARZON | B14: 9979157 | C14: 4094887 | D14: =(C14/$B14)*100 -> 41.034398 | E14: 2066770 | F14: =(E14/$B14)*100 -> 20.710868 | G14: 1937095 | H14: =(G14/$B14)*100 -> 19.411409 | I14: 916388 | J14: =(I14/$B14)*100 -> 9.1830202 | K14: 2625838 | L14: =(K14/$B14)*100 -> 26.313225 | M14: 1092175 | N14: =(M14/$B14)*100 -> 10.944562 | O14: 4737034 | P14: =(O14/$B14)*100 -> 47.46928 | Q14: 9696983 | R14: =(Q14/$B14)*100 -> 97.172366 | S14: 8786018 | T14: =(S14/$B14)*100 -> 88.043689 | U14: 535718 | V14: =(U14/$B14)*100 -> 5.3683693 | W14: 1172719 | X14: =(W14/$B14)*100 -> 11.751684 | Y14: 953316 | Z14: =(Y14/$B14)*100 -> 9.5530715 | AA14: 1157342 | AB14: =(AA14/$B14)*100 -> 11.597593 | AC14: 819686 | AD14: =(AC14/$B14)*100 -> 8.2139804 | AE14: 609856 | AF14: =(AE14/$B14)*100 -> 6.1112978 | AG14: 843787 | AH14: =(AG14/$B14)*100 -> 8.4554938 | AI14: 2094178 | AJ14: =(AI14/$B14)*100 -> 20.98552 | AK14: 7209792 | AL14: =(AK14/$B14)*100 -> 72.248508 | AM14: 3538638 | AN14: =(AM14/$B14)*100 -> 35.46029 | AO14: 3671611 | AP14: =(AO14/$B14)*100 -> 36.792797 | AQ14: 1751389 | AR14: =(AQ14/$B14)*100 -> 17.55047 | AS14: 1051771 | AT14: =(AS14/$B14)*100 -> 10.539678
A15: MIMAROPA Region | B15: 1614249 | C15: 580738 | D15: =(C15/$B15)*100 -> 35.975739 | E15: 355764 | F15: =(E15/$B15)*100 -> 22.038979 | G15: 288541 | H15: =(G15/$B15)*100 -> 17.874628 | I15: 121415 | J15: =(I15/$B15)*100 -> 7.5214542 | K15: 632666 | L15: =(K15/$B15)*100 -> 39.19259 | M15: 101977 | N15: =(M15/$B15)*100 -> 6.317303 | O15: 598528 | P15: =(O15/$B15)*100 -> 37.077799 | Q15: 1537362 | R15: =(Q15/$B15)*100 -> 95.23698 | S15: 1487543 | T15: =(S15/$B15)*100 -> 92.150777 | U15: 57826 | V15: =(U15/$B15)*100 -> 3.5822231 | W15: 105066 | X15: =(W15/$B15)*100 -> 6.5086613 | Y15: 95414 | Z15: =(Y15/$B15)*100 -> 5.9107362 | AA15: 146211 | AB15: =(AA15/$B15)*100 -> 9.0575246 | AC15: 82223 | AD15: =(AC15/$B15)*100 -> 5.093576 | AE15: 49589 | AF15: =(AE15/$B15)*100 -> 3.0719548 | AG15: 26249 | AH15: =(AG15/$B15)*100 -> 1.6260812 | AI15: 104105 | AJ15: =(AI15/$B15)*100 -> 6.449129 | AK15: 868330 | AL15: =(AK15/$B15)*100 -> 53.791577 | AM15: 518930 | AN15: =(AM15/$B15)*100 -> 32.146837 | AO15: 493244 | AP15: =(AO15/$B15)*100 -> 30.555633 | AQ15: 147769 | AR15: =(AQ15/$B15)*100 -> 9.1540401 | AS15: 105664 | AT15: =(AS15/$B15)*100 -> 6.5457064
A16: Region V - Bicol Region | B16: 3094742 | C16: 1170767 | D16: =(C16/$B16)*100 -> 37.830843 | E16: 703174 | F16: =(E16/$B16)*100 -> 22.721571 | G16: 701323 | H16: =(G16/$B16)*100 -> 22.66176 | I16: 198115 | J16: =(I16/$B16)*100 -> 6.4016645 | K16: 962474 | L16: =(K16/$B16)*100 -> 31.100299 | M16: 270402 | N16: =(M16/$B16)*100 -> 8.737465 | O16: 809402 | P16: =(O16/$B16)*100 -> 26.154103 | Q16: 2941618 | R16: =(Q16/$B16)*100 -> 95.052124 | S16: 2597035 | T16: =(S16/$B16)*100 -> 83.917658 | U16: 123062 | V16: =(U16/$B16)*100 -> 3.9764866 | W16: 285851 | X16: =(W16/$B16)*100 -> 9.2366666 | Y16: 238979 | Z16: =(Y16/$B16)*100 -> 7.7220977 | AA16: 454764 | AB16: =(AA16/$B16)*100 -> 14.694731 | AC16: 138925 | AD16: =(AC16/$B16)*100 -> 4.4890656 | AE16: 93094 | AF16: =(AE16/$B16)*100 -> 3.0081344 | AG16: 153648 | AH16: =(AG16/$B16)*100 -> 4.9648081 | AI16: 313163 | AJ16: =(AI16/$B16)*100 -> 10.119196 | AK16: 1956463 | AL16: =(AK16/$B16)*100 -> 63.218937 | AM16: 972212 | AN16: =(AM16/$B16)*100 -> 31.414961 | AO16: 777832 | AP16: =(AO16/$B16)*100 -> 25.133985 | AQ16: 456530 | AR16: =(AQ16/$B16)*100 -> 14.751795 | AS16: 300423 | AT16: =(AS16/$B16)*100 -> 9.7075297
A17: Region VI - Western Visayas | B17: 4053706 | C17: 1804537 | D17: =(C17/$B17)*100 -> 44.515734 | E17: 783956 | F17: =(E17/$B17)*100 -> 19.339242 | G17: 848469 | H17: =(G17/$B17)*100 -> 20.930699 | I17: 356055 | J17: =(I17/$B17)*100 -> 8.7834441 | K17: 767352 | L17: =(K17/$B17)*100 -> 18.929641 | M17: 313555 | N17: =(M17/$B17)*100 -> 7.7350207 | O17: 1752868 | P17: =(O17/$B17)*100 -> 43.241123 | Q17: 3682647 | R17: =(Q17/$B17)*100 -> 90.846425 | S17: 3704784 | T17: =(S17/$B17)*100 -> 91.392518 | U17: 222874 | V17: =(U17/$B17)*100 -> 5.4980307 | W17: 331386 | X17: =(W17/$B17)*100 -> 8.1748898 | Y17: 369086 | Z17: =(Y17/$B17)*100 -> 9.104903 | AA17: 448352 | AB17: =(AA17/$B17)*100 -> 11.060299 | AC17: 287493 | AD17: =(AC17/$B17)*100 -> 7.0921029 | AE17: 200191 | AF17: =(AE17/$B17)*100 -> 4.9384687 | AG17: 355669 | AH17: =(AG17/$B17)*100 -> 8.7739219 | AI17: 559176 | AJ17: =(AI17/$B17)*100 -> 13.794192 | AK17: 2595104 | AL17: =(AK17/$B17)*100 -> 64.018062 | AM17: 1183723 | AN17: =(AM17/$B17)*100 -> 29.201008 | AO17: 1326304 | AP17: =(AO17/$B17)*100 -> 32.718308 | AQ17: 650711 | AR17: =(AQ17/$B17)*100 -> 16.052249 | AS17: 216293 | AT17: =(AS17/$B17)*100 -> 5.3356854
A18: Region VII - Central Visayas | B18: 4522717 | C18: 1768056 | D18: =(C18/$B18)*100 -> 39.092784 | E18: 802714 | F18: =(E18/$B18)*100 -> 17.748491 | G18: 951638 | H18: =(G18/$B18)*100 -> 21.04129 | I18: 519429 | J18: =(I18/$B18)*100 -> 11.484888 | K18: 1397031 | L18: =(K18/$B18)*100 -> 30.889198 | M18: 421087 | N18: =(M18/$B18)*100 -> 9.3104875 | O18: 1950223 | P18: =(O18/$B18)*100 -> 43.120606 | Q18: 4318560 | R18: =(Q18/$B18)*100 -> 95.485966 | S18: 3926422 | T18: =(S18/$B18)*100 -> 86.815558 | U18: 274107 | V18: =(U18/$B18)*100 -> 6.0606711 | W18: 441765 | X18: =(W18/$B18)*100 -> 9.7676905 | Y18: 311284 | Z18: =(Y18/$B18)*100 -> 6.8826769 | AA18: 756748 | AB18: =(AA18/$B18)*100 -> 16.732155 | AC18: 336395 | AD18: =(AC18/$B18)*100 -> 7.4378963 | AE18: 234367 | AF18: =(AE18/$B18)*100 -> 5.1819957 | AG18: 666167 | AH18: =(AG18/$B18)*100 -> 14.729354 | AI18: 1259780 | AJ18: =(AI18/$B18)*100 -> 27.854495 | AK18: 2924632 | AL18: =(AK18/$B18)*100 -> 64.665377 | AM18: 1671885 | AN18: =(AM18/$B18)*100 -> 36.966385 | AO18: 1740696 | AP18: =(AO18/$B18)*100 -> 38.487838 | AQ18: 941937 | AR18: =(AQ18/$B18)*100 -> 20.826795 | AS18: 436723 | AT18: =(AS18/$B18)*100 -> 9.6562089
A19: Region VIII - Eastern Visayas | B19: 2570726 | C19: 671360 | D19: =(C19/$B19)*100 -> 26.11558 | E19: 481197 | F19: =(E19/$B19)*100 -> 18.718331 | G19: 442832 | H19: =(G19/$B19)*100 -> 17.225951 | I19: 213785 | J19: =(I19/$B19)*100 -> 8.3161333 | K19: 636508 | L19: =(K19/$B19)*100 -> 24.759854 | M19: 192264 | N19: =(M19/$B19)*100 -> 7.4789768 | O19: 816886 | P19: =(O19/$B19)*100 -> 31.776471 | Q19: 2324601 | R19: =(Q19/$B19)*100 -> 90.425856 | S19: 2252737 | T19: =(S19/$B19)*100 -> 87.630381 | U19: 102581 | V19: =(U19/$B19)*100 -> 3.9903514 | W19: 211232 | X19: =(W19/$B19)*100 -> 8.2168228 | Y19: 180816 | Z19: =(Y19/$B19)*100 -> 7.0336551 | AA19: 286394 | AB19: =(AA19/$B19)*100 -> 11.140588 | AC19: 131877 | AD19: =(AC19/$B19)*100 -> 5.1299516 | AE19: 90107 | AF19: =(AE19/$B19)*100 -> 3.5051188 | AG19: 113770 | AH19: =(AG19/$B19)*100 -> 4.4255981 | AI19: 459240 | AJ19: =(AI19/$B19)*100 -> 17.864214 | AK19: 1653699 | AL19: =(AK19/$B19)*100 -> 64.328093 | AM19: 687613 | AN19: =(AM19/$B19)*100 -> 26.747814 | AO19: 688193 | AP19: =(AO19/$B19)*100 -> 26.770375 | AQ19: 283694 | AR19: =(AQ19/$B19)*100 -> 11.03556 | AS19: 194830 | AT19: =(AS19/$B19)*100 -> 7.5787929
... A25: Bangsamoro Autonomous Region in Muslim Mindanao | B25: 1496986 | C25: 409404 | D25: =(C25/$B25)*100 -> 27.348552 | E25: 144501 | F25: =(E25/$B25)*100 -> 9.6527957 | G25: 154839 | H25: =(G25/$B25)*100 -> 10.343383 | I25: 24522 | J25: =(I25/$B25)*100 -> 1.6380915 | K25: 316918 | L25: =(K25/$B25)*100 -> 21.170405 | M25: 57070 | N25: =(M25/$B25)*100 -> 3.8123269 | O25: 358525 | P25: =(O25/$B25)*100 -> 23.94979 | Q25: 1354179 | R25: =(Q25/$B25)*100 -> 90.460365 | S25: 1393082 | T25: =(S25/$B25)*100 -> 93.05912 | U25: 27726 | V25: =(U25/$B25)*100 -> 1.8521215 | W25: 32949 | X25: =(W25/$B25)*100 -> 2.2010226 | Y25: 48684 | Z25: =(Y25/$B25)*100 -> 3.2521346 | AA25: 94225 | AB25: =(AA25/$B25)*100 -> 6.294314 | AC25: 45551 | AD25: =(AC25/$B25)*100 -> 3.0428474 | AE25: 9712 | AF25: =(AE25/$B25)*100 -> 0.64877026 | AG25: 47046 | AH25: =(AG25/$B25)*100 -> 3.1427148 | AI25: 114966 | AJ25: =(AI25/$B25)*100 -> 7.6798313 | AK25: 838462 | AL25: =(AK25/$B25)*100 -> 56.010009 | AM25: 388821 | AN25: =(AM25/$B25)*100 -> 25.97359 | AO25: 587897 | AP25: =(AO25/$B25)*100 -> 39.272044 | AQ25: 155530 | AR25: =(AQ25/$B25)*100 -> 10.389543 | AS25: 45900 | AT25: =(AS25/$B25)*100 -> 3.0661609
A28: Notes:
A29: Details may not add up to totals due to rounding.
A30: p Estimates are preliminary and may change
A31: Source of data: Philippine Statistics Authority, 2024 National Information and Communications Technology Household Survey.

Sheet C36_a TO C36_m
A1: BACK TO LIST
A2: Table #. Number and Proportion of Households By Reason for Not Having an Internet Connection and Region, Philippines: 2019r and 2024p
A4: Region | B4: 2019
B5: Households Which Do Not Have an Internet Connection at Home | C5: Reasons for Not Having an Internet Connection
C6: Internet Service Not Available in the Area | E6: Privacy or Security Concerns | G6: Exposure to Harmful Content | I6: Not Allowed to Use the Internet | K6: Have Access to the Internet Elsewhere | M6: High Cost of Internet Subscription | O6: High Cost of Equipment | Q6: Do not Need the Internet | S6: Members have Individual/Personal Connection | U6: Others
C7: Number | D7: Proportion | E7: Number | F7: Proportion | G7: Number | H7: Proportion | I7: Number | J7: Proportion | K7: Number | L7: Proportion | M7: Number | N7: Proportion | O7: Number | P7: Proportion | Q7: Number | R7: Proportion | S7: Number | T7: Proportion | U7: Number | V7: Proportion
A9: PHILIPPINES | B9: 19237079 | C9: 3729704 | D9: =C9/$B9*100 -> 19.388099 | E9: 219186 | F9: =E9/$B9*100 -> 1.1393934 | G9: 73222 | H9: =G9/$B9*100 -> 0.38062951 | I9: 97182 | J9: =I9/$B9*100 -> 0.50518065 | K9: 882825 | L9: =K9/$B9*100 -> 4.5891843 | M9: 10094487 | N9: =M9/$B9*100 -> 52.474115 | O9: 6509587 | P9: =O9/$B9*100 -> 33.83875 | Q9: 1720534 | R9: =Q9/$B9*100 -> 8.9438423 | S9: 1698211 | T9: =S9/$B9*100 -> 8.8278007 | U9: 396970 | V9: =U9/$B9*100 -> 2.0635669
A10: National Capital Region | B10: 2008874 | C10: 107769 | D10: =C10/$B10*100 -> 5.3646471 | E10: 38176 | F10: =E10/$B10*100 -> 1.9003681 | G10: 7103 | H10: =G10/$B10*100 -> 0.35358116 | I10: 18854 | J10: =I10/$B10*100 -> 0.93853572 | K10: 157519 | L10: =K10/$B10*100 -> 7.8411588 | M10: 1187583 | N10: =M10/$B10*100 -> 59.116849 | O10: 625405 | P10: =O10/$B10*100 -> 31.132117 | Q10: 215969 | R10: =Q10/$B10*100 -> 10.750749 | S10: 351442 | T10: =S10/$B10*100 -> 17.494477 | U10: 40586 | V10: =U10/$B10*100 -> 2.0203358
A11: Cordillera Administrative Region | B11: 272693 | C11: 81520 | D11: =C11/$B11*100 -> 29.894423 | E11: 94 | F11: =E11/$B11*100 -> 0.034470999 | G11: 264 | H11: =G11/$B11*100 -> 0.096812166 | I11: 141 | J11: =I11/$B11*100 -> 0.051706498 | K11: 9281 | L11: =K11/$B11*100 -> 3.403461 | M11: 70553 | N11: =M11/$B11*100 -> 25.872685 | O11: 60661 | P11: =O11/$B11*100 -> 22.245162 | Q11: 16253 | R11: =Q11/$B11*100 -> 5.9601823 | S11: 50485 | T11: =S11/$B11*100 -> 18.513493 | U11: 3171 | V11: =U11/$B11*100 -> 1.1628461
A12: Region I - Ilocos Region | B12: 1025390 | C12: 133482 | D12: =C12/$B12*100 -> 13.017681 | E12: 3280 | F12: =E12/$B12*100 -> 0.31987829 | G12: 2067 | H12: =G12/$B12*100 -> 0.20158184 | I12: 4964 | J12: =I12/$B12*100 -> 0.48410849 | K12: 47837 | L12: =K12/$B12*100 -> 4.6652493 | M12: 582889 | N12: =M12/$B12*100 -> 56.84559 | O12: 255591 | P12: =O12/$B12*100 -> 24.926223 | Q12: 57512 | R12: =Q12/$B12*100 -> 5.6087928 | S12: 389223 | T12: =S12/$B12*100 -> 37.958533 | U12: 15532 | V12: =U12/$B12*100 -> 1.5147407
A13: Region II - Cagayan Valley | B13: 701564 | C13: 121351 | D13: =C13/$B13*100 -> 17.29721 | E13: 7360 | F13: =E13/$B13*100 -> 1.0490846 | G13: 6120 | H13: =G13/$B13*100 -> 0.87233666 | I13: 3738 | J13: =I13/$B13*100 -> 0.53280955 | K13: 12503 | L13: =K13/$B13*100 -> 1.782161 | M13: 166159 | N13: =M13/$B13*100 -> 23.684083 | O13: 265684 | P13: =O13/$B13*100 -> 37.870244 | Q13: 11227 | R13: =Q13/$B13*100 -> 1.6002817 | S13: 53462 | T13: =S13/$B13*100 -> 7.6204024 | U13: 5959 | V13: =U13/$B13*100 -> 0.84938794
A14: Region III - Central Luzon | B14: 2160105 | C14: 274594 | D14: =C14/$B14*100 -> 12.712067 | E14: 743 | F14: =E14/$B14*100 -> 0.034396476 | G14: 4281 | H14: =G14/$B14*100 -> 0.19818481 | I14: 3548 | J14: =I14/$B14*100 -> 0.16425127 | K14: 202823 | L14: =K14/$B14*100 -> 9.3894973 | M14: 1414276 | N14: =M14/$B14*100 -> 65.472558 | O14: 1149016 | P14: =O14/$B14*100 -> 53.192599 | Q14: 267431 | R14: =Q14/$B14*100 -> 12.380463 | S14: 170687 | T14: =S14/$B14*100 -> 7.9017918 | U14: 845 | V14: =U14/$B14*100 -> 0.039118469
A15: Region IV-A - CALABARZON | B15: 2642039 | C15: 486881 | D15: =C15/$B15*100 -> 18.428229 | E15: 123432 | F15: =E15/$B15*100 -> 4.6718463 | G15: 10400 | H15: =G15/$B15*100 -> 0.39363537 | I15: 10812 | J15: =I15/$B15*100 -> 0.40922939 | K15: 97027 | L15: =K15/$B15*100 -> 3.6724288 | M15: 1837437 | N15: =M15/$B15*100 -> 69.546172 | O15: 643307 | P15: =O15/$B15*100 -> 24.348884 | Q15: 315859 | R15: =Q15/$B15*100 -> 11.955123 | S15: 75817 | T15: =S15/$B15*100 -> 2.8696397 | U15: 206255 | V15: =U15/$B15*100 -> 7.8066599
A16: MIMAROPA Region | B16: 634776 | C16: 99527 | D16: =C16/$B16*100 -> 15.679074 | E16: 632 | F16: =E16/$B16*100 -> 0.09956268 | G16: 524 | H16: =G16/$B16*100 -> 0.082548805 | I16: 881 | J16: =I16/$B16*100 -> 0.13878912 | K16: 16090 | L16: =K16/$B16*100 -> 2.5347524 | M16: 308688 | N16: =M16/$B16*100 -> 48.629438 | O16: 252253 | P16: =O16/$B16*100 -> 39.7389 | Q16: 82895 | R16: =Q16/$B16*100 -> 13.058937 | S16: 111954 | T16: =S16/$B16*100 -> 17.636773 | U16: 57489 | V16: =U16/$B16*100 -> 9.0565806
A17: Region V - Bicol Region | B17: 955923 | C17: 379426 | D17: =C17/$B17*100 -> 39.692109 | E17: 6187 | F17: =E17/$B17*100 -> 0.64722786 | G17: 6025 | H17: =G17/$B17*100 -> 0.63028089 | I17: 9961 | J17: =I17/$B17*100 -> 1.0420295 | K17: 14284 | L17: =K17/$B17*100 -> 1.4942626 | M17: 242622 | N17: =M17/$B17*100 -> 25.380915 | O17: 198008 | P17: =O17/$B17*100 -> 20.713802 | Q17: 175350 | R17: =Q17/$B17*100 -> 18.343528 | S17: 45860 | T17: =S17/$B17*100 -> 4.7974575 | U17: 7830 | V17: =U17/$B17*100 -> 0.81910363
A18: Region VI - Western Visayas | B18: 1528295 | C18: 450590 | D18: =C18/$B18*100 -> 29.483182 | E18: 2704 | F18: =E18/$B18*100 -> 0.17692919 | G18: 742 | H18: =G18/$B18*100 -> 0.048550836 | I18: 1288 | J18: =I18/$B18*100 -> 0.084276923 | K18: 44711 | L18: =K18/$B18*100 -> 2.9255478 | M18: 894264 | N18: =M18/$B18*100 -> 58.513834 | O18: 251236 | P18: =O18/$B18*100 -> 16.438973 | Q18: 34648 | R18: =Q18/$B18*100 -> 2.2671016 | S18: 116641 | T18: =S18/$B18*100 -> 7.6320998 | U18: 3357 | V18: =U18/$B18*100 -> 0.21965655
A19: Region VII - Central Visayas | B19: 1633431 | C19: 78022 | D19: =C19/$B19*100 -> 4.7765715 | E19: 816 | F19: =E19/$B19*100 -> 0.049956197 | G19: 1811 | H19: =G19/$B19*100 -> 0.11087092 | I19: 5341 | J19: =I19/$B19*100 -> 0.32698045 | K19: 115781 | L19: =K19/$B19*100 -> 7.0882088 | M19: 868480 | N19: =M19/$B19*100 -> 53.169066 | O19: 639513 | P19: =O19/$B19*100 -> 39.151516 | Q19: 95200 | R19: =Q19/$B19*100 -> 5.8282229 | S19: 112542 | T19: =S19/$B19*100 -> 6.8899145 | U19: 13163 | V19: =U19/$B19*100 -> 0.80584977
A20: Region VIII - Eastern Visayas | B20: 869184 | C20: 136948 | D20: =C20/$B20*100 -> 15.755927 | E20: 1777 | F20: =E20/$B20*100 -> 0.20444463 | G20: 538 | H20: =G20/$B20*100 -> 0.061897136 | I20: 589 | J20: =I20/$B20*100 -> 0.067764708 | K20: 15059 | L20: =K20/$B20*100 -> 1.7325445 | M20: 433435 | N20: =M20/$B20*100 -> 49.866887 | O20: 448368 | P20: =O20/$B20*100 -> 51.584935 | Q20: 15029 | R20: =Q20/$B20*100 -> 1.729093 | S20: 53126 | T20: =S20/$B20*100 -> 6.1121696 | U20: 7355 | V20: =U20/$B20*100 -> 0.84619597
... A26: Bangsamoro Autonomous Region in Muslim Mindanao | B26: 497769 | C26: 264319 | D26: =C26/$B26*100 -> 53.100735 | E26: 5420 | F26: =E26/$B26*100 -> 1.0888585 | G26: 23580 | H26: =G26/$B26*100 -> 4.7371371 | I26: 23580 | J26: =I26/$B26*100 -> 4.7371371 | K26: 492 | L26: =K26/$B26*100 -> 0.098841029 | M26: 27473 | N26: =M26/$B26*100 -> 5.5192268 | O26: 171869 | P26: =O26/$B26*100 -> 34.527863 | Q26: 8126 | R26: =Q26/$B26*100 -> 1.6324841 | S26: 1814 | T26: =S26/$B26*100 -> 0.36442607 | U26: 494 | V26: =U26/$B26*100 -> 0.099242821
A30: Region | B30: 2024
B31: Households Which Do Not Have an Internet Connection at Home | C31: Reasons for Not Having an Internet Connection
C32: Internet Service Not Available in the Area | E32: Privacy or Security Concerns | G32: Exposure to Harmful Content | I32: Not Allowed to Use the Internet | K32: Have Access to the Internet Elsewhere | M32: High Cost of Internet Subscription | O32: High Cost of Equipment | Q32: Poor Quality and Speed | S32: Do not Know How to Use | U32: Do not Know What Internet is | W32: Do not Need the Internet | Y32: Members have Individual/Personal Connection | AA32: Others
C33: Number | D33: Proportion | E33: Number | F33: Proportion | G33: Number | H33: Proportion | I33: Number | J33: Proportion | K33: Number | L33: Proportion | M33: Number | N33: Proportion | O33: Number | P33: Proportion | Q33: Number | R33: Proportion | S33: Number | T33: Proportion | U33: Number | V33: Proportion | W33: Number | X33: Proportion | Y33: Number | Z33: Proportion | AA33: Number | AB33: Proportion
A35: PHILIPPINES | B35: 14238011 | C35: 1590818 | D35: =(C35/$B35)*100 -> 11.173035 | E35: 339642 | F35: =(E35/$B35)*100 -> 2.3854596 | G35: 244453 | H35: =(G35/$B35)*100 -> 1.7169041 | I35: 290144 | J35: =(I35/$B35)*100 -> 2.0378127 | K35: 2912581 | L35: =(K35/$B35)*100 -> 20.456376 | M35: 8299865 | N35: =(M35/$B35)*100 -> 58.293711 | O35: 5338451 | P35: =(O35/$B35)*100 -> 37.494359 | Q35: 1333917 | R35: =(Q35/$B35)*100 -> 9.3687033 | S35: 1688615 | T35: =(S35/$B35)*100 -> 11.859908 | U35: 797373 | V35: =(U35/$B35)*100 -> 5.6003117 | W35: 1119335 | X35: =(W35/$B35)*100 -> 7.8615967 | Y35: 4387963 | Z35: =(Y35/$B35)*100 -> 30.818652 | AA35: 328951 | AB35: =(AA35/$B35)*100 -> 2.3103719
A36: National Capital Region | B36: 1149454 | C36: 14445 | D36: =(C36/$B36)*100 -> 1.2566836 | E36: 32323 | F36: =(E36/$B36)*100 -> 2.8120308 | G36: 14030 | H36: =(G36/$B36)*100 -> 1.2205795 | I36: 20602 | J36: =(I36/$B36)*100 -> 1.7923292 | K36: 172397 | L36: =(K36/$B36)*100 -> 14.998164 | M36: 817652 | N36: =(M36/$B36)*100 -> 71.133947 | O36: 302201 | P36: =(O36/$B36)*100 -> 26.29083 | Q36: 47997 | R36: =(Q36/$B36)*100 -> 4.1756347 | S36: 44867 | T36: =(S36/$B36)*100 -> 3.9033315 | U36: 21226 | V36: =(U36/$B36)*100 -> 1.8466159 | W36: 100527 | X36: =(W36/$B36)*100 -> 8.7456305 | Y36: 471699 | Z36: =(Y36/$B36)*100 -> 41.036788 | AA36: 5088 | AB36: =(AA36/$B36)*100 -> 0.44264494
A37: Cordillera Administrative Region | B37: 219137 | C37: 27454 | D37: =(C37/$B37)*100 -> 12.528236 | E37: 5544 | F37: =(E37/$B37)*100 -> 2.5299242 | G37: 2929 | H37: =(G37/$B37)*100 -> 1.3366068 | I37: 3182 | J37: =(I37/$B37)*100 -> 1.4520597 | K37: 35713 | L37: =(K37/$B37)*100 -> 16.297111 | M37: 88324 | N37: =(M37/$B37)*100 -> 40.30538 | O37: 69218 | P37: =(O37/$B37)*100 -> 31.586633 | Q37: 22081 | R37: =(Q37/$B37)*100 -> 10.076345 | S37: 44808 | T37: =(S37/$B37)*100 -> 20.447483 | U37: 23287 | V37: =(U37/$B37)*100 -> 10.626686 | W37: 16073 | X37: =(W37/$B37)*100 -> 7.334681 | Y37: 109979 | Z37: =(Y37/$B37)*100 -> 50.187326 | AA37: 219 | AB37: =(AA37/$B37)*100 -> 0.099937482
A38: Region I - Ilocos Region | B38: 550450 | C38: 11148 | D38: =(C38/$B38)*100 -> 2.0252521 | E38: 881 | F38: =(E38/$B38)*100 -> 0.16005087 | G38: 677 | H38: =(G38/$B38)*100 -> 0.12299028 | I38: 7078 | J38: =(I38/$B38)*100 -> 1.285857 | K38: 50698 | L38: =(K38/$B38)*100 -> 9.2102825 | M38: 290007 | N38: =(M38/$B38)*100 -> 52.685439 | O38: 164485 | P38: =(O38/$B38)*100 -> 29.881915 | Q38: 27550 | R38: =(Q38/$B38)*100 -> 5.0049959 | S38: 100884 | T38: =(S38/$B38)*100 -> 18.32755 | U38: 63523 | V38: =(U38/$B38)*100 -> 11.540194 | W38: 70540 | X38: =(W38/$B38)*100 -> 12.81497 | Y38: 282377 | Z38: =(Y38/$B38)*100 -> 51.299301 | AA38: 6383 | AB38: =(AA38/$B38)*100 -> 1.1595967
A39: Region II - Cagayan Valley | B39: 413508 | C39: 66636 | D39: =(C39/$B39)*100 -> 16.114803 | E39: 9508 | F39: =(E39/$B39)*100 -> 2.2993509 | G39: 5627 | H39: =(G39/$B39)*100 -> 1.3607959 | I39: 24144 | J39: =(I39/$B39)*100 -> 5.8388229 | K39: 109582 | L39: =(K39/$B39)*100 -> 26.500576 | M39: 224629 | N39: =(M39/$B39)*100 -> 54.32277 | O39: 147741 | P39: =(O39/$B39)*100 -> 35.728692 | Q39: 44643 | R39: =(Q39/$B39)*100 -> 10.796164 | S39: 86891 | T39: =(S39/$B39)*100 -> 21.013136 | U39: 45675 | V39: =(U39/$B39)*100 -> 11.045736 | W39: 25385 | X39: =(W39/$B39)*100 -> 6.1389381 | Y39: 120510 | Z39: =(Y39/$B39)*100 -> 29.14333 | AA39: 2245 | AB39: =(AA39/$B39)*100 -> 0.54291574
A40: Region III - Central Luzon | B40: 1222146 | C40: 103419 | D40: =(C40/$B40)*100 -> 8.4620823 | E40: 29486 | F40: =(E40/$B40)*100 -> 2.4126414 | G40: 14780 | H40: =(G40/$B40)*100 -> 1.2093481 | I40: 32165 | J40: =(I40/$B40)*100 -> 2.631846 | K40: 186895 | L40: =(K40/$B40)*100 -> 15.292363 | M40: 696845 | N40: =(M40/$B40)*100 -> 57.018147 | O40: 427458 | P40: =(O40/$B40)*100 -> 34.976018 | Q40: 59585 | R40: =(Q40/$B40)*100 -> 4.8754404 | S40: 117340 | T40: =(S40/$B40)*100 -> 9.6011442 | U40: 59215 | V40: =(U40/$B40)*100 -> 4.8451658 | W40: 93793 | X40: =(W40/$B40)*100 -> 7.6744513 | Y40: 413158 | Z40: =(Y40/$B40)*100 -> 33.805945 | AA40: 91938 | AB40: =(AA40/$B40)*100 -> 7.5226691
A41: Region IV-A - CALABARZON | B41: 2045833 | C41: 300864 | D41: =(C41/$B41)*100 -> 14.706186 | E41: 17966 | F41: =(E41/$B41)*100 -> 0.8781753 | G41: 15803 | H41: =(G41/$B41)*100 -> 0.77244819 | I41: 34980 | J41: =(I41/$B41)*100 -> 1.709817 | K41: 334020 | L41: =(K41/$B41)*100 -> 16.326846 | M41: 1395628 | N41: =(M41/$B41)*100 -> 68.21808 | O41: 460650 | P41: =(O41/$B41)*100 -> 22.516501 | Q41: 80074 | R41: =(Q41/$B41)*100 -> 3.9140047 | S41: 143966 | T41: =(S41/$B41)*100 -> 7.0370358 | U41: 28023 | V41: =(U41/$B41)*100 -> 1.3697599 | W41: 132743 | X41: =(W41/$B41)*100 -> 6.4884573 | Y41: 757258 | Z41: =(Y41/$B41)*100 -> 37.014654 | AA41: 10062 | AB41: =(AA41/$B41)*100 -> 0.491829
A42: MIMAROPA Region | B42: 572477 | C42: 109980 | D42: =(C42/$B42)*100 -> 19.211252 | E42: 3978 | F42: =(E42/$B42)*100 -> 0.69487508 | G42: 2154 | H42: =(G42/$B42)*100 -> 0.37625966 | I42: 6876 | J42: =(I42/$B42)*100 -> 1.2010963 | K42: 109816 | L42: =(K42/$B42)*100 -> 19.182605 | M42: 163936 | N42: =(M42/$B42)*100 -> 28.63626 | O42: 119310 | P42: =(O42/$B42)*100 -> 20.841012 | Q42: 65767 | R42: =(Q42/$B42)*100 -> 11.488147 | S42: 77087 | T42: =(S42/$B42)*100 -> 13.465519 | U42: 33062 | V42: =(U42/$B42)*100 -> 5.7752539 | W42: 19712 | X42: =(W42/$B42)*100 -> 3.4432824 | Y42: 252116 | Z42: =(Y42/$B42)*100 -> 44.039499 | AA42: 39070 | AB42: =(AA42/$B42)*100 -> 6.8247283
A43: Region V - Bicol Region | B43: 819370 | C43: 84753 | D43: =(C43/$B43)*100 -> 10.343679 | E43: 19597 | F43: =(E43/$B43)*100 -> 2.3917156 | G43: 15005 | H43: =(G43/$B43)*100 -> 1.831285 | I43: 8246 | J43: =(I43/$B43)*100 -> 1.006383 | K43: 168115 | L43: =(K43/$B43)*100 -> 20.517593 | M43: 532441 | N43: =(M43/$B43)*100 -> 64.981754 | O43: 335018 | P43: =(O43/$B43)*100 -> 40.887267 | Q43: 55475 | R43: =(Q43/$B43)*100 -> 6.7704456 | S43: 95900 | T43: =(S43/$B43)*100 -> 11.704114 | U43: 46972 | V43: =(U43/$B43)*100 -> 5.7326971 | W43: 79361 | X43: =(W43/$B43)*100 -> 9.6856121 | Y43: 156222 | Z43: =(Y43/$B43)*100 -> 19.066112 | AA43: 3786 | AB43: =(AA43/$B43)*100 -> 0.46206232
A44: Region VI - Western Visayas | B44: 1211918 | C44: 134547 | D44: =(C44/$B44)*100 -> 11.101989 | E44: 55786 | F44: =(E44/$B44)*100 -> 4.6031167 | G44: 30672 | H44: =(G44/$B44)*100 -> 2.5308643 | I44: 21117 | J44: =(I44/$B44)*100 -> 1.7424446 | K44: 309587 | L44: =(K44/$B44)*100 -> 25.54521 | M44: 550657 | N44: =(M44/$B44)*100 -> 45.43682 | O44: 526057 | P44: =(O44/$B44)*100 -> 43.40698 | Q44: 171555 | R44: =(Q44/$B44)*100 -> 14.155661 | S44: 165805 | T44: =(S44/$B44)*100 -> 13.681206 | U44: 82216 | V44: =(U44/$B44)*100 -> 6.7839573 | W44: 126598 | X44: =(W44/$B44)*100 -> 10.446086 | Y44: 361017 | Z44: =(Y44/$B44)*100 -> 29.788897 | AA44: 616 | AB44: =(AA44/$B44)*100 -> 0.050828521
A45: Region VII - Central Visayas | B45: 1209204 | C45: 57818 | D45: =(C45/$B45)*100 -> 4.7814926 | E45: 11951 | F45: =(E45/$B45)*100 -> 0.98833613 | G45: 19068 | H45: =(G45/$B45)*100 -> 1.5769051 | I45: 23431 | J45: =(I45/$B45)*100 -> 1.937721 | K45: 296922 | L45: =(K45/$B45)*100 -> 24.555162 | M45: 807977 | N45: =(M45/$B45)*100 -> 66.818916 | O45: 625980 | P45: =(O45/$B45)*100 -> 51.76794 | Q45: 103846 | R45: =(Q45/$B45)*100 -> 8.5879637 | S45: 165758 | T45: =(S45/$B45)*100 -> 13.708026 | U45: 78070 | V45: =(U45/$B45)*100 -> 6.4563134 | W45: 101673 | X45: =(W45/$B45)*100 -> 8.4082587 | Y45: 462836 | Z45: =(Y45/$B45)*100 -> 38.276089 | AA45: 37546 | AB45: =(AA45/$B45)*100 -> 3.1050178
A46: Region VIII - Eastern Visayas | B46: 790040 | C46: 70358 | D46: =(C46/$B46)*100 -> 8.905625 | E46: 29155 | F46: =(E46/$B46)*100 -> 3.6903195 | G46: 29457 | H46: =(G46/$B46)*100 -> 3.7285454 | I46: 27525 | J46: =(I46/$B46)*100 -> 3.4840008 | K46: 242991 | L46: =(K46/$B46)*100 -> 30.756797 | M46: 420839 | N46: =(M46/$B46)*100 -> 53.268062 | O46: 399990 | P46: =(O46/$B46)*100 -> 50.629082 | Q46: 84565 | R46: =(Q46/$B46)*100 -> 10.703888 | S46: 107745 | T46: =(S46/$B46)*100 -> 13.637917 | U46: 61624 | V46: =(U46/$B46)*100 -> 7.8001114 | W46: 37907 | X46: =(W46/$B46)*100 -> 4.7981115 | Y46: 149969 | Z46: =(Y46/$B46)*100 -> 18.982457 | AA46: 38751 | AB46: =(AA46/$B46)*100 -> 4.9049415
... A52: Bangsamoro Autonomous Region in Muslim Mindanao | B52: 611371 | C52: 172662 | D52: =(C52/$B52)*100 -> 28.241771 | E52: 43539 | F52: =(E52/$B52)*100 -> 7.121535 | G52: 38736 | H52: =(G52/$B52)*100 -> 6.3359237 | I52: 23094 | J52: =(I52/$B52)*100 -> 3.7774118 | K52: 129275 | L52: =(K52/$B52)*100 -> 21.145098 | M52: 234296 | N52: =(M52/$B52)*100 -> 38.323048 | O52: 228055 | P52: =(O52/$B52)*100 -> 37.302227 | Q52: 136496 | R52: =(Q52/$B52)*100 -> 22.326214 | S52: 61850 | T52: =(S52/$B52)*100 -> 10.116607 | U52: 31038 | V52: =(U52/$B52)*100 -> 5.0767864 | W52: 50069 | X52: =(W52/$B52)*100 -> 8.1896263 | Y52: 88848 | Z52: =(Y52/$B52)*100 -> 14.532583 | AA52: 22961 | AB52: =(AA52/$B52)*100 -> 3.7556574
A55: Notes:
A56: Details may not add up to totals due to rounding.
A57: p Estimates are preliminary and may change
A58: r Revised
A59: Source of data: Philippine Statistics Authority, 2024 National Information and Communications Technology Household Survey.

Sheet i_C21-22
A1: BACK TO LIST
A2: Table #. Number and Proportion of Individuals Who Have Not Used the Internet by Reason for Not Using the Internet and Region, Philippines: 2019 and 2024p
A4: Region | B4: 2019
B5: Individuals Who Have Not Used the Internet | C5: Reasons for Not Using the Internet
C6: Internet Service is Not Available in the Area | E6: Privacy or Security Concerns | G6: Exposure to Harmful Content | I6: Not Allowed to Use the Internet | K6: High Cost of Internet Subscription | M6: High Cost of Equipment | O6: Poor Quality and Speed | Q6: Do Not Know How to Use It | S6: Don't Know What Internet Is | U6: Do Not Need the Internet | W6: Others
C7: Number | D7: Proportion | E7: Number | F7: Proportion | G7: Number | H7: Proportion | I7: Number | J7: Proportion | K7: Number | L7: Proportion | M7: Number | N7: Proportion | O7: Number | P7: Proportion | Q7: Number | R7: Proportion | S7: Number | T7: Proportion | U7: Number | V7: Proportion | W7: Number | X7: Proportion
A9: PHILIPPINES | B9: 23929404 | C9: 5462074.9 | D9: =(C9/$B9)*100 -> 22.825787 | E9: 1061636.9 | F9: =(E9/$B9)*100 -> 4.4365374 | G9: 168167.41 | H9: =(G9/$B9)*100 -> 0.70276472 | I9: 623151 | J9: =(I9/$B9)*100 -> 2.6041225 | K9: 6937271.8 | L9: =(K9/$B9)*100 -> 28.990575 | M9: 5348057.7 | N9: =(M9/$B9)*100 -> 22.349314 | O9: 1880380.4 | P9: =(O9/$B9)*100 -> 7.8580329 | Q9: 9373010.1 | R9: =(Q9/$B9)*100 -> 39.169426 | S9: 2865350.1 | T9: =(S9/$B9)*100 -> 11.974181 | U9: 3131132.4 | V9: =(U9/$B9)*100 -> 13.084874 | W9: 630499.08 | X9: =(W9/$B9)*100 -> 2.6348299
A10: National Capital Region | B10: 2255650 | C10: 257314.25 | D10: =(C10/$B10)*100 -> 11.407543 | E10: 287209.44 | F10: =(E10/$B10)*100 -> 12.73289 | G10: 50416.86 | H10: =(G10/$B10)*100 -> 2.2351366 | I10: 84667.479 | J10: =(I10/$B10)*100 -> 3.7535734 | K10: 573102.68 | L10: =(K10/$B10)*100 -> 25.407429 | M10: 308135.22 | N10: =(M10/$B10)*100 -> 13.660595 | O10: 48992.856 | P10: =(O10/$B10)*100 -> 2.1720061 | Q10: 728491.46 | R10: =(Q10/$B10)*100 -> 32.296299 | S10: 207791.17 | T10: =(S10/$B10)*100 -> 9.2120307 | U10: 532896.84 | V10: =(U10/$B10)*100 -> 23.624979 | W10: 46083.757 | X10: =(W10/$B10)*100 -> 2.0430367
A11: Cordillera Administrative Region | B11: 317640 | C11: 86439.138 | D11: =(C11/$B11)*100 -> 27.212926 | E11: 787.22339 | F11: =(E11/$B11)*100 -> 0.24783509 | G11: 917.21726 | H11: =(G11/$B11)*100 -> 0.28876 | I11: 678.37274 | J11: =(I11/$B11)*100 -> 0.21356653 | K11: 48923.644 | L11: =(K11/$B11)*100 -> 15.40223 | M11: 33557.566 | N11: =(M11/$B11)*100 -> 10.564654 | O11: 59966.079 | P11: =(O11/$B11)*100 -> 18.87863 | Q11: 128755.22 | R11: =(Q11/$B11)*100 -> 40.534952 | S11: 16683.406 | T11: =(S11/$B11)*100 -> 5.2523 | U11: 43741.956 | V11: =(U11/$B11)*100 -> 13.770922 | W11: 6234.2282 | X11: =(W11/$B11)*100 -> 1.962671
A12: Region I - Ilocos Region | B12: 1239098 | C12: 201372.49 | D12: =(C12/$B12)*100 -> 16.251538 | E12: 25609.059 | F12: =(E12/$B12)*100 -> 2.0667501 | G12: 1979.9587 | H12: =(G12/$B12)*100 -> 0.15979032 | I12: 40857.105 | J12: =(I12/$B12)*100 -> 3.2973263 | K12: 572477.61 | L12: =(K12/$B12)*100 -> 46.201157 | M12: 248486.59 | N12: =(M12/$B12)*100 -> 20.053829 | O12: 106675.72 | P12: =(O12/$B12)*100 -> 8.6091431 | Q12: 511156.4 | R12: =(Q12/$B12)*100 -> 41.252298 | S12: 116120.39 | T12: =(S12/$B12)*100 -> 9.3713645 | U12: 134469.38 | V12: =(U12/$B12)*100 -> 10.852199 | W12: 92806.62 | X12: =(W12/$B12)*100 -> 7.4898531
A13: Region II - Cagayan Valley | B13: 1110591 | C13: 243158.09 | D13: =(C13/$B13)*100 -> 21.894477 | E13: 18342.608 | F13: =(E13/$B13)*100 -> 1.6516078 | G13: 3878.9804 | H13: =(G13/$B13)*100 -> 0.34927173 | I13: 19571.515 | J13: =(I13/$B13)*100 -> 1.7622612 | K13: 234458.44 | L13: =(K13/$B13)*100 -> 21.111141 | M13: 331811.11 | N13: =(M13/$B13)*100 -> 29.876985 | O13: 157595.58 | P13: =(O13/$B13)*100 -> 14.190244 | Q13: 466514.17 | R13: =(Q13/$B13)*100 -> 42.005938 | S13: 180920.77 | T13: =(S13/$B13)*100 -> 16.290495 | U13: 15450.894 | V13: =(U13/$B13)*100 -> 1.3912317 | W13: 20980.732 | X13: =(W13/$B13)*100 -> 1.8891502
A14: Region III - Central Luzon | B14: 2721073 | C14: 401062.07 | D14: =(C14/$B14)*100 -> 14.739115 | E14: 11259.496 | F14: =(E14/$B14)*100 -> 0.41378884 | G14: 3764.6849 | H14: =(G14/$B14)*100 -> 0.13835295 | I14: 91273.256 | J14: =(I14/$B14)*100 -> 3.3543112 | K14: 1348866.2 | L14: =(K14/$B14)*100 -> 49.571115 | M14: 1233649.7 | N14: =(M14/$B14)*100 -> 45.336883 | O14: 212065.1 | P14: =(O14/$B14)*100 -> 7.7934365 | Q14: 1055071.2 | R14: =(Q14/$B14)*100 -> 38.774085 | S14: 458685.77 | T14: =(S14/$B14)*100 -> 16.856797 | U14: 535148.1 | V14: =(U14/$B14)*100 -> 19.666804 | W14: 4534.1358 | X14: =(W14/$B14)*100 -> 0.16663044
A15: Region IV-A - CALABARZON | B15: 2664358 | C15: 609629.63 | D15: =(C15/$B15)*100 -> 22.88092 | E15: 572819.23 | F15: =(E15/$B15)*100 -> 21.499334 | G15: 53595.713 | H15: =(G15/$B15)*100 -> 2.0115808 | I15: 133557.99 | J15: =(I15/$B15)*100 -> 5.0127643 | K15: 765125.38 | L15: =(K15/$B15)*100 -> 28.717063 | M15: 266310.49 | N15: =(M15/$B15)*100 -> 9.9952967 | O15: 43288.026 | P15: =(O15/$B15)*100 -> 1.6247076 | Q15: 718299.9 | R15: =(Q15/$B15)*100 -> 26.959587 | S15: 215577.94 | T15: =(S15/$B15)*100 -> 8.0911776 | U15: 405378.95 | V15: =(U15/$B15)*100 -> 15.214883 | W15: 191879.39 | X15: =(W15/$B15)*100 -> 7.2017122
A16: MIMAROPA Region | B16: 772686 | C16: 106798.07 | D16: =(C16/$B16)*100 -> 13.821665 | E16: 215.30618 | F16: =(E16/$B16)*100 -> 0.027864641 | G16: 0 | H16: =(G16/$B16)*100 -> 0 | I16: 68300.699 | J16: =(I16/$B16)*100 -> 8.8393862 | K16: 203327.76 | L16: =(K16/$B16)*100 -> 26.31441 | M16: 174719.46 | N16: =(M16/$B16)*100 -> 22.611961 | O16: 42620.103 | P16: =(O16/$B16)*100 -> 5.5158374 | Q16: 317148.18 | R16: =(Q16/$B16)*100 -> 41.044898 | S16: 88597.411 | T16: =(S16/$B16)*100 -> 11.46616 | U16: 181769.01 | V16: =(U16/$B16)*100 -> 23.524304 | W16: 94121.096 | X16: =(W16/$B16)*100 -> 12.181028
A17: Region V - Bicol Region | B17: 1563470 | C17: 734127.3 | D17: =(C17/$B17)*100 -> 46.954998 | E17: 24317.897 | F17: =(E17/$B17)*100 -> 1.5553799 | G17: 17107.026 | H17: =(G17/$B17)*100 -> 1.0941704 | I17: 31999.43 | J17: =(I17/$B17)*100 -> 2.0466929 | K17: 216529.73 | L17: =(K17/$B17)*100 -> 13.849305 | M17: 198437.87 | N17: =(M17/$B17)*100 -> 12.692145 | O17: 65551.482 | P17: =(O17/$B17)*100 -> 4.192692 | Q17: 372693.62 | R17: =(Q17/$B17)*100 -> 23.837594 | S17: 202305.53 | T17: =(S17/$B17)*100 -> 12.939521 | U17: 277610.16 | V17: =(U17/$B17)*100 -> 17.756027 | W17: 25856.746 | X17: =(W17/$B17)*100 -> 1.6538051
A18: Region VI - Western Visayas | B18: 1831734 | C18: 612442.34 | D18: =(C18/$B18)*100 -> 33.435113 | E18: 30101.644 | F18: =(E18/$B18)*100 -> 1.6433414 | G18: 2672.9239 | H18: =(G18/$B18)*100 -> 0.14592315 | I18: 4196.0688 | J18: =(I18/$B18)*100 -> 0.22907632 | K18: 689150.01 | L18: =(K18/$B18)*100 -> 37.622821 | M18: 253651.5 | N18: =(M18/$B18)*100 -> 13.847617 | O18: 234620.24 | P18: =(O18/$B18)*100 -> 12.808642 | Q18: 641018.41 | R18: =(Q18/$B18)*100 -> 34.995169 | S18: 222509.76 | T18: =(S18/$B18)*100 -> 12.147493 | U18: 52816.261 | V18: =(U18/$B18)*100 -> 2.8834023 | W18: 0 | X18: =(W18/$B18)*100 -> 0
A19: Region VII - Central Visayas | B19: 1564597 | C19: 35633.963 | D19: =(C19/$B19)*100 -> 2.277517 | E19: 540.55902 | F19: =(E19/$B19)*100 -> 0.034549409 | G19: 253.60223 | H19: =(G19/$B19)*100 -> 0.016208789 | I19: 19701.51 | J19: =(I19/$B19)*100 -> 1.2592067 | K19: 473701.55 | L19: =(K19/$B19)*100 -> 30.276266 | M19: 321596.19 | N19: =(M19/$B19)*100 -> 20.55457 | O19: 61191.55 | P19: =(O19/$B19)*100 -> 3.9110103 | Q19: 874131.28 | R19: =(Q19/$B19)*100 -> 55.86942 | S19: 81917.993 | T19: =(S19/$B19)*100 -> 5.2357248 | U19: 154298.68 | V19: =(U19/$B19)*100 -> 9.8618799 | W19: 13248.425 | X19: =(W19/$B19)*100 -> 0.84676275
A20: Region VIII - Eastern Visayas | B20: 1278925 | C20: 168839.79 | D20: =(C20/$B20)*100 -> 13.201696 | E20: 8603.1405 | F20: =(E20/$B20)*100 -> 0.6726853 | G20: 1391.4937 | H20: =(G20/$B20)*100 -> 0.10880182 | I20: 16979.733 | J20: =(I20/$B20)*100 -> 1.3276567 | K20: 207066.19 | L20: =(K20/$B20)*100 -> 16.190644 | M20: 327991.83 | N20: =(M20/$B20)*100 -> 25.6459 | O20: 109407.55 | P20: =(O20/$B20)*100 -> 8.5546494 | Q20: 764704.81 | R20: =(Q20/$B20)*100 -> 59.79278 | S20: 360750.21 | T20: =(S20/$B20)*100 -> 28.2073 | U20: 46134.966 | V20: =(U20/$B20)*100 -> 3.6073238 | W20: 51104.965 | X20: =(W20/$B20)*100 -> 3.9959314
... A26: Bangsamoro Autonomous Region in Muslim Mindanao | B26: 863927 | C26: 429205.62 | D26: =(C26/$B26)*100 -> 49.680774 | E26: 7510.8691 | F26: =(E26/$B26)*100 -> 0.86938701 | G26: 1019.4633 | H26: =(G26/$B26)*100 -> 0.11800341 | I26: 4219.7588 | J26: =(I26/$B26)*100 -> 0.48843927 | K26: 20831.674 | L26: =(K26/$B26)*100 -> 2.4112771 | M26: 309810.63 | N26: =(M26/$B26)*100 -> 35.860742 | O26: 247961.53 | P26: =(O26/$B26)*100 -> 28.701677 | Q26: 226569.61 | R26: =(Q26/$B26)*100 -> 26.22555 | S26: 152603.34 | T26: =(S26/$B26)*100 -> 17.663916 | U26: 9855.7727 | V26: =(U26/$B26)*100 -> 1.1408108 | W26: 26042.966 | X26: =(W26/$B26)*100 -> 3.0144869
A29: Region | B29: 2024
B30: Individuals Who Have Not Used the Internet | C30: Reasons for Not Using the Internet
C31: Internet Service is Not Available in the Area | E31: Privacy or Security Concerns | G31: Exposure to Harmful Content | I31: Not Allowed to Use the Internet | K31: High Cost of Internet Subscription | M31: High Cost of Equipment | O31: Poor Quality and Speed | Q31: Do Not Know How to Use It | S31: Don't Know What Internet Is | U31: Do Not Need the Internet | W31: Others
C32: Number | D32: Proportion | E32: Number | F32: Proportion | G32: Number | H32: Proportion | I32: Number | J32: Proportion | K32: Number | L32: Proportion | M32: Number | N32: Proportion | O32: Number | P32: Proportion | Q32: Number | R32: Proportion | S32: Number | T32: Proportion | U32: Number | V32: Proportion | W32: Number | X32: Proportion
A34: PHILIPPINES | B34: 29926147 | C34: 4805862 | D34: =(C34/$B34)*100 -> 16.059074 | E34: 1890427 | F34: =(E34/$B34)*100 -> 6.3169743 | G34: 1300318 | H34: =(G34/$B34)*100 -> 4.3450899 | I34: 1988431 | J34: =(I34/$B34)*100 -> 6.6444604 | K34: 12468302 | L34: =(K34/$B34)*100 -> 41.663573 | M34: 9940860 | N34: =(M34/$B34)*100 -> 33.217975 | O34: 3733277 | P34: =(O34/$B34)*100 -> 12.474967 | Q34: 8833623 | R34: =(Q34/$B34)*100 -> 29.518077 | S34: 3412397 | T34: =(S34/$B34)*100 -> 11.402728 | U34: 4468962 | V34: =(U34/$B34)*100 -> 14.933302 | W34: 2213443 | X34: =(W34/$B34)*100 -> 7.3963514
A35: National Capital Region | B35: 2471172 | C35: 250889 | D35: =(C35/$B35)*100 -> 10.152632 | E35: 424951 | F35: =(E35/$B35)*100 -> 17.196334 | G35: 282013 | H35: =(G35/$B35)*100 -> 11.412115 | I35: 281605 | J35: =(I35/$B35)*100 -> 11.395605 | K35: 1211296 | L35: =(K35/$B35)*100 -> 49.017066 | M35: 712552 | N35: =(M35/$B35)*100 -> 28.834577 | O35: 192203 | P35: =(O35/$B35)*100 -> 7.7778075 | Q35: 365289 | R35: =(Q35/$B35)*100 -> 14.782014 | S35: 143003 | T35: =(S35/$B35)*100 -> 5.7868493 | U35: 365608 | V35: =(U35/$B35)*100 -> 14.794923 | W35: 81842 | X35: =(W35/$B35)*100 -> 3.3118698
A36: Cordillera Administrative Region | B36: 421700 | C36: 91790 | D36: =(C36/$B36)*100 -> 21.766659 | E36: 16321 | F36: =(E36/$B36)*100 -> 3.8702869 | G36: 16597 | H36: =(G36/$B36)*100 -> 3.9357363 | I36: 27902 | J36: =(I36/$B36)*100 -> 6.6165521 | K36: 105656 | L36: =(K36/$B36)*100 -> 25.054778 | M36: 147627 | N36: =(M36/$B36)*100 -> 35.007588 | O36: 58995 | P36: =(O36/$B36)*100 -> 13.989803 | Q36: 175429 | R36: =(Q36/$B36)*100 -> 41.600427 | S36: 75894 | T36: =(S36/$B36)*100 -> 17.997154 | U36: 43189 | V36: =(U36/$B36)*100 -> 10.241641 | W36: 7990 | X36: =(W36/$B36)*100 -> 1.8947119
A37: Region I - Ilocos Region | B37: 1128880 | C37: 85478 | D37: =(C37/$B37)*100 -> 7.5719297 | E37: 36944 | F37: =(E37/$B37)*100 -> 3.2726242 | G37: 10589 | H37: =(G37/$B37)*100 -> 0.93800935 | I37: 158034 | J37: =(I37/$B37)*100 -> 13.999185 | K37: 353502 | L37: =(K37/$B37)*100 -> 31.3144 | M37: 264521 | N37: =(M37/$B37)*100 -> 23.432163 | O37: 59703 | P37: =(O37/$B37)*100 -> 5.2886932 | Q37: 484755 | R37: =(Q37/$B37)*100 -> 42.941234 | S37: 245193 | T37: =(S37/$B37)*100 -> 21.720023 | U37: 166949 | V37: =(U37/$B37)*100 -> 14.788906 | W37: 123321 | X37: =(W37/$B37)*100 -> 10.92419
A38: Region II - Cagayan Valley | B38: 765878 | C38: 121723 | D38: =(C38/$B38)*100 -> 15.893262 | E38: 27603 | F38: =(E38/$B38)*100 -> 3.6040988 | G38: 25351 | H38: =(G38/$B38)*100 -> 3.3100572 | I38: 92271 | J38: =(I38/$B38)*100 -> 12.047741 | K38: 323956 | L38: =(K38/$B38)*100 -> 42.298643 | M38: 175331 | N38: =(M38/$B38)*100 -> 22.892811 | O38: 65905 | P38: =(O38/$B38)*100 -> 8.6051564 | Q38: 342416 | R38: =(Q38/$B38)*100 -> 44.708948 | S38: 141156 | T38: =(S38/$B38)*100 -> 18.430612 | U38: 97518 | V38: =(U38/$B38)*100 -> 12.732837 | W38: 91199 | X38: =(W38/$B38)*100 -> 11.907771
A39: Region III - Central Luzon | B39: 2781894 | C39: 392579 | D39: =(C39/$B39)*100 -> 14.111932 | E39: 118739 | F39: =(E39/$B39)*100 -> 4.2682791 | G39: 110313 | H39: =(G39/$B39)*100 -> 3.9653919 | I39: 194342 | J39: =(I39/$B39)*100 -> 6.9859599 | K39: 938908 | L39: =(K39/$B39)*100 -> 33.750675 | M39: 979069 | N39: =(M39/$B39)*100 -> 35.194332 | O39: 324809 | P39: =(O39/$B39)*100 -> 11.675822 | Q39: 847296 | R39: =(Q39/$B39)*100 -> 30.457523 | S39: 365285 | T39: =(S39/$B39)*100 -> 13.130802 | U39: 385523 | V39: =(U39/$B39)*100 -> 13.858292 | W39: 332668 | X39: =(W39/$B39)*100 -> 11.958328
A40: Region IV-A - CALABARZON | B40: 4006369 | C40: 1014155 | D40: =(C40/$B40)*100 -> 25.313569 | E40: 268910 | F40: =(E40/$B40)*100 -> 6.7120627 | G40: 178567 | H40: =(G40/$B40)*100 -> 4.4570782 | I40: 226049 | J40: =(I40/$B40)*100 -> 5.6422411 | K40: 2228146 | L40: =(K40/$B40)*100 -> 55.615097 | M40: 952208 | N40: =(M40/$B40)*100 -> 23.767356 | O40: 277579 | P40: =(O40/$B40)*100 -> 6.9284432 | Q40: 757094 | R40: =(Q40/$B40)*100 -> 18.897261 | S40: 141671 | T40: =(S40/$B40)*100 -> 3.5361446 | U40: 508475 | V40: =(U40/$B40)*100 -> 12.691667 | W40: 249121 | X40: =(W40/$B40)*100 -> 6.2181242
A41: MIMAROPA Region | B41: 923877 | C41: 194297 | D41: =(C41/$B41)*100 -> 21.030613 | E41: 10451 | F41: =(E41/$B41)*100 -> 1.1312112 | G41: 9051 | H41: =(G41/$B41)*100 -> 0.97967587 | I41: 58135 | J41: =(I41/$B41)*100 -> 6.2925043 | K41: 131805 | L41: =(K41/$B41)*100 -> 14.266509 | M41: 172241 | N41: =(M41/$B41)*100 -> 18.643283 | O41: 147286 | P41: =(O41/$B41)*100 -> 15.942165 | Q41: 356425 | R41: =(Q41/$B41)*100 -> 38.57927 | S41: 124047 | T41: =(S41/$B41)*100 -> 13.426787 | U41: 59988 | V41: =(U41/$B41)*100 -> 6.4930721 | W41: 186506 | X41: =(W41/$B41)*100 -> 20.187319
A42: Region V - Bicol Region | B42: 1790063 | C42: 165153 | D42: =(C42/$B42)*100 -> 9.2260999 | E42: 127623 | F42: =(E42/$B42)*100 -> 7.1295256 | G42: 57718 | H42: =(G42/$B42)*100 -> 3.2243558 | I42: 106809 | J42: =(I42/$B42)*100 -> 5.9667732 | K42: 813182 | L42: =(K42/$B42)*100 -> 45.427563 | M42: 662919 | N42: =(M42/$B42)*100 -> 37.033278 | O42: 130714 | P42: =(O42/$B42)*100 -> 7.3022011 | Q42: 562679 | R42: =(Q42/$B42)*100 -> 31.433475 | S42: 202775 | T42: =(S42/$B42)*100 -> 11.327814 | U42: 324085 | V42: =(U42/$B42)*100 -> 18.10467 | W42: 127728 | X42: =(W42/$B42)*100 -> 7.1353913
A43: Region VI - Western Visayas | B43: 2533168 | C43: 312671 | D43: =(C43/$B43)*100 -> 12.343082 | E43: 240613 | F43: =(E43/$B43)*100 -> 9.4985015 | G43: 129789 | H43: =(G43/$B43)*100 -> 5.1235844 | I43: 172203 | J43: =(I43/$B43)*100 -> 6.7979305 | K43: 836091 | L43: =(K43/$B43)*100 -> 33.005746 | M43: 875144 | N43: =(M43/$B43)*100 -> 34.547413 | O43: 382414 | P43: =(O43/$B43)*100 -> 15.096275 | Q43: 759958 | R43: =(Q43/$B43)*100 -> 30.0003 | S43: 356479 | T43: =(S43/$B43)*100 -> 14.072458 | U43: 595690 | V43: =(U43/$B43)*100 -> 23.515614 | W43: 79743 | X43: =(W43/$B43)*100 -> 3.1479554
A44: Region VII - Central Visayas | B44: 2146223 | C44: 147347 | D44: =(C44/$B44)*100 -> 6.8654096 | E44: 70301 | F44: =(E44/$B44)*100 -> 3.2755683 | G44: 58308 | H44: =(G44/$B44)*100 -> 2.7167727 | I44: 123331 | J44: =(I44/$B44)*100 -> 5.7464206 | K44: 1037670 | L44: =(K44/$B44)*100 -> 48.348657 | M44: 893480 | N44: =(M44/$B44)*100 -> 41.630343 | O44: 213764 | P44: =(O44/$B44)*100 -> 9.9600088 | Q44: 925098 | R44: =(Q44/$B44)*100 -> 43.103536 | S44: 292267 | T44: =(S44/$B44)*100 -> 13.617737 | U44: 408468 | V44: =(U44/$B44)*100 -> 19.031946 | W44: 169329 | X44: =(W44/$B44)*100 -> 7.8896275
A45: Region VIII - Eastern Visayas | B45: 1293489 | C45: 114035 | D45: =(C45/$B45)*100 -> 8.8160781 | E45: 46077 | F45: =(E45/$B45)*100 -> 3.5622259 | G45: 41074 | H45: =(G45/$B45)*100 -> 3.1754425 | I45: 115205 | J45: =(I45/$B45)*100 -> 8.9065311 | K45: 396871 | L45: =(K45/$B45)*100 -> 30.682209 | M45: 522258 | N45: =(M45/$B45)*100 -> 40.375914 | O45: 155982 | P45: =(O45/$B45)*100 -> 12.059012 | Q45: 569291 | R45: =(Q45/$B45)*100 -> 44.012048 | S45: 261714 | T45: =(S45/$B45)*100 -> 20.233183 | U45: 141361 | V45: =(U45/$B45)*100 -> 10.928659 | W45: 177593 | X45: =(W45/$B45)*100 -> 13.729765
... A51: Bangsamoro Autonomous Region in Muslim Mindanao | B51: 2249632 | C51: 773452 | D51: =(C51/$B51)*100 -> 34.381268 | E51: 253589 | F51: =(E51/$B51)*100 -> 11.272466 | G51: 246281 | H51: =(G51/$B51)*100 -> 10.947613 | I51: 137777 | J51: =(I51/$B51)*100 -> 6.1244239 | K51: 731265 | L51: =(K51/$B51)*100 -> 32.505983 | M51: 848734 | N51: =(M51/$B51)*100 -> 37.727682 | O51: 708411 | P51: =(O51/$B51)*100 -> 31.490084 | Q51: 539897 | R51: =(Q51/$B51)*100 -> 23.999347 | S51: 253606 | T51: =(S51/$B51)*100 -> 11.273222 | U51: 384756 | V51: =(U51/$B51)*100 -> 17.103064 | W51: 157958 | X51: =(W51/$B51)*100 -> 7.021504
A54: Notes:
A55: Details may not add up to totals due to rounding.
A56: p Estimates are preliminary and may change
A57: Source of data: Philippine Statistics Authority, 2024 National Information and Communications Technology Household Survey.

Sheet C23
A1: BACK TO LIST
A2: Table #. Number and Proportion of Households with Access to Television by Region, Philippines: 2019 and 2024p
A4: Region | B4: 2019 | E4: 2024
B5: Total Households | C5: With Access to Television | E5: Total Households | F5: With Access to Television
C7: Number | D7: Proportion | F7: Number | G7: Proportion
A9: PHILIPPINES | B9: ='Estimated Totals'!B7 -> 23360960 | C9: 19330080 | D9: =(C9/$B9)*100 -> 82.74523 | E9: 27793884 | F9: 17680057 | G9: =(F9/$E9)*100 -> 63.611322
A10: National Capital Region | B10: ='Estimated Totals'!B8 -> 3009545 | C10: 2829350 | D10: =(C10/$B10)*100 -> 94.01255 | E10: 3667731 | F10: 2833219 | G10: =(F10/$E10)*100 -> 77.247186
A11: Cordillera Administrative Region | B11: ='Estimated Totals'!B9 -> 388188 | C11: 315885 | D11: =(C11/$B11)*100 -> 81.374231 | E11: 468413 | F11: 295167 | G11: =(F11/$E11)*100 -> 63.014263
A12: Region I - Ilocos Region | B12: ='Estimated Totals'!B10 -> 1250337 | C12: 1090157 | D12: =(C12/$B12)*100 -> 87.189054 | E12: 1316881 | F12: 886863 | G12: =(F12/$E12)*100 -> 67.345721
A13: Region II - Cagayan Valley | B13: ='Estimated Totals'!B11 -> 855893 | C13: 713038 | D13: =(C13/$B13)*100 -> 83.309245 | E13: 934252 | F13: 586642 | G13: =(F13/$E13)*100 -> 62.792694
A14: Region III - Central Luzon | B14: ='Estimated Totals'!B12 -> 2823200 | C14: 2668170 | D14: =(C14/$B14)*100 -> 94.508714 | E14: 3161851 | F14: 2225993 | G14: =(F14/$E14)*100 -> 70.401578
A15: Region IV-A - CALABARZON | B15: ='Estimated Totals'!B13 -> 3486186 | C15: 3217334 | D15: =(C15/$B15)*100 -> 92.288076 | E15: 4369198 | F15: 3196584 | G15: =(F15/$E15)*100 -> 73.161802
A16: MIMAROPA Region | B16: ='Estimated Totals'!B14 -> 686916 | C16: 501164 | D16: =(C16/$B16)*100 -> 72.958557 | E16: 828498 | F16: 469527 | G16: =(F16/$E16)*100 -> 56.672074
A17: Region V - Bicol Region | B17: ='Estimated Totals'!B15 -> 1030986 | C17: 774635 | D17: =(C17/$B17)*100 -> 75.135356 | E17: 1384033 | F17: 798540 | G17: =(F17/$E17)*100 -> 57.696601
A18: Region VI - Western Visayas | B18: ='Estimated Totals'!B16 -> 1705556 | C18: 1388172 | D18: =(C18/$B18)*100 -> 81.391171 | E18: 2040922 | F18: 1303510 | G18: =(F18/$E18)*100 -> 63.868683
A19: Region VII - Central Visayas | B19: ='Estimated Totals'!B17 -> 1820052 | C19: 1326302 | D19: =(C19/$B19)*100 -> 72.871654 | E19: 2077216 | F19: 1195707 | G19: =(F19/$E19)*100 -> 57.562959
A20: Region VIII - Eastern Visayas | B20: ='Estimated Totals'!B18 -> 1042723 | C20: 732218 | D20: =(C20/$B20)*100 -> 70.221718 | E20: 1200913 | F20: 677361 | G20: =(F20/$E20)*100 -> 56.403836
